Workbook
Name Product: 'Product List'!$A:$A
Name Products: #REF!
Name Family: 'Product Families'!$A:$A
Name Names: Personnel!$A$10:$A$32
Name ManualSheet1: 'Production Sheet - Manual'!$A$1:$I$77
Name ManualSheet2: 'Production Sheet - Manual'!$J$1:$AK$97

Sheet Wholesale Pricing
H1: Part 1 | I1: Part 2 | J1: Part 3 | K1: Part 4 | L1: Part 5 | M1: Part 1 Calcs | R1: Part 2 Calcs | W1: Part 3 Calcs | AB1: Part 4 Calcs | AG1: Part 5 Calcs
A2: Family Code | B2: Wholesale Price | C2: Pack Quantity | D2: Single Item Price | E2: Total from Target Amount | G2: Notes | H2: Code | I2: Code | J2: Code | K2: Code | L2: Code | M2: Target Rate | N2: Amount | O2: Single Amount | P2: % | Q2: Wholesale Calc | R2: Target Rate | S2: Amount | T2: Single Amount | U2: % | V2: Wholesale Calc | W2: Target Rate | X2: Amount | Y2: Single Amount | Z2: % | AA2: Wholesale Calc | AB2: Target Rate | AC2: Amount | AD2: Single Amount | AE2: % | AF2: Wholesale Calc | AG2: Target Rate | AH2: Amount | AI2: Single Amount | AJ2: % | AK2: Wholesale Calc
A3: ABB1 | B3: 2.64 | C3: 8 | D3: =iferror(B3/C3,"") -> 0.33 | E3: =sum(O3+T3+Y3+AD3+AI3) -> 0.08625 | H3: ABB1 | I3: ABBP | M3: {=iferror(xlookup($H3,'Product Families'!$A:$A,'Product Families'!$P:$P),"")} -> 0.05 | N3: {=iferror(xlookup($H3,'Product Families'!$A:$A,'Product Families'!$Q:$Q),"")} -> 1 | O3: =iferror(M3/N3,"") -> 0.05 | P3: =iferror(O3/$E3,"") -> 0.57971014 | Q3: =round($D3*P3,2) -> 0.19 | R3: {=iferror(xlookup($I3,'Product Families'!$A:$A,'Product Families'!$P:$P),"")} -> 0.29 | S3: {=iferror(xlookup($I3,'Product Families'!$A:$A,'Product Families'!$Q:$Q),"")} -> 8 | T3: =iferror(R3/S3,"") -> 0.03625 | U3: =iferror(T3/$E3,"") -> 0.42028986 | V3: =round($D3*U3,2) -> 0.14 | W3: {=iferror(xlookup($J3,'Product Families'!$A:$A,'Product Families'!$P:$P),"")} | X3: {=iferror(xlookup($J3,'Product Families'!$A:$A,'Product Families'!$Q:$Q),"")} | Y3: =iferror(W3/X3,"") | Z3: =iferror(Y3/$E3,"") -> 0 | AA3: =round($D3*Z3,2) -> 0 | AB3: {=iferror(xlookup($K3,'Product Families'!$A:$A,'Product Families'!$P:$P),"")} | AC3: {=iferror(xlookup($K3,'Product Families'!$A:$A,'Product Families'!$Q:$Q),"")} | AD3: =iferror(AB3/AC3,"") | AE3: =iferror(AD3/$E3,"") -> 0 | AF3: =round($D3*AE3,2) -> 0 | AG3: {=iferror(xlookup($L3,'Product Families'!$A:$A,'Product Families'!$P:$P),"")} | AH3: {=iferror(xlookup($L3,'Product Families'!$A:$A,'Product Families'!$Q:$Q),"")} | AI3: =iferror(AG3/AH3,"") | AJ3: =iferror(AI3/$E3,"") -> 0 | AK3: =round($D3*AJ3,2) -> 0
A4: ABP | B4: 15.17 | C4: 1 | D4: =iferror(B4/C4,"") -> 15.17 | E4: =sum(O4+T4+Y4+AD4+AI4) -> 0 | H4: ABP | M4: {=iferror(xlookup($H4,'Product Families'!$A:$A,'Product Families'!$P:$P),"")} -> 0.19 | N4: {=iferror(xlookup($H4,'Product Families'!$A:$A,'Product Families'!$Q:$Q),"")} | O4: =iferror(M4/N4,"") | P4: =iferror(O4/$E4,"") | Q4: =round($D4*P4,2) -> 0 | R4: {=iferror(xlookup($I4,'Product Families'!$A:$A,'Product Families'!$P:$P),"")} | S4: {=iferror(xlookup($I4,'Product Families'!$A:$A,'Product Families'!$Q:$Q),"")} | T4: =iferror(R4/S4,"") | U4: =iferror(T4/$E4,"") | V4: =round($D4*U4,2) -> 0 | W4: {=iferror(xlookup($J4,'Product Families'!$A:$A,'Product Families'!$P:$P),"")} | X4: {=iferror(xlookup($J4,'Product Families'!$A:$A,'Product Families'!$Q:$Q),"")} | Y4: =iferror(W4/X4,"") | Z4: =iferror(Y4/$E4,"") | AA4: =round($D4*Z4,2) -> 0 | AB4: {=iferror(xlookup($K4,'Product Families'!$A:$A,'Product Families'!$P:$P),"")} | AC4: {=iferror(xlookup($K4,'Product Families'!$A:$A,'Product Families'!$Q:$Q),"")} | AD4: =iferror(AB4/AC4,"") | AE4: =iferror(AD4/$E4,"") | AF4: =round($D4*AE4,2) -> 0 | AG4: {=iferror(xlookup($L4,'Product Families'!$A:$A,'Product Families'!$P:$P),"")} | AH4: {=iferror(xlookup($L4,'Product Families'!$A:$A,'Product Families'!$Q:$Q),"")} | AI4: =iferror(AG4/AH4,"") | AJ4: =iferror(AI4/$E4,"") | AK4: =round($D4*AJ4,2) -> 0
A5: ABPC | B5: 10.96 | C5: 5 | D5: =iferror(B5/C5,"") -> 2.192 | E5: =sum(O5+T5+Y5+AD5+AI5) -> 0 | H5: ABPC | M5: {=iferror(xlookup($H5,'Product Families'!$A:$A,'Product Families'!$P:$P),"")} -> 0.25 | N5: {=iferror(xlookup($H5,'Product Families'!$A:$A,'Product Families'!$Q:$Q),"")} | O5: =iferror(M5/N5,"") | P5: =iferror(O5/$E5,"") | Q5: =round($D5*P5,2) -> 0 | R5: {=iferror(xlookup($I5,'Product Families'!$A:$A,'Product Families'!$P:$P),"")} | S5: {=iferror(xlookup($I5,'Product Families'!$A:$A,'Product Families'!$Q:$Q),"")} | T5: =iferror(R5/S5,"") | U5: =iferror(T5/$E5,"") | V5: =round($D5*U5,2) -> 0 | W5: {=iferror(xlookup($J5,'Product Families'!$A:$A,'Product Families'!$P:$P),"")} | X5: {=iferror(xlookup($J5,'Product Families'!$A:$A,'Product Families'!$Q:$Q),"")} | Y5: =iferror(W5/X5,"") | Z5: =iferror(Y5/$E5,"") | AA5: =round($D5*Z5,2) -> 0 | AB5: {=iferror(xlookup($K5,'Product Families'!$A:$A,'Product Families'!$P:$P),"")} | AC5: {=iferror(xlookup($K5,'Product Families'!$A:$A,'Product Families'!$Q:$Q),"")} | AD5: =iferror(AB5/AC5,"") | AE5: =iferror(AD5/$E5,"") | AF5: =round($D5*AE5,2) -> 0 | AG5: {=iferror(xlookup($L5,'Product Families'!$A:$A,'Product Families'!$P:$P),"")} | AH5: {=iferror(xlookup($L5,'Product Families'!$A:$A,'Product Families'!$Q:$Q),"")} | AI5: =iferror(AG5/AH5,"") | AJ5: =iferror(AI5/$E5,"") | AK5: =round($D5*AJ5,2) -> 0
A6: ABPCULB | B6: 9.81 | C6: 5 | D6: =iferror(B6/C6,"") -> 1.962 | E6: =sum(O6+T6+Y6+AD6+AI6) -> 0 | H6: ABPCULB | M6: {=iferror(xlookup($H6,'Product Families'!$A:$A,'Product Families'!$P:$P),"")} -> 0.94 | N6: {=iferror(xlookup($H6,'Product Families'!$A:$A,'Product Families'!$Q:$Q),"")} | O6: =iferror(M6/N6,"") | P6: =iferror(O6/$E6,"") | Q6: =round($D6*P6,2) -> 0 | R6: {=iferror(xlookup($I6,'Product Families'!$A:$A,'Product Families'!$P:$P),"")} | S6: {=iferror(xlookup($I6,'Product Families'!$A:$A,'Product Families'!$Q:$Q),"")} | T6: =iferror(R6/S6,"") | U6: =iferror(T6/$E6,"") | V6: =round($D6*U6,2) -> 0 | W6: {=iferror(xlookup($J6,'Product Families'!$A:$A,'Product Families'!$P:$P),"")} | X6: {=iferror(xlookup($J6,'Product Families'!$A:$A,'Product Families'!$Q:$Q),"")} | Y6: =iferror(W6/X6,"") | Z6: =iferror(Y6/$E6,"") | AA6: =round($D6*Z6,2) -> 0 | AB6: {=iferror(xlookup($K6,'Product Families'!$A:$A,'Product Families'!$P:$P),"")} | AC6: {=iferror(xlookup($K6,'Product Families'!$A:$A,'Product Families'!$Q:$Q),"")} | AD6: =iferror(AB6/AC6,"") | AE6: =iferror(AD6/$E6,"") | AF6: =round($D6*AE6,2) -> 0 | AG6: {=iferror(xlookup($L6,'Product Families'!$A:$A,'Product Families'!$P:$P),"")} | AH6: {=iferror(xlookup($L6,'Product Families'!$A:$A,'Product Families'!$Q:$Q),"")} | AI6: =iferror(AG6/AH6,"") | AJ6: =iferror(AI6/$E6,"") | AK6: =round($D6*AJ6,2) -> 0
A7: ACBB | B7: 13.3 | C7: 6 | D7: =iferror(B7/C7,"") -> 2.2166667 | E7: =sum(O7+T7+Y7+AD7+AI7) -> 0 | H7: ACBB | I7: ACBBL | J7: ACBBP | M7: {=iferror(xlookup($H7,'Product Families'!$A:$A,'Product Families'!$P:$P),"")} -> 0.1 | N7: {=iferror(xlookup($H7,'Product Families'!$A:$A,'Product Families'!$Q:$Q),"")} | O7: =iferror(M7/N7,"") | P7: =iferror(O7/$E7,"") | Q7: =round($D7*P7,2) -> 0 | R7: {=iferror(xlookup($I7,'Product Families'!$A:$A,'Product Families'!$P:$P),"")} -> 0.08 | S7: {=iferror(xlookup($I7,'Product Families'!$A:$A,'Product Families'!$Q:$Q),"")} | T7: =iferror(R7/S7,"") | U7: =iferror(T7/$E7,"") | V7: =round($D7*U7,2) -> 0 | W7: {=iferror(xlookup($J7,'Product Families'!$A:$A,'Product Families'!$P:$P),"")} -> 0.42 | X7: {=iferror(xlookup($J7,'Product Families'!$A:$A,'Product Families'!$Q:$Q),"")} | Y7: =iferror(W7/X7,"") | Z7: =iferror(Y7/$E7,"") | AA7: =round($D7*Z7,2) -> 0 | AB7: {=iferror(xlookup($K7,'Product Families'!$A:$A,'Product Families'!$P:$P),"")} | AC7: {=iferror(xlookup($K7,'Product Families'!$A:$A,'Product Families'!$Q:$Q),"")} | AD7: =iferror(AB7/AC7,"") | AE7: =iferror(AD7/$E7,"") | AF7: =round($D7*AE7,2) -> 0 | AG7: {=iferror(xlookup($L7,'Product Families'!$A:$A,'Product Families'!$P:$P),"")} | AH7: {=iferror(xlookup($L7,'Product Families'!$A:$A,'Product Families'!$Q:$Q),"")} | AI7: =iferror(AG7/AH7,"") | AJ7: =iferror(AI7/$E7,"") | AK7: =round($D7*AJ7,2) -> 0
A8: ACBBG | B8: offline | D8: =iferror(B8/C8,"") | E8: =sum(O8+T8+Y8+AD8+AI8) -> 0 | G8: product not made | H8: ACBBG | M8: {=iferror(xlookup($H8,'Product Families'!$A:$A,'Product Families'!$P:$P),"")} -> 0.44 | N8: {=iferror(xlookup($H8,'Product Families'!$A:$A,'Product Families'!$Q:$Q),"")} | O8: =iferror(M8/N8,"") | P8: =iferror(O8/$E8,"") | Q8: =round($D8*P8,2) -> 0 | R8: {=iferror(xlookup($I8,'Product Families'!$A:$A,'Product Families'!$P:$P),"")} | S8: {=iferror(xlookup($I8,'Product Families'!$A:$A,'Product Families'!$Q:$Q),"")} | T8: =iferror(R8/S8,"") | U8: =iferror(T8/$E8,"") | V8: =round($D8*U8,2) -> 0 | W8: {=iferror(xlookup($J8,'Product Families'!$A:$A,'Product Families'!$P:$P),"")} | X8: {=iferror(xlookup($J8,'Product Families'!$A:$A,'Product Families'!$Q:$Q),"")} | Y8: =iferror(W8/X8,"") | Z8: =iferror(Y8/$E8,"") | AA8: =round($D8*Z8,2) -> 0 | AB8: {=iferror(xlookup($K8,'Product Families'!$A:$A,'Product Families'!$P:$P),"")} | AC8: {=iferror(xlookup($K8,'Product Families'!$A:$A,'Product Families'!$Q:$Q),"")} | AD8: =iferror(AB8/AC8,"") | AE8: =iferror(AD8/$E8,"") | AF8: =round($D8*AE8,2) -> 0 | AG8: {=iferror(xlookup($L8,'Product Families'!$A:$A,'Product Families'!$P:$P),"")} | AH8: {=iferror(xlookup($L8,'Product Families'!$A:$A,'Product Families'!$Q:$Q),"")} | AI8: =iferror(AG8/AH8,"") | AJ8: =iferror(AI8/$E8,"") | AK8: =round($D8*AJ8,2) -> 0
A9: ACBC | B9: 21 | C9: 4 | D9: =iferror(B9/C9,"") -> 5.25 | E9: =sum(O9+T9+Y9+AD9+AI9) -> 0 | H9: ACBC | M9: {=iferror(xlookup($H9,'Product Families'!$A:$A,'Product Families'!$P:$P),"")} -> 0.15 | N9: {=iferror(xlookup($H9,'Product Families'!$A:$A,'Product Families'!$Q:$Q),"")} | O9: =iferror(M9/N9,"") | P9: =iferror(O9/$E9,"") | Q9: =round($D9*P9,2) -> 0 | R9: {=iferror(xlookup($I9,'Product Families'!$A:$A,'Product Families'!$P:$P),"")} | S9: {=iferror(xlookup($I9,'Product Families'!$A:$A,'Product Families'!$Q:$Q),"")} | T9: =iferror(R9/S9,"") | U9: =iferror(T9/$E9,"") | V9: =round($D9*U9,2) -> 0 | W9: {=iferror(xlookup($J9,'Product Families'!$A:$A,'Product Families'!$P:$P),"")} | X9: {=iferror(xlookup($J9,'Product Families'!$A:$A,'Product Families'!$Q:$Q),"")} | Y9: =iferror(W9/X9,"") | Z9: =iferror(Y9/$E9,"") | AA9: =round($D9*Z9,2) -> 0 | AB9: {=iferror(xlookup($K9,'Product Families'!$A:$A,'Product Families'!$P:$P),"")} | AC9: {=iferror(xlookup($K9,'Product Families'!$A:$A,'Product Families'!$Q:$Q),"")} | AD9: =iferror(AB9/AC9,"") | AE9: =iferror(AD9/$E9,"") | AF9: =round($D9*AE9,2) -> 0 | AG9: {=iferror(xlookup($L9,'Product Families'!$A:$A,'Product Families'!$P:$P),"")} | AH9: {=iferror(xlookup($L9,'Product Families'!$A:$A,'Product Families'!$Q:$Q),"")} | AI9: =iferror(AG9/AH9,"") | AJ9: =iferror(AI9/$E9,"") | AK9: =round($D9*AJ9,2) -> 0
A10: ACCLAY | B10: n/a | D10: =iferror(B10/C10,"") | E10: =sum(O10+T10+Y10+AD10+AI10) -> 0 | G10: code not in use | H10: ACCLAY | M10: {=iferror(xlookup($H10,'Product Families'!$A:$A,'Product Families'!$P:$P),"")} -> 0.24 | N10: {=iferror(xlookup($H10,'Product Families'!$A:$A,'Product Families'!$Q:$Q),"")} | O10: =iferror(M10/N10,"") | P10: =iferror(O10/$E10,"") | Q10: =round($D10*P10,2) -> 0 | R10: {=iferror(xlookup($I10,'Product Families'!$A:$A,'Product Families'!$P:$P),"")} | S10: {=iferror(xlookup($I10,'Product Families'!$A:$A,'Product Families'!$Q:$Q),"")} | T10: =iferror(R10/S10,"") | U10: =iferror(T10/$E10,"") | V10: =round($D10*U10,2) -> 0 | W10: {=iferror(xlookup($J10,'Product Families'!$A:$A,'Product Families'!$P:$P),"")} | X10: {=iferror(xlookup($J10,'Product Families'!$A:$A,'Product Families'!$Q:$Q),"")} | Y10: =iferror(W10/X10,"") | Z10: =iferror(Y10/$E10,"") | AA10: =round($D10*Z10,2) -> 0 | AB10: {=iferror(xlookup($K10,'Product Families'!$A:$A,'Product Families'!$P:$P),"")} | AC10: {=iferror(xlookup($K10,'Product Families'!$A:$A,'Product Families'!$Q:$Q),"")} | AD10: =iferror(AB10/AC10,"") | AE10: =iferror(AD10/$E10,"") | AF10: =round($D10*AE10,2) -> 0 | AG10: {=iferror(xlookup($L10,'Product Families'!$A:$A,'Product Families'!$P:$P),"")} | AH10: {=iferror(xlookup($L10,'Product Families'!$A:$A,'Product Families'!$Q:$Q),"")} | AI10: =iferror(AG10/AH10,"") | AJ10: =iferror(AI10/$E10,"") | AK10: =round($D10*AJ10,2) -> 0
A11: ACD | B11: 8.5 | C11: 1 | D11: =iferror(B11/C11,"") -> 8.5 | E11: =sum(O11+T11+Y11+AD11+AI11) -> 0 | H11: ACD | M11: {=iferror(xlookup($H11,'Product Families'!$A:$A,'Product Families'!$P:$P),"")} -> 0.68 | N11: {=iferror(xlookup($H11,'Product Families'!$A:$A,'Product Families'!$Q:$Q),"")} | O11: =iferror(M11/N11,"") | P11: =iferror(O11/$E11,"") | Q11: =round($D11*P11,2) -> 0 | R11: {=iferror(xlookup($I11,'Product Families'!$A:$A,'Product Families'!$P:$P),"")} | S11: {=iferror(xlookup($I11,'Product Families'!$A:$A,'Product Families'!$Q:$Q),"")} | T11: =iferror(R11/S11,"") | U11: =iferror(T11/$E11,"") | V11: =round($D11*U11,2) -> 0 | W11: {=iferror(xlookup($J11,'Product Families'!$A:$A,'Product Families'!$P:$P),"")} | X11: {=iferror(xlookup($J11,'Product Families'!$A:$A,'Product Families'!$Q:$Q),"")} | Y11: =iferror(W11/X11,"") | Z11: =iferror(Y11/$E11,"") | AA11: =round($D11*Z11,2) -> 0 | AB11: {=iferror(xlookup($K11,'Product Families'!$A:$A,'Product Families'!$P:$P),"")} | AC11: {=iferror(xlookup($K11,'Product Families'!$A:$A,'Product Families'!$Q:$Q),"")} | AD11: =iferror(AB11/AC11,"") | AE11: =iferror(AD11/$E11,"") | AF11: =round($D11*AE11,2) -> 0 | AG11: {=iferror(xlookup($L11,'Product Families'!$A:$A,'Product Families'!$P:$P),"")} | AH11: {=iferror(xlookup($L11,'Product Families'!$A:$A,'Product Families'!$Q:$Q),"")} | AI11: =iferror(AG11/AH11,"") | AJ11: =iferror(AI11/$E11,"") | AK11: =round($D11*AJ11,2) -> 0
A12: ACDR | B12: 4 | C12: 1 | D12: =iferror(B12/C12,"") -> 4 | E12: =sum(O12+T12+Y12+AD12+AI12) -> 0 | H12: ACDR | M12: {=iferror(xlookup($H12,'Product Families'!$A:$A,'Product Families'!$P:$P),"")} -> 0.24 | N12: {=iferror(xlookup($H12,'Product Families'!$A:$A,'Product Families'!$Q:$Q),"")} | O12: =iferror(M12/N12,"") | P12: =iferror(O12/$E12,"") | Q12: =round($D12*P12,2) -> 0 | R12: {=iferror(xlookup($I12,'Product Families'!$A:$A,'Product Families'!$P:$P),"")} | S12: {=iferror(xlookup($I12,'Product Families'!$A:$A,'Product Families'!$Q:$Q),"")} | T12: =iferror(R12/S12,"") | U12: =iferror(T12/$E12,"") | V12: =round($D12*U12,2) -> 0 | W12: {=iferror(xlookup($J12,'Product Families'!$A:$A,'Product Families'!$P:$P),"")} | X12: {=iferror(xlookup($J12,'Product Families'!$A:$A,'Product Families'!$Q:$Q),"")} | Y12: =iferror(W12/X12,"") | Z12: =iferror(Y12/$E12,"") | AA12: =round($D12*Z12,2) -> 0 | AB12: {=iferror(xlookup($K12,'Product Families'!$A:$A,'Product Families'!$P:$P),"")} | AC12: {=iferror(xlookup($K12,'Product Families'!$A:$A,'Product Families'!$Q:$Q),"")} | AD12: =iferror(AB12/AC12,"") | AE12: =iferror(AD12/$E12,"") | AF12: =round($D12*AE12,2) -> 0 | AG12: {=iferror(xlookup($L12,'Product Families'!$A:$A,'Product Families'!$P:$P),"")} | AH12: {=iferror(xlookup($L12,'Product Families'!$A:$A,'Product Families'!$Q:$Q),"")} | AI12: =iferror(AG12/AH12,"") | AJ12: =iferror(AI12/$E12,"") | AK12: =round($D12*AJ12,2) -> 0
A13: ACFC | B13: offline | D13: =iferror(B13/C13,"") | E13: =sum(O13+T13+Y13+AD13+AI13) -> 0 | G13: product not made | H13: ACFC | M13: {=iferror(xlookup($H13,'Product Families'!$A:$A,'Product Families'!$P:$P),"")} -> 0.15 | N13: {=iferror(xlookup($H13,'Product Families'!$A:$A,'Product Families'!$Q:$Q),"")} | O13: =iferror(M13/N13,"") | P13: =iferror(O13/$E13,"") | Q13: =round($D13*P13,2) -> 0 | R13: {=iferror(xlookup($I13,'Product Families'!$A:$A,'Product Families'!$P:$P),"")} | S13: {=iferror(xlookup($I13,'Product Families'!$A:$A,'Product Families'!$Q:$Q),"")} | T13: =iferror(R13/S13,"") | U13: =iferror(T13/$E13,"") | V13: =round($D13*U13,2) -> 0 | W13: {=iferror(xlookup($J13,'Product Families'!$A:$A,'Product Families'!$P:$P),"")} | X13: {=iferror(xlookup($J13,'Product Families'!$A:$A,'Product Families'!$Q:$Q),"")} | Y13: =iferror(W13/X13,"") | Z13: =iferror(Y13/$E13,"") | AA13: =round($D13*Z13,2) -> 0 | AB13: {=iferror(xlookup($K13,'Product Families'!$A:$A,'Product Families'!$P:$P),"")} | AC13: {=iferror(xlookup($K13,'Product Families'!$A:$A,'Product Families'!$Q:$Q),"")} | AD13: =iferror(AB13/AC13,"") | AE13: =iferror(AD13/$E13,"") | AF13: =round($D13*AE13,2) -> 0 | AG13: {=iferror(xlookup($L13,'Product Families'!$A:$A,'Product Families'!$P:$P),"")} | AH13: {=iferror(xlookup($L13,'Product Families'!$A:$A,'Product Families'!$Q:$Q),"")} | AI13: =iferror(AG13/AH13,"") | AJ13: =iferror(AI13/$E13,"") | AK13: =round($D13*AJ13,2) -> 0
A14: ACFD | B14: 17.85 | C14: 3 | D14: =iferror(B14/C14,"") -> 5.95 | E14: =sum(O14+T14+Y14+AD14+AI14) -> 0 | H14: ACFD | M14: {=iferror(xlookup($H14,'Product Families'!$A:$A,'Product Families'!$P:$P),"")} -> 0.68 | N14: {=iferror(xlookup($H14,'Product Families'!$A:$A,'Product Families'!$Q:$Q),"")} | O14: =iferror(M14/N14,"") | P14: =iferror(O14/$E14,"") | Q14: =round($D14*P14,2) -> 0 | R14: {=iferror(xlookup($I14,'Product Families'!$A:$A,'Product Families'!$P:$P),"")} | S14: {=iferror(xlookup($I14,'Product Families'!$A:$A,'Product Families'!$Q:$Q),"")} | T14: =iferror(R14/S14,"") | U14: =iferror(T14/$E14,"") | V14: =round($D14*U14,2) -> 0 | W14: {=iferror(xlookup($J14,'Product Families'!$A:$A,'Product Families'!$P:$P),"")} | X14: {=iferror(xlookup($J14,'Product Families'!$A:$A,'Product Families'!$Q:$Q),"")} | Y14: =iferror(W14/X14,"") | Z14: =iferror(Y14/$E14,"") | AA14: =round($D14*Z14,2) -> 0 | AB14: {=iferror(xlookup($K14,'Product Families'!$A:$A,'Product Families'!$P:$P),"")} | AC14: {=iferror(xlookup($K14,'Product Families'!$A:$A,'Product Families'!$Q:$Q),"")} | AD14: =iferror(AB14/AC14,"") | AE14: =iferror(AD14/$E14,"") | AF14: =round($D14*AE14,2) -> 0 | AG14: {=iferror(xlookup($L14,'Product Families'!$A:$A,'Product Families'!$P:$P),"")} | AH14: {=iferror(xlookup($L14,'Product Families'!$A:$A,'Product Families'!$Q:$Q),"")} | AI14: =iferror(AG14/AH14,"") | AJ14: =iferror(AI14/$E14,"") | AK14: =round($D14*AJ14,2) -> 0
A15: ACFM | B15: 12.75 - 19.95 | C15: 4 | D15: =iferror(B15/C15,"") | E15: =sum(O15+T15+Y15+AD15+AI15) -> 0 | G15: 3 different prices | H15: ACFM | M15: {=iferror(xlookup($H15,'Product Families'!$A:$A,'Product Families'!$P:$P),"")} -> 0.29 | N15: {=iferror(xlookup($H15,'Product Families'!$A:$A,'Product Families'!$Q:$Q),"")} | O15: =iferror(M15/N15,"") | P15: =iferror(O15/$E15,"") | Q15: =round($D15*P15,2) -> 0 | R15: {=iferror(xlookup($I15,'Product Families'!$A:$A,'Product Families'!$P:$P),"")} | S15: {=iferror(xlookup($I15,'Product Families'!$A:$A,'Product Families'!$Q:$Q),"")} | T15: =iferror(R15/S15,"") | U15: =iferror(T15/$E15,"") | V15: =round($D15*U15,2) -> 0 | W15: {=iferror(xlookup($J15,'Product Families'!$A:$A,'Product Families'!$P:$P),"")} | X15: {=iferror(xlookup($J15,'Product Families'!$A:$A,'Product Families'!$Q:$Q),"")} | Y15: =iferror(W15/X15,"") | Z15: =iferror(Y15/$E15,"") | AA15: =round($D15*Z15,2) -> 0 | AB15: {=iferror(xlookup($K15,'Product Families'!$A:$A,'Product Families'!$P:$P),"")} | AC15: {=iferror(xlookup($K15,'Product Families'!$A:$A,'Product Families'!$Q:$Q),"")} | AD15: =iferror(AB15/AC15,"") | AE15: =iferror(AD15/$E15,"") | AF15: =round($D15*AE15,2) -> 0 | AG15: {=iferror(xlookup($L15,'Product Families'!$A:$A,'Product Families'!$P:$P),"")} | AH15: {=iferror(xlookup($L15,'Product Families'!$A:$A,'Product Families'!$Q:$Q),"")} | AI15: =iferror(AG15/AH15,"") | AJ15: =iferror(AI15/$E15,"") | AK15: =round($D15*AJ15,2) -> 0
A16: ACGB | B16: n/a | D16: =iferror(B16/C16,"") | E16: =sum(O16+T16+Y16+AD16+AI16) -> 0 | G16: code not in use | H16: ACGB | M16: {=iferror(xlookup($H16,'Product Families'!$A:$A,'Product Families'!$P:$P),"")} -> 0.48 | N16: {=iferror(xlookup($H16,'Product Families'!$A:$A,'Product Families'!$Q:$Q),"")} | O16: =iferror(M16/N16,"") | P16: =iferror(O16/$E16,"") | Q16: =round($D16*P16,2) -> 0 | R16: {=iferror(xlookup($I16,'Product Families'!$A:$A,'Product Families'!$P:$P),"")} | S16: {=iferror(xlookup($I16,'Product Families'!$A:$A,'Product Families'!$Q:$Q),"")} | T16: =iferror(R16/S16,"") | U16: =iferror(T16/$E16,"") | V16: =round($D16*U16,2) -> 0 | W16: {=iferror(xlookup($J16,'Product Families'!$A:$A,'Product Families'!$P:$P),"")} | X16: {=iferror(xlookup($J16,'Product Families'!$A:$A,'Product Families'!$Q:$Q),"")} | Y16: =iferror(W16/X16,"") | Z16: =iferror(Y16/$E16,"") | AA16: =round($D16*Z16,2) -> 0 | AB16: {=iferror(xlookup($K16,'Product Families'!$A:$A,'Product Families'!$P:$P),"")} | AC16: {=iferror(xlookup($K16,'Product Families'!$A:$A,'Product Families'!$Q:$Q),"")} | AD16: =iferror(AB16/AC16,"") | AE16: =iferror(AD16/$E16,"") | AF16: =round($D16*AE16,2) -> 0 | AG16: {=iferror(xlookup($L16,'Product Families'!$A:$A,'Product Families'!$P:$P),"")} | AH16: {=iferror(xlookup($L16,'Product Families'!$A:$A,'Product Families'!$Q:$Q),"")} | AI16: =iferror(AG16/AH16,"") | AJ16: =iferror(AI16/$E16,"") | AK16: =round($D16*AJ16,2) -> 0
A17: ACGP | B17: 11.5 | C17: 1 | D17: =iferror(B17/C17,"") -> 11.5 | E17: =sum(O17+T17+Y17+AD17+AI17) -> 0 | H17: ACGP | M17: {=iferror(xlookup($H17,'Product Families'!$A:$A,'Product Families'!$P:$P),"")} -> 1.15 | N17: {=iferror(xlookup($H17,'Product Families'!$A:$A,'Product Families'!$Q:$Q),"")} | O17: =iferror(M17/N17,"") | P17: =iferror(O17/$E17,"") | Q17: =round($D17*P17,2) -> 0 | R17: {=iferror(xlookup($I17,'Product Families'!$A:$A,'Product Families'!$P:$P),"")} | S17: {=iferror(xlookup($I17,'Product Families'!$A:$A,'Product Families'!$Q:$Q),"")} | T17: =iferror(R17/S17,"") | U17: =iferror(T17/$E17,"") | V17: =round($D17*U17,2) -> 0 | W17: {=iferror(xlookup($J17,'Product Families'!$A:$A,'Product Families'!$P:$P),"")} | X17: {=iferror(xlookup($J17,'Product Families'!$A:$A,'Product Families'!$Q:$Q),"")} | Y17: =iferror(W17/X17,"") | Z17: =iferror(Y17/$E17,"") | AA17: =round($D17*Z17,2) -> 0 | AB17: {=iferror(xlookup($K17,'Product Families'!$A:$A,'Product Families'!$P:$P),"")} | AC17: {=iferror(xlookup($K17,'Product Families'!$A:$A,'Product Families'!$Q:$Q),"")} | AD17: =iferror(AB17/AC17,"") | AE17: =iferror(AD17/$E17,"") | AF17: =round($D17*AE17,2) -> 0 | AG17: {=iferror(xlookup($L17,'Product Families'!$A:$A,'Product Families'!$P:$P),"")} | AH17: {=iferror(xlookup($L17,'Product Families'!$A:$A,'Product Families'!$Q:$Q),"")} | AI17: =iferror(AG17/AH17,"") | AJ17: =iferror(AI17/$E17,"") | AK17: =round($D17*AJ17,2) -> 0
A18: ACGS | B18: 5.95 - 10.50 | C18: 1 | D18: =iferror(B18/C18,"") | E18: =sum(O18+T18+Y18+AD18+AI18) -> 0 | G18: 2 different prices | H18: ACGS | M18: {=iferror(xlookup($H18,'Product Families'!$A:$A,'Product Families'!$P:$P),"")} -> 0.44 | N18: {=iferror(xlookup($H18,'Product Families'!$A:$A,'Product Families'!$Q:$Q),"")} | O18: =iferror(M18/N18,"") | P18: =iferror(O18/$E18,"") | Q18: =round($D18*P18,2) -> 0 | R18: {=iferror(xlookup($I18,'Product Families'!$A:$A,'Product Families'!$P:$P),"")} | S18: {=iferror(xlookup($I18,'Product Families'!$A:$A,'Product Families'!$Q:$Q),"")} | T18: =iferror(R18/S18,"") | U18: =iferror(T18/$E18,"") | V18: =round($D18*U18,2) -> 0 | W18: {=iferror(xlookup($J18,'Product Families'!$A:$A,'Product Families'!$P:$P),"")} | X18: {=iferror(xlookup($J18,'Product Families'!$A:$A,'Product Families'!$Q:$Q),"")} | Y18: =iferror(W18/X18,"") | Z18: =iferror(Y18/$E18,"") | AA18: =round($D18*Z18,2) -> 0 | AB18: {=iferror(xlookup($K18,'Product Families'!$A:$A,'Product Families'!$P:$P),"")} | AC18: {=iferror(xlookup($K18,'Product Families'!$A:$A,'Product Families'!$Q:$Q),"")} | AD18: =iferror(AB18/AC18,"") | AE18: =iferror(AD18/$E18,"") | AF18: =round($D18*AE18,2) -> 0 | AG18: {=iferror(xlookup($L18,'Product Families'!$A:$A,'Product Families'!$P:$P),"")} | AH18: {=iferror(xlookup($L18,'Product Families'!$A:$A,'Product Families'!$Q:$Q),"")} | AI18: =iferror(AG18/AH18,"") | AJ18: =iferror(AI18/$E18,"") | AK18: =round($D18*AJ18,2) -> 0
A19: ACHS | B19: 15.84 | C19: 6 | D19: =iferror(B19/C19,"") -> 2.64 | E19: =sum(O19+T19+Y19+AD19+AI19) -> 0 | G19: Discontinuing | H19: ACHS | I19: ACHSP | M19: {=iferror(xlookup($H19,'Product Families'!$A:$A,'Product Families'!$P:$P),"")} -> 0.18 | N19: {=iferror(xlookup($H19,'Product Families'!$A:$A,'Product Families'!$Q:$Q),"")} | O19: =iferror(M19/N19,"") | P19: =iferror(O19/$E19,"") | Q19: =round($D19*P19,2) -> 0 | R19: {=iferror(xlookup($I19,'Product Families'!$A:$A,'Product Families'!$P:$P),"")} -> 0.22 | S19: {=iferror(xlookup($I19,'Product Families'!$A:$A,'Product Families'!$Q:$Q),"")} | T19: =iferror(R19/S19,"") | U19: =iferror(T19/$E19,"") | V19: =round($D19*U19,2) -> 0 | W19: {=iferror(xlookup($J19,'Product Families'!$A:$A,'Product Families'!$P:$P),"")} | X19: {=iferror(xlookup($J19,'Product Families'!$A:$A,'Product Families'!$Q:$Q),"")} | Y19: =iferror(W19/X19,"") | Z19: =iferror(Y19/$E19,"") | AA19: =round($D19*Z19,2) -> 0 | AB19: {=iferror(xlookup($K19,'Product Families'!$A:$A,'Product Families'!$P:$P),"")} | AC19: {=iferror(xlookup($K19,'Product Families'!$A:$A,'Product Families'!$Q:$Q),"")} | AD19: =iferror(AB19/AC19,"") | AE19: =iferror(AD19/$E19,"") | AF19: =round($D19*AE19,2) -> 0 | AG19: {=iferror(xlookup($L19,'Product Families'!$A:$A,'Product Families'!$P:$P),"")} | AH19: {=iferror(xlookup($L19,'Product Families'!$A:$A,'Product Families'!$Q:$Q),"")} | AI19: =iferror(AG19/AH19,"") | AJ19: =iferror(AI19/$E19,"") | AK19: =round($D19*AJ19,2) -> 0
A20: ACLB | B20: 13.25 | C20: 6 | D20: =iferror(B20/C20,"") -> 2.2083333 | E20: =sum(O20+T20+Y20+AD20+AI20) -> 0 | H20: ACLB | I20: ACLBL | J20: ACLBP | M20: {=iferror(xlookup($H20,'Product Families'!$A:$A,'Product Families'!$P:$P),"")} -> 0.06 | N20: {=iferror(xlookup($H20,'Product Families'!$A:$A,'Product Families'!$Q:$Q),"")} | O20: =iferror(M20/N20,"") | P20: =iferror(O20/$E20,"") | Q20: =round($D20*P20,2) -> 0 | R20: {=iferror(xlookup($I20,'Product Families'!$A:$A,'Product Families'!$P:$P),"")} -> 0.05 | S20: {=iferror(xlookup($I20,'Product Families'!$A:$A,'Product Families'!$Q:$Q),"")} | T20: =iferror(R20/S20,"") | U20: =iferror(T20/$E20,"") | V20: =round($D20*U20,2) -> 0 | W20: {=iferror(xlookup($J20,'Product Families'!$A:$A,'Product Families'!$P:$P),"")} -> 1.07 | X20: {=iferror(xlookup($J20,'Product Families'!$A:$A,'Product Families'!$Q:$Q),"")} | Y20: =iferror(W20/X20,"") | Z20: =iferror(Y20/$E20,"") | AA20: =round($D20*Z20,2) -> 0 | AB20: {=iferror(xlookup($K20,'Product Families'!$A:$A,'Product Families'!$P:$P),"")} | AC20: {=iferror(xlookup($K20,'Product Families'!$A:$A,'Product Families'!$Q:$Q),"")} | AD20: =iferror(AB20/AC20,"") | AE20: =iferror(AD20/$E20,"") | AF20: =round($D20*AE20,2) -> 0 | AG20: {=iferror(xlookup($L20,'Product Families'!$A:$A,'Product Families'!$P:$P),"")} | AH20: {=iferror(xlookup($L20,'Product Families'!$A:$A,'Product Families'!$Q:$Q),"")} | AI20: =iferror(AG20/AH20,"") | AJ20: =iferror(AI20/$E20,"") | AK20: =round($D20*AJ20,2) -> 0
A21: ACOSS | B21: offline | D21: =iferror(B21/C21,"") | E21: =sum(O21+T21+Y21+AD21+AI21) -> 0 | G21: Discontinued | H21: ACOSS | I21: ACOSSP | M21: {=iferror(xlookup($H21,'Product Families'!$A:$A,'Product Families'!$P:$P),"")} -> 0.15 | N21: {=iferror(xlookup($H21,'Product Families'!$A:$A,'Product Families'!$Q:$Q),"")} | O21: =iferror(M21/N21,"") | P21: =iferror(O21/$E21,"") | Q21: =round($D21*P21,2) -> 0 | R21: {=iferror(xlookup($I21,'Product Families'!$A:$A,'Product Families'!$P:$P),"")} -> 0.1 | S21: {=iferror(xlookup($I21,'Product Families'!$A:$A,'Product Families'!$Q:$Q),"")} | T21: =iferror(R21/S21,"") | U21: =iferror(T21/$E21,"") | V21: =round($D21*U21,2) -> 0 | W21: {=iferror(xlookup($J21,'Product Families'!$A:$A,'Product Families'!$P:$P),"")} | X21: {=iferror(xlookup($J21,'Product Families'!$A:$A,'Product Families'!$Q:$Q),"")} | Y21: =iferror(W21/X21,"") | Z21: =iferror(Y21/$E21,"") | AA21: =round($D21*Z21,2) -> 0 | AB21: {=iferror(xlookup($K21,'Product Families'!$A:$A,'Product Families'!$P:$P),"")} | AC21: {=iferror(xlookup($K21,'Product Families'!$A:$A,'Product Families'!$Q:$Q),"")} | AD21: =iferror(AB21/AC21,"") | AE21: =iferror(AD21/$E21,"") | AF21: =round($D21*AE21,2) -> 0 | AG21: {=iferror(xlookup($L21,'Product Families'!$A:$A,'Product Families'!$P:$P),"")} | AH21: {=iferror(xlookup($L21,'Product Families'!$A:$A,'Product Families'!$Q:$Q),"")} | AI21: =iferror(AG21/AH21,"") | AJ21: =iferror(AI21/$E21,"") | AK21: =round($D21*AJ21,2) -> 0
A22: ACREBL | B22: 17.5 | C22: 6 | D22: =iferror(B22/C22,"") -> 2.9166667 | E22: =sum(O22+T22+Y22+AD22+AI22) -> 0 | H22: ACREBL | M22: {=iferror(xlookup($H22,'Product Families'!$A:$A,'Product Families'!$P:$P),"")} -> 0.13 | N22: {=iferror(xlookup($H22,'Product Families'!$A:$A,'Product Families'!$Q:$Q),"")} | O22: =iferror(M22/N22,"") | P22: =iferror(O22/$E22,"") | Q22: =round($D22*P22,2) -> 0 | R22: {=iferror(xlookup($I22,'Product Families'!$A:$A,'Product Families'!$P:$P),"")} | S22: {=iferror(xlookup($I22,'Product Families'!$A:$A,'Product Families'!$Q:$Q),"")} | T22: =iferror(R22/S22,"") | U22: =iferror(T22/$E22,"") | V22: =round($D22*U22,2) -> 0 | W22: {=iferror(xlookup($J22,'Product Families'!$A:$A,'Product Families'!$P:$P),"")} | X22: {=iferror(xlookup($J22,'Product Families'!$A:$A,'Product Families'!$Q:$Q),"")} | Y22: =iferror(W22/X22,"") | Z22: =iferror(Y22/$E22,"") | AA22: =round($D22*Z22,2) -> 0 | AB22: {=iferror(xlookup($K22,'Product Families'!$A:$A,'Product Families'!$P:$P),"")} | AC22: {=iferror(xlookup($K22,'Product Families'!$A:$A,'Product Families'!$Q:$Q),"")} | AD22: =iferror(AB22/AC22,"") | AE22: =iferror(AD22/$E22,"") | AF22: =round($D22*AE22,2) -> 0 | AG22: {=iferror(xlookup($L22,'Product Families'!$A:$A,'Product Families'!$P:$P),"")} | AH22: {=iferror(xlookup($L22,'Product Families'!$A:$A,'Product Families'!$Q:$Q),"")} | AI22: =iferror(AG22/AH22,"") | AJ22: =iferror(AI22/$E22,"") | AK22: =round($D22*AJ22,2) -> 0
A23: ACRM | B23: offline | D23: =iferror(B23/C23,"") | E23: =sum(O23+T23+Y23+AD23+AI23) -> 0 | G23: product not made | H23: ACRM | M23: {=iferror(xlookup($H23,'Product Families'!$A:$A,'Product Families'!$P:$P),"")} -> 0.63 | N23: {=iferror(xlookup($H23,'Product Families'!$A:$A,'Product Families'!$Q:$Q),"")} | O23: =iferror(M23/N23,"") | P23: =iferror(O23/$E23,"") | Q23: =round($D23*P23,2) -> 0 | R23: {=iferror(xlookup($I23,'Product Families'!$A:$A,'Product Families'!$P:$P),"")} | S23: {=iferror(xlookup($I23,'Product Families'!$A:$A,'Product Families'!$Q:$Q),"")} | T23: =iferror(R23/S23,"") | U23: =iferror(T23/$E23,"") | V23: =round($D23*U23,2) -> 0 | W23: {=iferror(xlookup($J23,'Product Families'!$A:$A,'Product Families'!$P:$P),"")} | X23: {=iferror(xlookup($J23,'Product Families'!$A:$A,'Product Families'!$Q:$Q),"")} | Y23: =iferror(W23/X23,"") | Z23: =iferror(Y23/$E23,"") | AA23: =round($D23*Z23,2) -> 0 | AB23: {=iferror(xlookup($K23,'Product Families'!$A:$A,'Product Families'!$P:$P),"")} | AC23: {=iferror(xlookup($K23,'Product Families'!$A:$A,'Product Families'!$Q:$Q),"")} | AD23: =iferror(AB23/AC23,"") | AE23: =iferror(AD23/$E23,"") | AF23: =round($D23*AE23,2) -> 0 | AG23: {=iferror(xlookup($L23,'Product Families'!$A:$A,'Product Families'!$P:$P),"")} | AH23: {=iferror(xlookup($L23,'Product Families'!$A:$A,'Product Families'!$Q:$Q),"")} | AI23: =iferror(AG23/AH23,"") | AJ23: =iferror(AI23/$E23,"") | AK23: =round($D23*AJ23,2) -> 0
A24: ACSaltB | B24: n/a | D24: =iferror(B24/C24,"") | E24: =sum(O24+T24+Y24+AD24+AI24) -> 0 | G24: code not in use | H24: ACSaltB | M24: {=iferror(xlookup($H24,'Product Families'!$A:$A,'Product Families'!$P:$P),"")} -> 1.67 | N24: {=iferror(xlookup($H24,'Product Families'!$A:$A,'Product Families'!$Q:$Q),"")} | O24: =iferror(M24/N24,"") | P24: =iferror(O24/$E24,"") | Q24: =round($D24*P24,2) -> 0 | R24: {=iferror(xlookup($I24,'Product Families'!$A:$A,'Product Families'!$P:$P),"")} | S24: {=iferror(xlookup($I24,'Product Families'!$A:$A,'Product Families'!$Q:$Q),"")} | T24: =iferror(R24/S24,"") | U24: =iferror(T24/$E24,"") | V24: =round($D24*U24,2) -> 0 | W24: {=iferror(xlookup($J24,'Product Families'!$A:$A,'Product Families'!$P:$P),"")} | X24: {=iferror(xlookup($J24,'Product Families'!$A:$A,'Product Families'!$Q:$Q),"")} | Y24: =iferror(W24/X24,"") | Z24: =iferror(Y24/$E24,"") | AA24: =round($D24*Z24,2) -> 0 | AB24: {=iferror(xlookup($K24,'Product Families'!$A:$A,'Product Families'!$P:$P),"")} | AC24: {=iferror(xlookup($K24,'Product Families'!$A:$A,'Product Families'!$Q:$Q),"")} | AD24: =iferror(AB24/AC24,"") | AE24: =iferror(AD24/$E24,"") | AF24: =round($D24*AE24,2) -> 0 | AG24: {=iferror(xlookup($L24,'Product Families'!$A:$A,'Product Families'!$P:$P),"")} | AH24: {=iferror(xlookup($L24,'Product Families'!$A:$A,'Product Families'!$Q:$Q),"")} | AI24: =iferror(AG24/AH24,"") | AJ24: =iferror(AI24/$E24,"") | AK24: =round($D24*AJ24,2) -> 0
A25: ACSample | B25: 5 | C25: 1 | D25: =iferror(B25/C25,"") -> 5 | E25: =sum(O25+T25+Y25+AD25+AI25) -> 0 | G25: old acfp-02 / fragrance sanpmle pack | H25: ACSample | M25: {=iferror(xlookup($H25,'Product Families'!$A:$A,'Product Families'!$P:$P),"")} -> 0.29 | N25: {=iferror(xlookup($H25,'Product Families'!$A:$A,'Product Families'!$Q:$Q),"")} | O25: =iferror(M25/N25,"") | P25: =iferror(O25/$E25,"") | Q25: =round($D25*P25,2) -> 0 | R25: {=iferror(xlookup($I25,'Product Families'!$A:$A,'Product Families'!$P:$P),"")} | S25: {=iferror(xlookup($I25,'Product Families'!$A:$A,'Product Families'!$Q:$Q),"")} | T25: =iferror(R25/S25,"") | U25: =iferror(T25/$E25,"") | V25: =round($D25*U25,2) -> 0 | W25: {=iferror(xlookup($J25,'Product Families'!$A:$A,'Product Families'!$P:$P),"")} | X25: {=iferror(xlookup($J25,'Product Families'!$A:$A,'Product Families'!$Q:$Q),"")} | Y25: =iferror(W25/X25,"") | Z25: =iferror(Y25/$E25,"") | AA25: =round($D25*Z25,2) -> 0 | AB25: {=iferror(xlookup($K25,'Product Families'!$A:$A,'Product Families'!$P:$P),"")} | AC25: {=iferror(xlookup($K25,'Product Families'!$A:$A,'Product Families'!$Q:$Q),"")} | AD25: =iferror(AB25/AC25,"") | AE25: =iferror(AD25/$E25,"") | AF25: =round($D25*AE25,2) -> 0 | AG25: {=iferror(xlookup($L25,'Product Families'!$A:$A,'Product Families'!$P:$P),"")} | AH25: {=iferror(xlookup($L25,'Product Families'!$A:$A,'Product Families'!$Q:$Q),"")} | AI25: =iferror(AG25/AH25,"") | AJ25: =iferror(AI25/$E25,"") | AK25: =round($D25*AJ25,2) -> 0
A26: ACSR | B26: 18.5 | C26: 6 | D26: =iferror(B26/C26,"") -> 3.0833333 | E26: =sum(O26+T26+Y26+AD26+AI26) -> 0 | H26: ACSR | M26: {=iferror(xlookup($H26,'Product Families'!$A:$A,'Product Families'!$P:$P),"")} -> 1.67 | N26: {=iferror(xlookup($H26,'Product Families'!$A:$A,'Product Families'!$Q:$Q),"")} | O26: =iferror(M26/N26,"") | P26: =iferror(O26/$E26,"") | Q26: =round($D26*P26,2) -> 0 | R26: {=iferror(xlookup($I26,'Product Families'!$A:$A,'Product Families'!$P:$P),"")} | S26: {=iferror(xlookup($I26,'Product Families'!$A:$A,'Product Families'!$Q:$Q),"")} | T26: =iferror(R26/S26,"") | U26: =iferror(T26/$E26,"") | V26: =round($D26*U26,2) -> 0 | W26: {=iferror(xlookup($J26,'Product Families'!$A:$A,'Product Families'!$P:$P),"")} | X26: {=iferror(xlookup($J26,'Product Families'!$A:$A,'Product Families'!$Q:$Q),"")} | Y26: =iferror(W26/X26,"") | Z26: =iferror(Y26/$E26,"") | AA26: =round($D26*Z26,2) -> 0 | AB26: {=iferror(xlookup($K26,'Product Families'!$A:$A,'Product Families'!$P:$P),"")} | AC26: {=iferror(xlookup($K26,'Product Families'!$A:$A,'Product Families'!$Q:$Q),"")} | AD26: =iferror(AB26/AC26,"") | AE26: =iferror(AD26/$E26,"") | AF26: =round($D26*AE26,2) -> 0 | AG26: {=iferror(xlookup($L26,'Product Families'!$A:$A,'Product Families'!$P:$P),"")} | AH26: {=iferror(xlookup($L26,'Product Families'!$A:$A,'Product Families'!$Q:$Q),"")} | AI26: =iferror(AG26/AH26,"") | AJ26: =iferror(AI26/$E26,"") | AK26: =round($D26*AJ26,2) -> 0
A27: ACSRB | B27: n/a | D27: =iferror(B27/C27,"") | E27: =sum(O27+T27+Y27+AD27+AI27) -> 0 | G27: Made with the Beast | H27: ACSRB | M27: {=iferror(xlookup($H27,'Product Families'!$A:$A,'Product Families'!$P:$P),"")} -> 0.21 | N27: {=iferror(xlookup($H27,'Product Families'!$A:$A,'Product Families'!$Q:$Q),"")} | O27: =iferror(M27/N27,"") | P27: =iferror(O27/$E27,"") | Q27: =round($D27*P27,2) -> 0 | R27: {=iferror(xlookup($I27,'Product Families'!$A:$A,'Product Families'!$P:$P),"")} | S27: {=iferror(xlookup($I27,'Product Families'!$A:$A,'Product Families'!$Q:$Q),"")} | T27: =iferror(R27/S27,"") | U27: =iferror(T27/$E27,"") | V27: =round($D27*U27,2) -> 0 | W27: {=iferror(xlookup($J27,'Product Families'!$A:$A,'Product Families'!$P:$P),"")} | X27: {=iferror(xlookup($J27,'Product Families'!$A:$A,'Product Families'!$Q:$Q),"")} | Y27: =iferror(W27/X27,"") | Z27: =iferror(Y27/$E27,"") | AA27: =round($D27*Z27,2) -> 0 | AB27: {=iferror(xlookup($K27,'Product Families'!$A:$A,'Product Families'!$P:$P),"")} | AC27: {=iferror(xlookup($K27,'Product Families'!$A:$A,'Product Families'!$Q:$Q),"")} | AD27: =iferror(AB27/AC27,"") | AE27: =iferror(AD27/$E27,"") | AF27: =round($D27*AE27,2) -> 0 | AG27: {=iferror(xlookup($L27,'Product Families'!$A:$A,'Product Families'!$P:$P),"")} | AH27: {=iferror(xlookup($L27,'Product Families'!$A:$A,'Product Families'!$Q:$Q),"")} | AI27: =iferror(AG27/AH27,"") | AJ27: =iferror(AI27/$E27,"") | AK27: =round($D27*AJ27,2) -> 0
A28: ACSS | B28: 15.5 | C28: 4 | D28: =iferror(B28/C28,"") -> 3.875 | E28: =sum(O28+T28+Y28+AD28+AI28) -> 0 | H28: ACSS | M28: {=iferror(xlookup($H28,'Product Families'!$A:$A,'Product Families'!$P:$P),"")} -> 0.44 | N28: {=iferror(xlookup($H28,'Product Families'!$A:$A,'Product Families'!$Q:$Q),"")} | O28: =iferror(M28/N28,"") | P28: =iferror(O28/$E28,"") | Q28: =round($D28*P28,2) -> 0 | R28: {=iferror(xlookup($I28,'Product Families'!$A:$A,'Product Families'!$P:$P),"")} | S28: {=iferror(xlookup($I28,'Product Families'!$A:$A,'Product Families'!$Q:$Q),"")} | T28: =iferror(R28/S28,"") | U28: =iferror(T28/$E28,"") | V28: =round($D28*U28,2) -> 0 | W28: {=iferror(xlookup($J28,'Product Families'!$A:$A,'Product Families'!$P:$P),"")} | X28: {=iferror(xlookup($J28,'Product Families'!$A:$A,'Product Families'!$Q:$Q),"")} | Y28: =iferror(W28/X28,"") | Z28: =iferror(Y28/$E28,"") | AA28: =round($D28*Z28,2) -> 0 | AB28: {=iferror(xlookup($K28,'Product Families'!$A:$A,'Product Families'!$P:$P),"")} | AC28: {=iferror(xlookup($K28,'Product Families'!$A:$A,'Product Families'!$Q:$Q),"")} | AD28: =iferror(AB28/AC28,"") | AE28: =iferror(AD28/$E28,"") | AF28: =round($D28*AE28,2) -> 0 | AG28: {=iferror(xlookup($L28,'Product Families'!$A:$A,'Product Families'!$P:$P),"")} | AH28: {=iferror(xlookup($L28,'Product Families'!$A:$A,'Product Families'!$Q:$Q),"")} | AI28: =iferror(AG28/AH28,"") | AJ28: =iferror(AI28/$E28,"") | AK28: =round($D28*AJ28,2) -> 0
A29: ACTEP | B29: 18 | C29: 3 | D29: =iferror(B29/C29,"") -> 6 | E29: =sum(O29+T29+Y29+AD29+AI29) -> 0 | H29: ACTEP | M29: {=iferror(xlookup($H29,'Product Families'!$A:$A,'Product Families'!$P:$P),"")} -> 0.44 | N29: {=iferror(xlookup($H29,'Product Families'!$A:$A,'Product Families'!$Q:$Q),"")} | O29: =iferror(M29/N29,"") | P29: =iferror(O29/$E29,"") | Q29: =round($D29*P29,2) -> 0 | R29: {=iferror(xlookup($I29,'Product Families'!$A:$A,'Product Families'!$P:$P),"")} | S29: {=iferror(xlookup($I29,'Product Families'!$A:$A,'Product Families'!$Q:$Q),"")} | T29: =iferror(R29/S29,"") | U29: =iferror(T29/$E29,"") | V29: =round($D29*U29,2) -> 0 | W29: {=iferror(xlookup($J29,'Product Families'!$A:$A,'Product Families'!$P:$P),"")} | X29: {=iferror(xlookup($J29,'Product Families'!$A:$A,'Product Families'!$Q:$Q),"")} | Y29: =iferror(W29/X29,"") | Z29: =iferror(Y29/$E29,"") | AA29: =round($D29*Z29,2) -> 0 | AB29: {=iferror(xlookup($K29,'Product Families'!$A:$A,'Product Families'!$P:$P),"")} | AC29: {=iferror(xlookup($K29,'Product Families'!$A:$A,'Product Families'!$Q:$Q),"")} | AD29: =iferror(AB29/AC29,"") | AE29: =iferror(AD29/$E29,"") | AF29: =round($D29*AE29,2) -> 0 | AG29: {=iferror(xlookup($L29,'Product Families'!$A:$A,'Product Families'!$P:$P),"")} | AH29: {=iferror(xlookup($L29,'Product Families'!$A:$A,'Product Families'!$Q:$Q),"")} | AI29: =iferror(AG29/AH29,"") | AJ29: =iferror(AI29/$E29,"") | AK29: =round($D29*AJ29,2) -> 0
A30: ACWM | B30: 16 | C30: 4 | D30: =iferror(B30/C30,"") -> 4 | E30: =sum(O30+T30+Y30+AD30+AI30) -> 0 | H30: ACWM | M30: {=iferror(xlookup($H30,'Product Families'!$A:$A,'Product Families'!$P:$P),"")} -> 0.44 | N30: {=iferror(xlookup($H30,'Product Families'!$A:$A,'Product Families'!$Q:$Q),"")} | O30: =iferror(M30/N30,"") | P30: =iferror(O30/$E30,"") | Q30: =round($D30*P30,2) -> 0 | R30: {=iferror(xlookup($I30,'Product Families'!$A:$A,'Product Families'!$P:$P),"")} | S30: {=iferror(xlookup($I30,'Product Families'!$A:$A,'Product Families'!$Q:$Q),"")} | T30: =iferror(R30/S30,"") | U30: =iferror(T30/$E30,"") | V30: =round($D30*U30,2) -> 0 | W30: {=iferror(xlookup($J30,'Product Families'!$A:$A,'Product Families'!$P:$P),"")} | X30: {=iferror(xlookup($J30,'Product Families'!$A:$A,'Product Families'!$Q:$Q),"")} | Y30: =iferror(W30/X30,"") | Z30: =iferror(Y30/$E30,"") | AA30: =round($D30*Z30,2) -> 0 | AB30: {=iferror(xlookup($K30,'Product Families'!$A:$A,'Product Families'!$P:$P),"")} | AC30: {=iferror(xlookup($K30,'Product Families'!$A:$A,'Product Families'!$Q:$Q),"")} | AD30: =iferror(AB30/AC30,"") | AE30: =iferror(AD30/$E30,"") | AF30: =round($D30*AE30,2) -> 0 | AG30: {=iferror(xlookup($L30,'Product Families'!$A:$A,'Product Families'!$P:$P),"")} | AH30: {=iferror(xlookup($L30,'Product Families'!$A:$A,'Product Families'!$Q:$Q),"")} | AI30: =iferror(AG30/AH30,"") | AJ30: =iferror(AI30/$E30,"") | AK30: =round($D30*AJ30,2) -> 0
A31: AHBL | B31: 16.32 | C31: 4 | D31: =iferror(B31/C31,"") -> 4.08 | E31: =sum(O31+T31+Y31+AD31+AI31) -> 0 | M31: {=iferror(xlookup($H31,'Product Families'!$A:$A,'Product Families'!$P:$P),"")} | N31: {=iferror(xlookup($H31,'Product Families'!$A:$A,'Product Families'!$Q:$Q),"")} | O31: =iferror(M31/N31,"") | P31: =iferror(O31/$E31,"") | Q31: =round($D31*P31,2) -> 0 | R31: {=iferror(xlookup($I31,'Product Families'!$A:$A,'Product Families'!$P:$P),"")} | S31: {=iferror(xlookup($I31,'Product Families'!$A:$A,'Product Families'!$Q:$Q),"")} | T31: =iferror(R31/S31,"") | U31: =iferror(T31/$E31,"") | V31: =round($D31*U31,2) -> 0 | W31: {=iferror(xlookup($J31,'Product Families'!$A:$A,'Product Families'!$P:$P),"")} | X31: {=iferror(xlookup($J31,'Product Families'!$A:$A,'Product Families'!$Q:$Q),"")} | Y31: =iferror(W31/X31,"") | Z31: =iferror(Y31/$E31,"") | AA31: =round($D31*Z31,2) -> 0 | AB31: {=iferror(xlookup($K31,'Product Families'!$A:$A,'Product Families'!$P:$P),"")} | AC31: {=iferror(xlookup($K31,'Product Families'!$A:$A,'Product Families'!$Q:$Q),"")} | AD31: =iferror(AB31/AC31,"") | AE31: =iferror(AD31/$E31,"") | AF31: =round($D31*AE31,2) -> 0 | AG31: {=iferror(xlookup($L31,'Product Families'!$A:$A,'Product Families'!$P:$P),"")} | AH31: {=iferror(xlookup($L31,'Product Families'!$A:$A,'Product Families'!$Q:$Q),"")} | AI31: =iferror(AG31/AH31,"") | AJ31: =iferror(AI31/$E31,"") | AK31: =round($D31*AJ31,2) -> 0
A32: AHBLP | B32: n/a | D32: =iferror(B32/C32,"") | E32: =sum(O32+T32+Y32+AD32+AI32) -> 0 | G32: code not in use | M32: {=iferror(xlookup($H32,'Product Families'!$A:$A,'Product Families'!$P:$P),"")} | N32: {=iferror(xlookup($H32,'Product Families'!$A:$A,'Product Families'!$Q:$Q),"")} | O32: =iferror(M32/N32,"") | P32: =iferror(O32/$E32,"") | Q32: =round($D32*P32,2) -> 0 | R32: {=iferror(xlookup($I32,'Product Families'!$A:$A,'Product Families'!$P:$P),"")} | S32: {=iferror(xlookup($I32,'Product Families'!$A:$A,'Product Families'!$Q:$Q),"")} | T32: =iferror(R32/S32,"") | U32: =iferror(T32/$E32,"") | V32: =round($D32*U32,2) -> 0 | W32: {=iferror(xlookup($J32,'Product Families'!$A:$A,'Product Families'!$P:$P),"")} | X32: {=iferror(xlookup($J32,'Product Families'!$A:$A,'Product Families'!$Q:$Q),"")} | Y32: =iferror(W32/X32,"") | Z32: =iferror(Y32/$E32,"") | AA32: =round($D32*Z32,2) -> 0 | AB32: {=iferror(xlookup($K32,'Product Families'!$A:$A,'Product Families'!$P:$P),"")} | AC32: {=iferror(xlookup($K32,'Product Families'!$A:$A,'Product Families'!$Q:$Q),"")} | AD32: =iferror(AB32/AC32,"") | AE32: =iferror(AD32/$E32,"") | AF32: =round($D32*AE32,2) -> 0 | AG32: {=iferror(xlookup($L32,'Product Families'!$A:$A,'Product Families'!$P:$P),"")} | AH32: {=iferror(xlookup($L32,'Product Families'!$A:$A,'Product Families'!$Q:$Q),"")} | AI32: =iferror(AG32/AH32,"") | AJ32: =iferror(AI32/$E32,"") | AK32: =round($D32*AJ32,2) -> 0
A33: AHBLC | B33: n/a | D33: =iferror(B33/C33,"") | E33: =sum(O33+T33+Y33+AD33+AI33) -> 0 | G33: code not in use | M33: {=iferror(xlookup($H33,'Product Families'!$A:$A,'Product Families'!$P:$P),"")} | N33: {=iferror(xlookup($H33,'Product Families'!$A:$A,'Product Families'!$Q:$Q),"")} | O33: =iferror(M33/N33,"") | P33: =iferror(O33/$E33,"") | Q33: =round($D33*P33,2) -> 0 | R33: {=iferror(xlookup($I33,'Product Families'!$A:$A,'Product Families'!$P:$P),"")} | S33: {=iferror(xlookup($I33,'Product Families'!$A:$A,'Product Families'!$Q:$Q),"")} | T33: =iferror(R33/S33,"") | U33: =iferror(T33/$E33,"") | V33: =round($D33*U33,2) -> 0 | W33: {=iferror(xlookup($J33,'Product Families'!$A:$A,'Product Families'!$P:$P),"")} | X33: {=iferror(xlookup($J33,'Product Families'!$A:$A,'Product Families'!$Q:$Q),"")} | Y33: =iferror(W33/X33,"") | Z33: =iferror(Y33/$E33,"") | AA33: =round($D33*Z33,2) -> 0 | AB33: {=iferror(xlookup($K33,'Product Families'!$A:$A,'Product Families'!$P:$P),"")} | AC33: {=iferror(xlookup($K33,'Product Families'!$A:$A,'Product Families'!$Q:$Q),"")} | AD33: =iferror(AB33/AC33,"") | AE33: =iferror(AD33/$E33,"") | AF33: =round($D33*AE33,2) -> 0 | AG33: {=iferror(xlookup($L33,'Product Families'!$A:$A,'Product Families'!$P:$P),"")} | AH33: {=iferror(xlookup($L33,'Product Families'!$A:$A,'Product Families'!$Q:$Q),"")} | AI33: =iferror(AG33/AH33,"") | AJ33: =iferror(AI33/$E33,"") | AK33: =round($D33*AJ33,2) -> 0
A34: AHBLUL | B34: 16.32 | C34: 4 | D34: =iferror(B34/C34,"") -> 4.08 | E34: =sum(O34+T34+Y34+AD34+AI34) -> 0 | M34: {=iferror(xlookup($H34,'Product Families'!$A:$A,'Product Families'!$P:$P),"")} | N34: {=iferror(xlookup($H34,'Product Families'!$A:$A,'Product Families'!$Q:$Q),"")} | O34: =iferror(M34/N34,"") | P34: =iferror(O34/$E34,"") | Q34: =round($D34*P34,2) -> 0 | R34: {=iferror(xlookup($I34,'Product Families'!$A:$A,'Product Families'!$P:$P),"")} | S34: {=iferror(xlookup($I34,'Product Families'!$A:$A,'Product Families'!$Q:$Q),"")} | T34: =iferror(R34/S34,"") | U34: =iferror(T34/$E34,"") | V34: =round($D34*U34,2) -> 0 | W34: {=iferror(xlookup($J34,'Product Families'!$A:$A,'Product Families'!$P:$P),"")} | X34: {=iferror(xlookup($J34,'Product Families'!$A:$A,'Product Families'!$Q:$Q),"")} | Y34: =iferror(W34/X34,"") | Z34: =iferror(Y34/$E34,"") | AA34: =round($D34*Z34,2) -> 0 | AB34: {=iferror(xlookup($K34,'Product Families'!$A:$A,'Product Families'!$P:$P),"")} | AC34: {=iferror(xlookup($K34,'Product Families'!$A:$A,'Product Families'!$Q:$Q),"")} | AD34: =iferror(AB34/AC34,"") | AE34: =iferror(AD34/$E34,"") | AF34: =round($D34*AE34,2) -> 0 | AG34: {=iferror(xlookup($L34,'Product Families'!$A:$A,'Product Families'!$P:$P),"")} | AH34: {=iferror(xlookup($L34,'Product Families'!$A:$A,'Product Families'!$Q:$Q),"")} | AI34: =iferror(AG34/AH34,"") | AJ34: =iferror(AI34/$E34,"") | AK34: =round($D34*AJ34,2) -> 0
A35: AHBW | B35: 14.84 | C35: 4 | D35: =iferror(B35/C35,"") -> 3.71 | E35: =sum(O35+T35+Y35+AD35+AI35) -> 0 | M35: {=iferror(xlookup($H35,'Product Families'!$A:$A,'Product Families'!$P:$P),"")} | N35: {=iferror(xlookup($H35,'Product Families'!$A:$A,'Product Families'!$Q:$Q),"")} | O35: =iferror(M35/N35,"") | P35: =iferror(O35/$E35,"") | Q35: =round($D35*P35,2) -> 0 | R35: {=iferror(xlookup($I35,'Product Families'!$A:$A,'Product Families'!$P:$P),"")} | S35: {=iferror(xlookup($I35,'Product Families'!$A:$A,'Product Families'!$Q:$Q),"")} | T35: =iferror(R35/S35,"") | U35: =iferror(T35/$E35,"") | V35: =round($D35*U35,2) -> 0 | W35: {=iferror(xlookup($J35,'Product Families'!$A:$A,'Product Families'!$P:$P),"")} | X35: {=iferror(xlookup($J35,'Product Families'!$A:$A,'Product Families'!$Q:$Q),"")} | Y35: =iferror(W35/X35,"") | Z35: =iferror(Y35/$E35,"") | AA35: =round($D35*Z35,2) -> 0 | AB35: {=iferror(xlookup($K35,'Product Families'!$A:$A,'Product Families'!$P:$P),"")} | AC35: {=iferror(xlookup($K35,'Product Families'!$A:$A,'Product Families'!$Q:$Q),"")} | AD35: =iferror(AB35/AC35,"") | AE35: =iferror(AD35/$E35,"") | AF35: =round($D35*AE35,2) -> 0 | AG35: {=iferror(xlookup($L35,'Product Families'!$A:$A,'Product Families'!$P:$P),"")} | AH35: {=iferror(xlookup($L35,'Product Families'!$A:$A,'Product Families'!$Q:$Q),"")} | AI35: =iferror(AG35/AH35,"") | AJ35: =iferror(AI35/$E35,"") | AK35: =round($D35*AJ35,2) -> 0
A36: AHBWB | B36: 25.13 | C36: 1 | D36: =iferror(B36/C36,"") -> 25.13 | E36: =sum(O36+T36+Y36+AD36+AI36) -> 0 | M36: {=iferror(xlookup($H36,'Product Families'!$A:$A,'Product Families'!$P:$P),"")} | N36: {=iferror(xlookup($H36,'Product Families'!$A:$A,'Product Families'!$Q:$Q),"")} | O36: =iferror(M36/N36,"") | P36: =iferror(O36/$E36,"") | Q36: =round($D36*P36,2) -> 0 | R36: {=iferror(xlookup($I36,'Product Families'!$A:$A,'Product Families'!$P:$P),"")} | S36: {=iferror(xlookup($I36,'Product Families'!$A:$A,'Product Families'!$Q:$Q),"")} | T36: =iferror(R36/S36,"") | U36: =iferror(T36/$E36,"") | V36: =round($D36*U36,2) -> 0 | W36: {=iferror(xlookup($J36,'Product Families'!$A:$A,'Product Families'!$P:$P),"")} | X36: {=iferror(xlookup($J36,'Product Families'!$A:$A,'Product Families'!$Q:$Q),"")} | Y36: =iferror(W36/X36,"") | Z36: =iferror(Y36/$E36,"") | AA36: =round($D36*Z36,2) -> 0 | AB36: {=iferror(xlookup($K36,'Product Families'!$A:$A,'Product Families'!$P:$P),"")} | AC36: {=iferror(xlookup($K36,'Product Families'!$A:$A,'Product Families'!$Q:$Q),"")} | AD36: =iferror(AB36/AC36,"") | AE36: =iferror(AD36/$E36,"") | AF36: =round($D36*AE36,2) -> 0 | AG36: {=iferror(xlookup($L36,'Product Families'!$A:$A,'Product Families'!$P:$P),"")} | AH36: {=iferror(xlookup($L36,'Product Families'!$A:$A,'Product Families'!$Q:$Q),"")} | AI36: =iferror(AG36/AH36,"") | AJ36: =iferror(AI36/$E36,"") | AK36: =round($D36*AJ36,2) -> 0
A37: AHBWP | B37: n/a | D37: =iferror(B37/C37,"") | E37: =sum(O37+T37+Y37+AD37+AI37) -> 0 | G37: code not in use | M37: {=iferror(xlookup($H37,'Product Families'!$A:$A,'Product Families'!$P:$P),"")} | N37: {=iferror(xlookup($H37,'Product Families'!$A:$A,'Product Families'!$Q:$Q),"")} | O37: =iferror(M37/N37,"") | P37: =iferror(O37/$E37,"") | Q37: =round($D37*P37,2) -> 0 | R37: {=iferror(xlookup($I37,'Product Families'!$A:$A,'Product Families'!$P:$P),"")} | S37: {=iferror(xlookup($I37,'Product Families'!$A:$A,'Product Families'!$Q:$Q),"")} | T37: =iferror(R37/S37,"") | U37: =iferror(T37/$E37,"") | V37: =round($D37*U37,2) -> 0 | W37: {=iferror(xlookup($J37,'Product Families'!$A:$A,'Product Families'!$P:$P),"")} | X37: {=iferror(xlookup($J37,'Product Families'!$A:$A,'Product Families'!$Q:$Q),"")} | Y37: =iferror(W37/X37,"") | Z37: =iferror(Y37/$E37,"") | AA37: =round($D37*Z37,2) -> 0 | AB37: {=iferror(xlookup($K37,'Product Families'!$A:$A,'Product Families'!$P:$P),"")} | AC37: {=iferror(xlookup($K37,'Product Families'!$A:$A,'Product Families'!$Q:$Q),"")} | AD37: =iferror(AB37/AC37,"") | AE37: =iferror(AD37/$E37,"") | AF37: =round($D37*AE37,2) -> 0 | AG37: {=iferror(xlookup($L37,'Product Families'!$A:$A,'Product Families'!$P:$P),"")} | AH37: {=iferror(xlookup($L37,'Product Families'!$A:$A,'Product Families'!$Q:$Q),"")} | AI37: =iferror(AG37/AH37,"") | AJ37: =iferror(AI37/$E37,"") | AK37: =round($D37*AJ37,2) -> 0
A38: AHBWUL | B38: 14.84 | C38: 4 | D38: =iferror(B38/C38,"") -> 3.71 | E38: =sum(O38+T38+Y38+AD38+AI38) -> 0 | M38: {=iferror(xlookup($H38,'Product Families'!$A:$A,'Product Families'!$P:$P),"")} | N38: {=iferror(xlookup($H38,'Product Families'!$A:$A,'Product Families'!$Q:$Q),"")} | O38: =iferror(M38/N38,"") | P38: =iferror(O38/$E38,"") | Q38: =round($D38*P38,2) -> 0 | R38: {=iferror(xlookup($I38,'Product Families'!$A:$A,'Product Families'!$P:$P),"")} | S38: {=iferror(xlookup($I38,'Product Families'!$A:$A,'Product Families'!$Q:$Q),"")} | T38: =iferror(R38/S38,"") | U38: =iferror(T38/$E38,"") | V38: =round($D38*U38,2) -> 0 | W38: {=iferror(xlookup($J38,'Product Families'!$A:$A,'Product Families'!$P:$P),"")} | X38: {=iferror(xlookup($J38,'Product Families'!$A:$A,'Product Families'!$Q:$Q),"")} | Y38: =iferror(W38/X38,"") | Z38: =iferror(Y38/$E38,"") | AA38: =round($D38*Z38,2) -> 0 | AB38: {=iferror(xlookup($K38,'Product Families'!$A:$A,'Product Families'!$P:$P),"")} | AC38: {=iferror(xlookup($K38,'Product Families'!$A:$A,'Product Families'!$Q:$Q),"")} | AD38: =iferror(AB38/AC38,"") | AE38: =iferror(AD38/$E38,"") | AF38: =round($D38*AE38,2) -> 0 | AG38: {=iferror(xlookup($L38,'Product Families'!$A:$A,'Product Families'!$P:$P),"")} | AH38: {=iferror(xlookup($L38,'Product Families'!$A:$A,'Product Families'!$Q:$Q),"")} | AI38: =iferror(AG38/AH38,"") | AJ38: =iferror(AI38/$E38,"") | AK38: =round($D38*AJ38,2) -> 0
A39: AHBWULC | B39: n/a | D39: =iferror(B39/C39,"") | E39: =sum(O39+T39+Y39+AD39+AI39) -> 0 | G39: code not in use | M39: {=iferror(xlookup($H39,'Product Families'!$A:$A,'Product Families'!$P:$P),"")} | N39: {=iferror(xlookup($H39,'Product Families'!$A:$A,'Product Families'!$Q:$Q),"")} | O39: =iferror(M39/N39,"") | P39: =iferror(O39/$E39,"") | Q39: =round($D39*P39,2) -> 0 | R39: {=iferror(xlookup($I39,'Product Families'!$A:$A,'Product Families'!$P:$P),"")} | S39: {=iferror(xlookup($I39,'Product Families'!$A:$A,'Product Families'!$Q:$Q),"")} | T39: =iferror(R39/S39,"") | U39: =iferror(T39/$E39,"") | V39: =round($D39*U39,2) -> 0 | W39: {=iferror(xlookup($J39,'Product Families'!$A:$A,'Product Families'!$P:$P),"")} | X39: {=iferror(xlookup($J39,'Product Families'!$A:$A,'Product Families'!$Q:$Q),"")} | Y39: =iferror(W39/X39,"") | Z39: =iferror(Y39/$E39,"") | AA39: =round($D39*Z39,2) -> 0 | AB39: {=iferror(xlookup($K39,'Product Families'!$A:$A,'Product Families'!$P:$P),"")} | AC39: {=iferror(xlookup($K39,'Product Families'!$A:$A,'Product Families'!$Q:$Q),"")} | AD39: =iferror(AB39/AC39,"") | AE39: =iferror(AD39/$E39,"") | AF39: =round($D39*AE39,2) -> 0 | AG39: {=iferror(xlookup($L39,'Product Families'!$A:$A,'Product Families'!$P:$P),"")} | AH39: {=iferror(xlookup($L39,'Product Families'!$A:$A,'Product Families'!$Q:$Q),"")} | AI39: =iferror(AG39/AH39,"") | AJ39: =iferror(AI39/$E39,"") | AK39: =round($D39*AJ39,2) -> 0
A40: AHBLC | B40: n/a | D40: =iferror(B40/C40,"") | E40: =sum(O40+T40+Y40+AD40+AI40) -> 0 | G40: code not in use | M40: {=iferror(xlookup($H40,'Product Families'!$A:$A,'Product Families'!$P:$P),"")} | N40: {=iferror(xlookup($H40,'Product Families'!$A:$A,'Product Families'!$Q:$Q),"")} | O40: =iferror(M40/N40,"") | P40: =iferror(O40/$E40,"") | Q40: =round($D40*P40,2) -> 0 | R40: {=iferror(xlookup($I40,'Product Families'!$A:$A,'Product Families'!$P:$P),"")} | S40: {=iferror(xlookup($I40,'Product Families'!$A:$A,'Product Families'!$Q:$Q),"")} | T40: =iferror(R40/S40,"") | U40: =iferror(T40/$E40,"") | V40: =round($D40*U40,2) -> 0 | W40: {=iferror(xlookup($J40,'Product Families'!$A:$A,'Product Families'!$P:$P),"")} | X40: {=iferror(xlookup($J40,'Product Families'!$A:$A,'Product Families'!$Q:$Q),"")} | Y40: =iferror(W40/X40,"") | Z40: =iferror(Y40/$E40,"") | AA40: =round($D40*Z40,2) -> 0 | AB40: {=iferror(xlookup($K40,'Product Families'!$A:$A,'Product Families'!$P:$P),"")} | AC40: {=iferror(xlookup($K40,'Product Families'!$A:$A,'Product Families'!$Q:$Q),"")} | AD40: =iferror(AB40/AC40,"") | AE40: =iferror(AD40/$E40,"") | AF40: =round($D40*AE40,2) -> 0 | AG40: {=iferror(xlookup($L40,'Product Families'!$A:$A,'Product Families'!$P:$P),"")} | AH40: {=iferror(xlookup($L40,'Product Families'!$A:$A,'Product Families'!$Q:$Q),"")} | AI40: =iferror(AG40/AH40,"") | AJ40: =iferror(AI40/$E40,"") | AK40: =round($D40*AJ40,2) -> 0
A41: AROSS | B41: 12.38 | C41: 16 | D41: =iferror(B41/C41,"") -> 0.77375 | E41: =sum(O41+T41+Y41+AD41+AI41) -> 0 | H41: AROSS | I41: AROSSP | M41: {=iferror(xlookup($H41,'Product Families'!$A:$A,'Product Families'!$P:$P),"")} -> 0.05 | N41: {=iferror(xlookup($H41,'Product Families'!$A:$A,'Product Families'!$Q:$Q),"")} | O41: =iferror(M41/N41,"") | P41: =iferror(O41/$E41,"") | Q41: =round($D41*P41,2) -> 0 | R41: {=iferror(xlookup($I41,'Product Families'!$A:$A,'Product Families'!$P:$P),"")} -> 0.37 | S41: {=iferror(xlookup($I41,'Product Families'!$A:$A,'Product Families'!$Q:$Q),"")} | T41: =iferror(R41/S41,"") | U41: =iferror(T41/$E41,"") | V41: =round($D41*U41,2) -> 0 | W41: {=iferror(xlookup($J41,'Product Families'!$A:$A,'Product Families'!$P:$P),"")} | X41: {=iferror(xlookup($J41,'Product Families'!$A:$A,'Product Families'!$Q:$Q),"")} | Y41: =iferror(W41/X41,"") | Z41: =iferror(Y41/$E41,"") | AA41: =round($D41*Z41,2) -> 0 | AB41: {=iferror(xlookup($K41,'Product Families'!$A:$A,'Product Families'!$P:$P),"")} | AC41: {=iferror(xlookup($K41,'Product Families'!$A:$A,'Product Families'!$Q:$Q),"")} | AD41: =iferror(AB41/AC41,"") | AE41: =iferror(AD41/$E41,"") | AF41: =round($D41*AE41,2) -> 0 | AG41: {=iferror(xlookup($L41,'Product Families'!$A:$A,'Product Families'!$P:$P),"")} | AH41: {=iferror(xlookup($L41,'Product Families'!$A:$A,'Product Families'!$Q:$Q),"")} | AI41: =iferror(AG41/AH41,"") | AJ41: =iferror(AI41/$E41,"") | AK41: =round($D41*AJ41,2) -> 0
A42: ArtS | B42: offline | D42: =iferror(B42/C42,"") | E42: =sum(O42+T42+Y42+AD42+AI42) -> 0 | G42: AW only | H42: ArtS | M42: {=iferror(xlookup($H42,'Product Families'!$A:$A,'Product Families'!$P:$P),"")} -> 0.05 | N42: {=iferror(xlookup($H42,'Product Families'!$A:$A,'Product Families'!$Q:$Q),"")} | O42: =iferror(M42/N42,"") | P42: =iferror(O42/$E42,"") | Q42: =round($D42*P42,2) -> 0 | R42: {=iferror(xlookup($I42,'Product Families'!$A:$A,'Product Families'!$P:$P),"")} | S42: {=iferror(xlookup($I42,'Product Families'!$A:$A,'Product Families'!$Q:$Q),"")} | T42: =iferror(R42/S42,"") | U42: =iferror(T42/$E42,"") | V42: =round($D42*U42,2) -> 0 | W42: {=iferror(xlookup($J42,'Product Families'!$A:$A,'Product Families'!$P:$P),"")} | X42: {=iferror(xlookup($J42,'Product Families'!$A:$A,'Product Families'!$Q:$Q),"")} | Y42: =iferror(W42/X42,"") | Z42: =iferror(Y42/$E42,"") | AA42: =round($D42*Z42,2) -> 0 | AB42: {=iferror(xlookup($K42,'Product Families'!$A:$A,'Product Families'!$P:$P),"")} | AC42: {=iferror(xlookup($K42,'Product Families'!$A:$A,'Product Families'!$Q:$Q),"")} | AD42: =iferror(AB42/AC42,"") | AE42: =iferror(AD42/$E42,"") | AF42: =round($D42*AE42,2) -> 0 | AG42: {=iferror(xlookup($L42,'Product Families'!$A:$A,'Product Families'!$P:$P),"")} | AH42: {=iferror(xlookup($L42,'Product Families'!$A:$A,'Product Families'!$Q:$Q),"")} | AI42: =iferror(AG42/AH42,"") | AJ42: =iferror(AI42/$E42,"") | AK42: =round($D42*AJ42,2) -> 0
A43: Asoap | B43: offline | D43: =iferror(B43/C43,"") | E43: =sum(O43+T43+Y43+AD43+AI43) -> 0 | G43: Discontinued | H43: Asoap | I43: AsoapP | M43: {=iferror(xlookup($H43,'Product Families'!$A:$A,'Product Families'!$P:$P),"")} -> 0.44 | N43: {=iferror(xlookup($H43,'Product Families'!$A:$A,'Product Families'!$Q:$Q),"")} | O43: =iferror(M43/N43,"") | P43: =iferror(O43/$E43,"") | Q43: =round($D43*P43,2) -> 0 | R43: {=iferror(xlookup($I43,'Product Families'!$A:$A,'Product Families'!$P:$P),"")} -> 0.19 | S43: {=iferror(xlookup($I43,'Product Families'!$A:$A,'Product Families'!$Q:$Q),"")} | T43: =iferror(R43/S43,"") | U43: =iferror(T43/$E43,"") | V43: =round($D43*U43,2) -> 0 | W43: {=iferror(xlookup($J43,'Product Families'!$A:$A,'Product Families'!$P:$P),"")} | X43: {=iferror(xlookup($J43,'Product Families'!$A:$A,'Product Families'!$Q:$Q),"")} | Y43: =iferror(W43/X43,"") | Z43: =iferror(Y43/$E43,"") | AA43: =round($D43*Z43,2) -> 0 | AB43: {=iferror(xlookup($K43,'Product Families'!$A:$A,'Product Families'!$P:$P),"")} | AC43: {=iferror(xlookup($K43,'Product Families'!$A:$A,'Product Families'!$Q:$Q),"")} | AD43: =iferror(AB43/AC43,"") | AE43: =iferror(AD43/$E43,"") | AF43: =round($D43*AE43,2) -> 0 | AG43: {=iferror(xlookup($L43,'Product Families'!$A:$A,'Product Families'!$P:$P),"")} | AH43: {=iferror(xlookup($L43,'Product Families'!$A:$A,'Product Families'!$Q:$Q),"")} | AI43: =iferror(AG43/AH43,"") | AJ43: =iferror(AI43/$E43,"") | AK43: =round($D43*AJ43,2) -> 0
A44: AVENA | B44: n/a | D44: =iferror(B44/C44,"") | E44: =sum(O44+T44+Y44+AD44+AI44) -> 0 | G44: bespoke | H44: AVENA | I44: AVENAP | M44: {=iferror(xlookup($H44,'Product Families'!$A:$A,'Product Families'!$P:$P),"")} -> 0.18 | N44: {=iferror(xlookup($H44,'Product Families'!$A:$A,'Product Families'!$Q:$Q),"")} | O44: =iferror(M44/N44,"") | P44: =iferror(O44/$E44,"") | Q44: =round($D44*P44,2) -> 0 | R44: {=iferror(xlookup($I44,'Product Families'!$A:$A,'Product Families'!$P:$P),"")} -> 0.31 | S44: {=iferror(xlookup($I44,'Product Families'!$A:$A,'Product Families'!$Q:$Q),"")} | T44: =iferror(R44/S44,"") | U44: =iferror(T44/$E44,"") | V44: =round($D44*U44,2) -> 0 | W44: {=iferror(xlookup($J44,'Product Families'!$A:$A,'Product Families'!$P:$P),"")} | X44: {=iferror(xlookup($J44,'Product Families'!$A:$A,'Product Families'!$Q:$Q),"")} | Y44: =iferror(W44/X44,"") | Z44: =iferror(Y44/$E44,"") | AA44: =round($D44*Z44,2) -> 0 | AB44: {=iferror(xlookup($K44,'Product Families'!$A:$A,'Product Families'!$P:$P),"")} | AC44: {=iferror(xlookup($K44,'Product Families'!$A:$A,'Product Families'!$Q:$Q),"")} | AD44: =iferror(AB44/AC44,"") | AE44: =iferror(AD44/$E44,"") | AF44: =round($D44*AE44,2) -> 0 | AG44: {=iferror(xlookup($L44,'Product Families'!$A:$A,'Product Families'!$P:$P),"")} | AH44: {=iferror(xlookup($L44,'Product Families'!$A:$A,'Product Families'!$Q:$Q),"")} | AI44: =iferror(AG44/AH44,"") | AJ44: =iferror(AI44/$E44,"") | AK44: =round($D44*AJ44,2) -> 0
A45: AWChill | B45: 9.95 | C45: 1 | D45: =iferror(B45/C45,"") -> 9.95 | E45: =sum(O45+T45+Y45+AD45+AI45) -> 0 | H45: AWChill | I45: AWChillP | M45: {=iferror(xlookup($H45,'Product Families'!$A:$A,'Product Families'!$P:$P),"")} -> 1.15 | N45: {=iferror(xlookup($H45,'Product Families'!$A:$A,'Product Families'!$Q:$Q),"")} | O45: =iferror(M45/N45,"") | P45: =iferror(O45/$E45,"") | Q45: =round($D45*P45,2) -> 0 | R45: {=iferror(xlookup($I45,'Product Families'!$A:$A,'Product Families'!$P:$P),"")} -> 0.39 | S45: {=iferror(xlookup($I45,'Product Families'!$A:$A,'Product Families'!$Q:$Q),"")} | T45: =iferror(R45/S45,"") | U45: =iferror(T45/$E45,"") | V45: =round($D45*U45,2) -> 0 | W45: {=iferror(xlookup($J45,'Product Families'!$A:$A,'Product Families'!$P:$P),"")} | X45: {=iferror(xlookup($J45,'Product Families'!$A:$A,'Product Families'!$Q:$Q),"")} | Y45: =iferror(W45/X45,"") | Z45: =iferror(Y45/$E45,"") | AA45: =round($D45*Z45,2) -> 0 | AB45: {=iferror(xlookup($K45,'Product Families'!$A:$A,'Product Families'!$P:$P),"")} | AC45: {=iferror(xlookup($K45,'Product Families'!$A:$A,'Product Families'!$Q:$Q),"")} | AD45: =iferror(AB45/AC45,"") | AE45: =iferror(AD45/$E45,"") | AF45: =round($D45*AE45,2) -> 0 | AG45: {=iferror(xlookup($L45,'Product Families'!$A:$A,'Product Families'!$P:$P),"")} | AH45: {=iferror(xlookup($L45,'Product Families'!$A:$A,'Product Families'!$Q:$Q),"")} | AI45: =iferror(AG45/AH45,"") | AJ45: =iferror(AI45/$E45,"") | AK45: =round($D45*AJ45,2) -> 0
A46: AWEBL | B46: 1.17 - 3.92 | D46: =iferror(B46/C46,"") | E46: =sum(O46+T46+Y46+AD46+AI46) -> 0 | G46: 8 different prices | M46: {=iferror(xlookup($H46,'Product Families'!$A:$A,'Product Families'!$P:$P),"")} | N46: {=iferror(xlookup($H46,'Product Families'!$A:$A,'Product Families'!$Q:$Q),"")} | O46: =iferror(M46/N46,"") | P46: =iferror(O46/$E46,"") | Q46: =round($D46*P46,2) -> 0 | R46: {=iferror(xlookup($I46,'Product Families'!$A:$A,'Product Families'!$P:$P),"")} | S46: {=iferror(xlookup($I46,'Product Families'!$A:$A,'Product Families'!$Q:$Q),"")} | T46: =iferror(R46/S46,"") | U46: =iferror(T46/$E46,"") | V46: =round($D46*U46,2) -> 0 | W46: {=iferror(xlookup($J46,'Product Families'!$A:$A,'Product Families'!$P:$P),"")} | X46: {=iferror(xlookup($J46,'Product Families'!$A:$A,'Product Families'!$Q:$Q),"")} | Y46: =iferror(W46/X46,"") | Z46: =iferror(Y46/$E46,"") | AA46: =round($D46*Z46,2) -> 0 | AB46: {=iferror(xlookup($K46,'Product Families'!$A:$A,'Product Families'!$P:$P),"")} | AC46: {=iferror(xlookup($K46,'Product Families'!$A:$A,'Product Families'!$Q:$Q),"")} | AD46: =iferror(AB46/AC46,"") | AE46: =iferror(AD46/$E46,"") | AF46: =round($D46*AE46,2) -> 0 | AG46: {=iferror(xlookup($L46,'Product Families'!$A:$A,'Product Families'!$P:$P),"")} | AH46: {=iferror(xlookup($L46,'Product Families'!$A:$A,'Product Families'!$Q:$Q),"")} | AI46: =iferror(AG46/AH46,"") | AJ46: =iferror(AI46/$E46,"") | AK46: =round($D46*AJ46,2) -> 0
A47: AWEBLUL | B47: n/a | D47: =iferror(B47/C47,"") | E47: =sum(O47+T47+Y47+AD47+AI47) -> 0 | G47: code not in use | M47: {=iferror(xlookup($H47,'Product Families'!$A:$A,'Product Families'!$P:$P),"")} | N47: {=iferror(xlookup($H47,'Product Families'!$A:$A,'Product Families'!$Q:$Q),"")} | O47: =iferror(M47/N47,"") | P47: =iferror(O47/$E47,"") | Q47: =round($D47*P47,2) -> 0 | R47: {=iferror(xlookup($I47,'Product Families'!$A:$A,'Product Families'!$P:$P),"")} | S47: {=iferror(xlookup($I47,'Product Families'!$A:$A,'Product Families'!$Q:$Q),"")} | T47: =iferror(R47/S47,"") | U47: =iferror(T47/$E47,"") | V47: =round($D47*U47,2) -> 0 | W47: {=iferror(xlookup($J47,'Product Families'!$A:$A,'Product Families'!$P:$P),"")} | X47: {=iferror(xlookup($J47,'Product Families'!$A:$A,'Product Families'!$Q:$Q),"")} | Y47: =iferror(W47/X47,"") | Z47: =iferror(Y47/$E47,"") | AA47: =round($D47*Z47,2) -> 0 | AB47: {=iferror(xlookup($K47,'Product Families'!$A:$A,'Product Families'!$P:$P),"")} | AC47: {=iferror(xlookup($K47,'Product Families'!$A:$A,'Product Families'!$Q:$Q),"")} | AD47: =iferror(AB47/AC47,"") | AE47: =iferror(AD47/$E47,"") | AF47: =round($D47*AE47,2) -> 0 | AG47: {=iferror(xlookup($L47,'Product Families'!$A:$A,'Product Families'!$P:$P),"")} | AH47: {=iferror(xlookup($L47,'Product Families'!$A:$A,'Product Families'!$Q:$Q),"")} | AI47: =iferror(AG47/AH47,"") | AJ47: =iferror(AI47/$E47,"") | AK47: =round($D47*AJ47,2) -> 0
A48: AWFO | B48: 6.31 | C48: 10 | D48: =iferror(B48/C48,"") -> 0.631 | E48: =sum(O48+T48+Y48+AD48+AI48) -> 0 | H48: AWFO | M48: {=iferror(xlookup($H48,'Product Families'!$A:$A,'Product Families'!$P:$P),"")} -> 0.71 | N48: {=iferror(xlookup($H48,'Product Families'!$A:$A,'Product Families'!$Q:$Q),"")} | O48: =iferror(M48/N48,"") | P48: =iferror(O48/$E48,"") | Q48: =round($D48*P48,2) -> 0 | R48: {=iferror(xlookup($I48,'Product Families'!$A:$A,'Product Families'!$P:$P),"")} | S48: {=iferror(xlookup($I48,'Product Families'!$A:$A,'Product Families'!$Q:$Q),"")} | T48: =iferror(R48/S48,"") | U48: =iferror(T48/$E48,"") | V48: =round($D48*U48,2) -> 0 | W48: {=iferror(xlookup($J48,'Product Families'!$A:$A,'Product Families'!$P:$P),"")} | X48: {=iferror(xlookup($J48,'Product Families'!$A:$A,'Product Families'!$Q:$Q),"")} | Y48: =iferror(W48/X48,"") | Z48: =iferror(Y48/$E48,"") | AA48: =round($D48*Z48,2) -> 0 | AB48: {=iferror(xlookup($K48,'Product Families'!$A:$A,'Product Families'!$P:$P),"")} | AC48: {=iferror(xlookup($K48,'Product Families'!$A:$A,'Product Families'!$Q:$Q),"")} | AD48: =iferror(AB48/AC48,"") | AE48: =iferror(AD48/$E48,"") | AF48: =round($D48*AE48,2) -> 0 | AG48: {=iferror(xlookup($L48,'Product Families'!$A:$A,'Product Families'!$P:$P),"")} | AH48: {=iferror(xlookup($L48,'Product Families'!$A:$A,'Product Families'!$Q:$Q),"")} | AI48: =iferror(AG48/AH48,"") | AJ48: =iferror(AI48/$E48,"") | AK48: =round($D48*AJ48,2) -> 0
A49: AWFOT | B49: n/a | D49: =iferror(B49/C49,"") | E49: =sum(O49+T49+Y49+AD49+AI49) -> 0 | G49: code not in use | H49: AWFOT | M49: {=iferror(xlookup($H49,'Product Families'!$A:$A,'Product Families'!$P:$P),"")} -> 0.88 | N49: {=iferror(xlookup($H49,'Product Families'!$A:$A,'Product Families'!$Q:$Q),"")} | O49: =iferror(M49/N49,"") | P49: =iferror(O49/$E49,"") | Q49: =round($D49*P49,2) -> 0 | R49: {=iferror(xlookup($I49,'Product Families'!$A:$A,'Product Families'!$P:$P),"")} | S49: {=iferror(xlookup($I49,'Product Families'!$A:$A,'Product Families'!$Q:$Q),"")} | T49: =iferror(R49/S49,"") | U49: =iferror(T49/$E49,"") | V49: =round($D49*U49,2) -> 0 | W49: {=iferror(xlookup($J49,'Product Families'!$A:$A,'Product Families'!$P:$P),"")} | X49: {=iferror(xlookup($J49,'Product Families'!$A:$A,'Product Families'!$Q:$Q),"")} | Y49: =iferror(W49/X49,"") | Z49: =iferror(Y49/$E49,"") | AA49: =round($D49*Z49,2) -> 0 | AB49: {=iferror(xlookup($K49,'Product Families'!$A:$A,'Product Families'!$P:$P),"")} | AC49: {=iferror(xlookup($K49,'Product Families'!$A:$A,'Product Families'!$Q:$Q),"")} | AD49: =iferror(AB49/AC49,"") | AE49: =iferror(AD49/$E49,"") | AF49: =round($D49*AE49,2) -> 0 | AG49: {=iferror(xlookup($L49,'Product Families'!$A:$A,'Product Families'!$P:$P),"")} | AH49: {=iferror(xlookup($L49,'Product Families'!$A:$A,'Product Families'!$Q:$Q),"")} | AI49: =iferror(AG49/AH49,"") | AJ49: =iferror(AI49/$E49,"") | AK49: =round($D49*AJ49,2) -> 0
A50: AWGSOAP | B50: 23.32 | C50: 100 | D50: =iferror(B50/C50,"") -> 0.2332 | E50: =sum(O50+T50+Y50+AD50+AI50) -> 0 | H50: AWGSOAP | M50: {=iferror(xlookup($H50,'Product Families'!$A:$A,'Product Families'!$P:$P),"")} -> 2.5 | N50: {=iferror(xlookup($H50,'Product Families'!$A:$A,'Product Families'!$Q:$Q),"")} | O50: =iferror(M50/N50,"") | P50: =iferror(O50/$E50,"") | Q50: =round($D50*P50,2) -> 0 | R50: {=iferror(xlookup($I50,'Product Families'!$A:$A,'Product Families'!$P:$P),"")} | S50: {=iferror(xlookup($I50,'Product Families'!$A:$A,'Product Families'!$Q:$Q),"")} | T50: =iferror(R50/S50,"") | U50: =iferror(T50/$E50,"") | V50: =round($D50*U50,2) -> 0 | W50: {=iferror(xlookup($J50,'Product Families'!$A:$A,'Product Families'!$P:$P),"")} | X50: {=iferror(xlookup($J50,'Product Families'!$A:$A,'Product Families'!$Q:$Q),"")} | Y50: =iferror(W50/X50,"") | Z50: =iferror(Y50/$E50,"") | AA50: =round($D50*Z50,2) -> 0 | AB50: {=iferror(xlookup($K50,'Product Families'!$A:$A,'Product Families'!$P:$P),"")} | AC50: {=iferror(xlookup($K50,'Product Families'!$A:$A,'Product Families'!$Q:$Q),"")} | AD50: =iferror(AB50/AC50,"") | AE50: =iferror(AD50/$E50,"") | AF50: =round($D50*AE50,2) -> 0 | AG50: {=iferror(xlookup($L50,'Product Families'!$A:$A,'Product Families'!$P:$P),"")} | AH50: {=iferror(xlookup($L50,'Product Families'!$A:$A,'Product Families'!$Q:$Q),"")} | AI50: =iferror(AG50/AH50,"") | AJ50: =iferror(AI50/$E50,"") | AK50: =round($D50*AJ50,2) -> 0
A51: AWGSOAP1 | B51: n/a | D51: =iferror(B51/C51,"") | E51: =sum(O51+T51+Y51+AD51+AI51) -> 0 | G51: Problems with machine | H51: AWGSOAP1 | M51: {=iferror(xlookup($H51,'Product Families'!$A:$A,'Product Families'!$P:$P),"")} -> 3 | N51: {=iferror(xlookup($H51,'Product Families'!$A:$A,'Product Families'!$Q:$Q),"")} | O51: =iferror(M51/N51,"") | P51: =iferror(O51/$E51,"") | Q51: =round($D51*P51,2) -> 0 | R51: {=iferror(xlookup($I51,'Product Families'!$A:$A,'Product Families'!$P:$P),"")} | S51: {=iferror(xlookup($I51,'Product Families'!$A:$A,'Product Families'!$Q:$Q),"")} | T51: =iferror(R51/S51,"") | U51: =iferror(T51/$E51,"") | V51: =round($D51*U51,2) -> 0 | W51: {=iferror(xlookup($J51,'Product Families'!$A:$A,'Product Families'!$P:$P),"")} | X51: {=iferror(xlookup($J51,'Product Families'!$A:$A,'Product Families'!$Q:$Q),"")} | Y51: =iferror(W51/X51,"") | Z51: =iferror(Y51/$E51,"") | AA51: =round($D51*Z51,2) -> 0 | AB51: {=iferror(xlookup($K51,'Product Families'!$A:$A,'Product Families'!$P:$P),"")} | AC51: {=iferror(xlookup($K51,'Product Families'!$A:$A,'Product Families'!$Q:$Q),"")} | AD51: =iferror(AB51/AC51,"") | AE51: =iferror(AD51/$E51,"") | AF51: =round($D51*AE51,2) -> 0 | AG51: {=iferror(xlookup($L51,'Product Families'!$A:$A,'Product Families'!$P:$P),"")} | AH51: {=iferror(xlookup($L51,'Product Families'!$A:$A,'Product Families'!$Q:$Q),"")} | AI51: =iferror(AG51/AH51,"") | AJ51: =iferror(AI51/$E51,"") | AK51: =round($D51*AJ51,2) -> 0
A52: AWHBL1 | B52: 5.9 | C52: 1 | D52: =iferror(B52/C52,"") -> 5.9 | E52: =sum(O52+T52+Y52+AD52+AI52) -> 0 | G52: awhbl code | M52: {=iferror(xlookup($H52,'Product Families'!$A:$A,'Product Families'!$P:$P),"")} | N52: {=iferror(xlookup($H52,'Product Families'!$A:$A,'Product Families'!$Q:$Q),"")} | O52: =iferror(M52/N52,"") | P52: =iferror(O52/$E52,"") | Q52: =round($D52*P52,2) -> 0 | R52: {=iferror(xlookup($I52,'Product Families'!$A:$A,'Product Families'!$P:$P),"")} | S52: {=iferror(xlookup($I52,'Product Families'!$A:$A,'Product Families'!$Q:$Q),"")} | T52: =iferror(R52/S52,"") | U52: =iferror(T52/$E52,"") | V52: =round($D52*U52,2) -> 0 | W52: {=iferror(xlookup($J52,'Product Families'!$A:$A,'Product Families'!$P:$P),"")} | X52: {=iferror(xlookup($J52,'Product Families'!$A:$A,'Product Families'!$Q:$Q),"")} | Y52: =iferror(W52/X52,"") | Z52: =iferror(Y52/$E52,"") | AA52: =round($D52*Z52,2) -> 0 | AB52: {=iferror(xlookup($K52,'Product Families'!$A:$A,'Product Families'!$P:$P),"")} | AC52: {=iferror(xlookup($K52,'Product Families'!$A:$A,'Product Families'!$Q:$Q),"")} | AD52: =iferror(AB52/AC52,"") | AE52: =iferror(AD52/$E52,"") | AF52: =round($D52*AE52,2) -> 0 | AG52: {=iferror(xlookup($L52,'Product Families'!$A:$A,'Product Families'!$P:$P),"")} | AH52: {=iferror(xlookup($L52,'Product Families'!$A:$A,'Product Families'!$Q:$Q),"")} | AI52: =iferror(AG52/AH52,"") | AJ52: =iferror(AI52/$E52,"") | AK52: =round($D52*AJ52,2) -> 0
A53: AWHBL2 | B53: n/a | D53: =iferror(B53/C53,"") | E53: =sum(O53+T53+Y53+AD53+AI53) -> 0 | G53: code not in use | M53: {=iferror(xlookup($H53,'Product Families'!$A:$A,'Product Families'!$P:$P),"")} | N53: {=iferror(xlookup($H53,'Product Families'!$A:$A,'Product Families'!$Q:$Q),"")} | O53: =iferror(M53/N53,"") | P53: =iferror(O53/$E53,"") | Q53: =round($D53*P53,2) -> 0 | R53: {=iferror(xlookup($I53,'Product Families'!$A:$A,'Product Families'!$P:$P),"")} | S53: {=iferror(xlookup($I53,'Product Families'!$A:$A,'Product Families'!$Q:$Q),"")} | T53: =iferror(R53/S53,"") | U53: =iferror(T53/$E53,"") | V53: =round($D53*U53,2) -> 0 | W53: {=iferror(xlookup($J53,'Product Families'!$A:$A,'Product Families'!$P:$P),"")} | X53: {=iferror(xlookup($J53,'Product Families'!$A:$A,'Product Families'!$Q:$Q),"")} | Y53: =iferror(W53/X53,"") | Z53: =iferror(Y53/$E53,"") | AA53: =round($D53*Z53,2) -> 0 | AB53: {=iferror(xlookup($K53,'Product Families'!$A:$A,'Product Families'!$P:$P),"")} | AC53: {=iferror(xlookup($K53,'Product Families'!$A:$A,'Product Families'!$Q:$Q),"")} | AD53: =iferror(AB53/AC53,"") | AE53: =iferror(AD53/$E53,"") | AF53: =round($D53*AE53,2) -> 0 | AG53: {=iferror(xlookup($L53,'Product Families'!$A:$A,'Product Families'!$P:$P),"")} | AH53: {=iferror(xlookup($L53,'Product Families'!$A:$A,'Product Families'!$Q:$Q),"")} | AI53: =iferror(AG53/AH53,"") | AJ53: =iferror(AI53/$E53,"") | AK53: =round($D53*AJ53,2) -> 0
A54: AWPFO | B54: n/a | D54: =iferror(B54/C54,"") | E54: =sum(O54+T54+Y54+AD54+AI54) -> 0 | G54: different prices | M54: {=iferror(xlookup($H54,'Product Families'!$A:$A,'Product Families'!$P:$P),"")} | N54: {=iferror(xlookup($H54,'Product Families'!$A:$A,'Product Families'!$Q:$Q),"")} | O54: =iferror(M54/N54,"") | P54: =iferror(O54/$E54,"") | Q54: =round($D54*P54,2) -> 0 | R54: {=iferror(xlookup($I54,'Product Families'!$A:$A,'Product Families'!$P:$P),"")} | S54: {=iferror(xlookup($I54,'Product Families'!$A:$A,'Product Families'!$Q:$Q),"")} | T54: =iferror(R54/S54,"") | U54: =iferror(T54/$E54,"") | V54: =round($D54*U54,2) -> 0 | W54: {=iferror(xlookup($J54,'Product Families'!$A:$A,'Product Families'!$P:$P),"")} | X54: {=iferror(xlookup($J54,'Product Families'!$A:$A,'Product Families'!$Q:$Q),"")} | Y54: =iferror(W54/X54,"") | Z54: =iferror(Y54/$E54,"") | AA54: =round($D54*Z54,2) -> 0 | AB54: {=iferror(xlookup($K54,'Product Families'!$A:$A,'Product Families'!$P:$P),"")} | AC54: {=iferror(xlookup($K54,'Product Families'!$A:$A,'Product Families'!$Q:$Q),"")} | AD54: =iferror(AB54/AC54,"") | AE54: =iferror(AD54/$E54,"") | AF54: =round($D54*AE54,2) -> 0 | AG54: {=iferror(xlookup($L54,'Product Families'!$A:$A,'Product Families'!$P:$P),"")} | AH54: {=iferror(xlookup($L54,'Product Families'!$A:$A,'Product Families'!$Q:$Q),"")} | AI54: =iferror(AG54/AH54,"") | AJ54: =iferror(AI54/$E54,"") | AK54: =round($D54*AJ54,2) -> 0
A55: AWRP | B55: 10.5 | C55: 6 | D55: =iferror(B55/C55,"") -> 1.75 | E55: =sum(O55+T55+Y55+AD55+AI55) -> 0 | M55: {=iferror(xlookup($H55,'Product Families'!$A:$A,'Product Families'!$P:$P),"")} | N55: {=iferror(xlookup($H55,'Product Families'!$A:$A,'Product Families'!$Q:$Q),"")} | O55: =iferror(M55/N55,"") | P55: =iferror(O55/$E55,"") | Q55: =round($D55*P55,2) -> 0 | R55: {=iferror(xlookup($I55,'Product Families'!$A:$A,'Product Families'!$P:$P),"")} | S55: {=iferror(xlookup($I55,'Product Families'!$A:$A,'Product Families'!$Q:$Q),"")} | T55: =iferror(R55/S55,"") | U55: =iferror(T55/$E55,"") | V55: =round($D55*U55,2) -> 0 | W55: {=iferror(xlookup($J55,'Product Families'!$A:$A,'Product Families'!$P:$P),"")} | X55: {=iferror(xlookup($J55,'Product Families'!$A:$A,'Product Families'!$Q:$Q),"")} | Y55: =iferror(W55/X55,"") | Z55: =iferror(Y55/$E55,"") | AA55: =round($D55*Z55,2) -> 0 | AB55: {=iferror(xlookup($K55,'Product Families'!$A:$A,'Product Families'!$P:$P),"")} | AC55: {=iferror(xlookup($K55,'Product Families'!$A:$A,'Product Families'!$Q:$Q),"")} | AD55: =iferror(AB55/AC55,"") | AE55: =iferror(AD55/$E55,"") | AF55: =round($D55*AE55,2) -> 0 | AG55: {=iferror(xlookup($L55,'Product Families'!$A:$A,'Product Families'!$P:$P),"")} | AH55: {=iferror(xlookup($L55,'Product Families'!$A:$A,'Product Families'!$Q:$Q),"")} | AI55: =iferror(AG55/AH55,"") | AJ55: =iferror(AI55/$E55,"") | AK55: =round($D55*AJ55,2) -> 0
A56: AWRS | B56: 13.67 | C56: 6 | D56: =iferror(B56/C56,"") -> 2.2783333 | E56: =sum(O56+T56+Y56+AD56+AI56) -> 0 | M56: {=iferror(xlookup($H56,'Product Families'!$A:$A,'Product Families'!$P:$P),"")} | N56: {=iferror(xlookup($H56,'Product Families'!$A:$A,'Product Families'!$Q:$Q),"")} | O56: =iferror(M56/N56,"") | P56: =iferror(O56/$E56,"") | Q56: =round($D56*P56,2) -> 0 | R56: {=iferror(xlookup($I56,'Product Families'!$A:$A,'Product Families'!$P:$P),"")} | S56: {=iferror(xlookup($I56,'Product Families'!$A:$A,'Product Families'!$Q:$Q),"")} | T56: =iferror(R56/S56,"") | U56: =iferror(T56/$E56,"") | V56: =round($D56*U56,2) -> 0 | W56: {=iferror(xlookup($J56,'Product Families'!$A:$A,'Product Families'!$P:$P),"")} | X56: {=iferror(xlookup($J56,'Product Families'!$A:$A,'Product Families'!$Q:$Q),"")} | Y56: =iferror(W56/X56,"") | Z56: =iferror(Y56/$E56,"") | AA56: =round($D56*Z56,2) -> 0 | AB56: {=iferror(xlookup($K56,'Product Families'!$A:$A,'Product Families'!$P:$P),"")} | AC56: {=iferror(xlookup($K56,'Product Families'!$A:$A,'Product Families'!$Q:$Q),"")} | AD56: =iferror(AB56/AC56,"") | AE56: =iferror(AD56/$E56,"") | AF56: =round($D56*AE56,2) -> 0 | AG56: {=iferror(xlookup($L56,'Product Families'!$A:$A,'Product Families'!$P:$P),"")} | AH56: {=iferror(xlookup($L56,'Product Families'!$A:$A,'Product Families'!$Q:$Q),"")} | AI56: =iferror(AG56/AH56,"") | AJ56: =iferror(AI56/$E56,"") | AK56: =round($D56*AJ56,2) -> 0
A57: AWRSUL | B57: 13.67 | C57: 6 | D57: =iferror(B57/C57,"") -> 2.2783333 | E57: =sum(O57+T57+Y57+AD57+AI57) -> 0 | M57: {=iferror(xlookup($H57,'Product Families'!$A:$A,'Product Families'!$P:$P),"")} | N57: {=iferror(xlookup($H57,'Product Families'!$A:$A,'Product Families'!$Q:$Q),"")} | O57: =iferror(M57/N57,"") | P57: =iferror(O57/$E57,"") | Q57: =round($D57*P57,2) -> 0 | R57: {=iferror(xlookup($I57,'Product Families'!$A:$A,'Product Families'!$P:$P),"")} | S57: {=iferror(xlookup($I57,'Product Families'!$A:$A,'Product Families'!$Q:$Q),"")} | T57: =iferror(R57/S57,"") | U57: =iferror(T57/$E57,"") | V57: =round($D57*U57,2) -> 0 | W57: {=iferror(xlookup($J57,'Product Families'!$A:$A,'Product Families'!$P:$P),"")} | X57: {=iferror(xlookup($J57,'Product Families'!$A:$A,'Product Families'!$Q:$Q),"")} | Y57: =iferror(W57/X57,"") | Z57: =iferror(Y57/$E57,"") | AA57: =round($D57*Z57,2) -> 0 | AB57: {=iferror(xlookup($K57,'Product Families'!$A:$A,'Product Families'!$P:$P),"")} | AC57: {=iferror(xlookup($K57,'Product Families'!$A:$A,'Product Families'!$Q:$Q),"")} | AD57: =iferror(AB57/AC57,"") | AE57: =iferror(AD57/$E57,"") | AF57: =round($D57*AE57,2) -> 0 | AG57: {=iferror(xlookup($L57,'Product Families'!$A:$A,'Product Families'!$P:$P),"")} | AH57: {=iferror(xlookup($L57,'Product Families'!$A:$A,'Product Families'!$Q:$Q),"")} | AI57: =iferror(AG57/AH57,"") | AJ57: =iferror(AI57/$E57,"") | AK57: =round($D57*AJ57,2) -> 0
A58: BAS | B58: 1.27 | C58: 1 | D58: =iferror(B58/C58,"") -> 1.27 | E58: =sum(O58+T58+Y58+AD58+AI58) -> 0 | H58: BAS | M58: {=iferror(xlookup($H58,'Product Families'!$A:$A,'Product Families'!$P:$P),"")} -> 0.24 | N58: {=iferror(xlookup($H58,'Product Families'!$A:$A,'Product Families'!$Q:$Q),"")} | O58: =iferror(M58/N58,"") | P58: =iferror(O58/$E58,"") | Q58: =round($D58*P58,2) -> 0 | R58: {=iferror(xlookup($I58,'Product Families'!$A:$A,'Product Families'!$P:$P),"")} | S58: {=iferror(xlookup($I58,'Product Families'!$A:$A,'Product Families'!$Q:$Q),"")} | T58: =iferror(R58/S58,"") | U58: =iferror(T58/$E58,"") | V58: =round($D58*U58,2) -> 0 | W58: {=iferror(xlookup($J58,'Product Families'!$A:$A,'Product Families'!$P:$P),"")} | X58: {=iferror(xlookup($J58,'Product Families'!$A:$A,'Product Families'!$Q:$Q),"")} | Y58: =iferror(W58/X58,"") | Z58: =iferror(Y58/$E58,"") | AA58: =round($D58*Z58,2) -> 0 | AB58: {=iferror(xlookup($K58,'Product Families'!$A:$A,'Product Families'!$P:$P),"")} | AC58: {=iferror(xlookup($K58,'Product Families'!$A:$A,'Product Families'!$Q:$Q),"")} | AD58: =iferror(AB58/AC58,"") | AE58: =iferror(AD58/$E58,"") | AF58: =round($D58*AE58,2) -> 0 | AG58: {=iferror(xlookup($L58,'Product Families'!$A:$A,'Product Families'!$P:$P),"")} | AH58: {=iferror(xlookup($L58,'Product Families'!$A:$A,'Product Families'!$Q:$Q),"")} | AI58: =iferror(AG58/AH58,"") | AJ58: =iferror(AI58/$E58,"") | AK58: =round($D58*AJ58,2) -> 0
A59: BB | B59: 2.12 - 4.51 | C59: 1 | D59: =iferror(B59/C59,"") | E59: =sum(O59+T59+Y59+AD59+AI59) -> 0 | G59: 6 different prices | M59: {=iferror(xlookup($H59,'Product Families'!$A:$A,'Product Families'!$P:$P),"")} | N59: {=iferror(xlookup($H59,'Product Families'!$A:$A,'Product Families'!$Q:$Q),"")} | O59: =iferror(M59/N59,"") | P59: =iferror(O59/$E59,"") | Q59: =round($D59*P59,2) -> 0 | R59: {=iferror(xlookup($I59,'Product Families'!$A:$A,'Product Families'!$P:$P),"")} | S59: {=iferror(xlookup($I59,'Product Families'!$A:$A,'Product Families'!$Q:$Q),"")} | T59: =iferror(R59/S59,"") | U59: =iferror(T59/$E59,"") | V59: =round($D59*U59,2) -> 0 | W59: {=iferror(xlookup($J59,'Product Families'!$A:$A,'Product Families'!$P:$P),"")} | X59: {=iferror(xlookup($J59,'Product Families'!$A:$A,'Product Families'!$Q:$Q),"")} | Y59: =iferror(W59/X59,"") | Z59: =iferror(Y59/$E59,"") | AA59: =round($D59*Z59,2) -> 0 | AB59: {=iferror(xlookup($K59,'Product Families'!$A:$A,'Product Families'!$P:$P),"")} | AC59: {=iferror(xlookup($K59,'Product Families'!$A:$A,'Product Families'!$Q:$Q),"")} | AD59: =iferror(AB59/AC59,"") | AE59: =iferror(AD59/$E59,"") | AF59: =round($D59*AE59,2) -> 0 | AG59: {=iferror(xlookup($L59,'Product Families'!$A:$A,'Product Families'!$P:$P),"")} | AH59: {=iferror(xlookup($L59,'Product Families'!$A:$A,'Product Families'!$Q:$Q),"")} | AI59: =iferror(AG59/AH59,"") | AJ59: =iferror(AI59/$E59,"") | AK59: =round($D59*AJ59,2) -> 0
A60: BBM | B60: n/a | D60: =iferror(B60/C60,"") | E60: =sum(O60+T60+Y60+AD60+AI60) -> 0 | G60: code not in use | M60: {=iferror(xlookup($H60,'Product Families'!$A:$A,'Product Families'!$P:$P),"")} | N60: {=iferror(xlookup($H60,'Product Families'!$A:$A,'Product Families'!$Q:$Q),"")} | O60: =iferror(M60/N60,"") | P60: =iferror(O60/$E60,"") | Q60: =round($D60*P60,2) -> 0 | R60: {=iferror(xlookup($I60,'Product Families'!$A:$A,'Product Families'!$P:$P),"")} | S60: {=iferror(xlookup($I60,'Product Families'!$A:$A,'Product Families'!$Q:$Q),"")} | T60: =iferror(R60/S60,"") | U60: =iferror(T60/$E60,"") | V60: =round($D60*U60,2) -> 0 | W60: {=iferror(xlookup($J60,'Product Families'!$A:$A,'Product Families'!$P:$P),"")} | X60: {=iferror(xlookup($J60,'Product Families'!$A:$A,'Product Families'!$Q:$Q),"")} | Y60: =iferror(W60/X60,"") | Z60: =iferror(Y60/$E60,"") | AA60: =round($D60*Z60,2) -> 0 | AB60: {=iferror(xlookup($K60,'Product Families'!$A:$A,'Product Families'!$P:$P),"")} | AC60: {=iferror(xlookup($K60,'Product Families'!$A:$A,'Product Families'!$Q:$Q),"")} | AD60: =iferror(AB60/AC60,"") | AE60: =iferror(AD60/$E60,"") | AF60: =round($D60*AE60,2) -> 0 | AG60: {=iferror(xlookup($L60,'Product Families'!$A:$A,'Product Families'!$P:$P),"")} | AH60: {=iferror(xlookup($L60,'Product Families'!$A:$A,'Product Families'!$Q:$Q),"")} | AI60: =iferror(AG60/AH60,"") | AJ60: =iferror(AI60/$E60,"") | AK60: =round($D60*AJ60,2) -> 0
A61: BBP | B61: n/a | D61: =iferror(B61/C61,"") | E61: =sum(O61+T61+Y61+AD61+AI61) -> 0 | G61: code not in use | M61: {=iferror(xlookup($H61,'Product Families'!$A:$A,'Product Families'!$P:$P),"")} | N61: {=iferror(xlookup($H61,'Product Families'!$A:$A,'Product Families'!$Q:$Q),"")} | O61: =iferror(M61/N61,"") | P61: =iferror(O61/$E61,"") | Q61: =round($D61*P61,2) -> 0 | R61: {=iferror(xlookup($I61,'Product Families'!$A:$A,'Product Families'!$P:$P),"")} | S61: {=iferror(xlookup($I61,'Product Families'!$A:$A,'Product Families'!$Q:$Q),"")} | T61: =iferror(R61/S61,"") | U61: =iferror(T61/$E61,"") | V61: =round($D61*U61,2) -> 0 | W61: {=iferror(xlookup($J61,'Product Families'!$A:$A,'Product Families'!$P:$P),"")} | X61: {=iferror(xlookup($J61,'Product Families'!$A:$A,'Product Families'!$Q:$Q),"")} | Y61: =iferror(W61/X61,"") | Z61: =iferror(Y61/$E61,"") | AA61: =round($D61*Z61,2) -> 0 | AB61: {=iferror(xlookup($K61,'Product Families'!$A:$A,'Product Families'!$P:$P),"")} | AC61: {=iferror(xlookup($K61,'Product Families'!$A:$A,'Product Families'!$Q:$Q),"")} | AD61: =iferror(AB61/AC61,"") | AE61: =iferror(AD61/$E61,"") | AF61: =round($D61*AE61,2) -> 0 | AG61: {=iferror(xlookup($L61,'Product Families'!$A:$A,'Product Families'!$P:$P),"")} | AH61: {=iferror(xlookup($L61,'Product Families'!$A:$A,'Product Families'!$Q:$Q),"")} | AI61: =iferror(AG61/AH61,"") | AJ61: =iferror(AI61/$E61,"") | AK61: =round($D61*AJ61,2) -> 0
A62: BB3 | B62: n/a | D62: =iferror(B62/C62,"") | E62: =sum(O62+T62+Y62+AD62+AI62) -> 0 | G62: code not in use | M62: {=iferror(xlookup($H62,'Product Families'!$A:$A,'Product Families'!$P:$P),"")} | N62: {=iferror(xlookup($H62,'Product Families'!$A:$A,'Product Families'!$Q:$Q),"")} | O62: =iferror(M62/N62,"") | P62: =iferror(O62/$E62,"") | Q62: =round($D62*P62,2) -> 0 | R62: {=iferror(xlookup($I62,'Product Families'!$A:$A,'Product Families'!$P:$P),"")} | S62: {=iferror(xlookup($I62,'Product Families'!$A:$A,'Product Families'!$Q:$Q),"")} | T62: =iferror(R62/S62,"") | U62: =iferror(T62/$E62,"") | V62: =round($D62*U62,2) -> 0 | W62: {=iferror(xlookup($J62,'Product Families'!$A:$A,'Product Families'!$P:$P),"")} | X62: {=iferror(xlookup($J62,'Product Families'!$A:$A,'Product Families'!$Q:$Q),"")} | Y62: =iferror(W62/X62,"") | Z62: =iferror(Y62/$E62,"") | AA62: =round($D62*Z62,2) -> 0 | AB62: {=iferror(xlookup($K62,'Product Families'!$A:$A,'Product Families'!$P:$P),"")} | AC62: {=iferror(xlookup($K62,'Product Families'!$A:$A,'Product Families'!$Q:$Q),"")} | AD62: =iferror(AB62/AC62,"") | AE62: =iferror(AD62/$E62,"") | AF62: =round($D62*AE62,2) -> 0 | AG62: {=iferror(xlookup($L62,'Product Families'!$A:$A,'Product Families'!$P:$P),"")} | AH62: {=iferror(xlookup($L62,'Product Families'!$A:$A,'Product Families'!$Q:$Q),"")} | AI62: =iferror(AG62/AH62,"") | AJ62: =iferror(AI62/$E62,"") | AK62: =round($D62*AJ62,2) -> 0
A63: BBEO | B63: 2.39 | C63: 1 | D63: =iferror(B63/C63,"") -> 2.39 | E63: =sum(O63+T63+Y63+AD63+AI63) -> 0 | M63: {=iferror(xlookup($H63,'Product Families'!$A:$A,'Product Families'!$P:$P),"")} | N63: {=iferror(xlookup($H63,'Product Families'!$A:$A,'Product Families'!$Q:$Q),"")} | O63: =iferror(M63/N63,"") | P63: =iferror(O63/$E63,"") | Q63: =round($D63*P63,2) -> 0 | R63: {=iferror(xlookup($I63,'Product Families'!$A:$A,'Product Families'!$P:$P),"")} | S63: {=iferror(xlookup($I63,'Product Families'!$A:$A,'Product Families'!$Q:$Q),"")} | T63: =iferror(R63/S63,"") | U63: =iferror(T63/$E63,"") | V63: =round($D63*U63,2) -> 0 | W63: {=iferror(xlookup($J63,'Product Families'!$A:$A,'Product Families'!$P:$P),"")} | X63: {=iferror(xlookup($J63,'Product Families'!$A:$A,'Product Families'!$Q:$Q),"")} | Y63: =iferror(W63/X63,"") | Z63: =iferror(Y63/$E63,"") | AA63: =round($D63*Z63,2) -> 0 | AB63: {=iferror(xlookup($K63,'Product Families'!$A:$A,'Product Families'!$P:$P),"")} | AC63: {=iferror(xlookup($K63,'Product Families'!$A:$A,'Product Families'!$Q:$Q),"")} | AD63: =iferror(AB63/AC63,"") | AE63: =iferror(AD63/$E63,"") | AF63: =round($D63*AE63,2) -> 0 | AG63: {=iferror(xlookup($L63,'Product Families'!$A:$A,'Product Families'!$P:$P),"")} | AH63: {=iferror(xlookup($L63,'Product Families'!$A:$A,'Product Families'!$Q:$Q),"")} | AI63: =iferror(AG63/AH63,"") | AJ63: =iferror(AI63/$E63,"") | AK63: =round($D63*AJ63,2) -> 0
A64: BBEOM | B64: n/a | D64: =iferror(B64/C64,"") | E64: =sum(O64+T64+Y64+AD64+AI64) -> 0 | G64: code not in use | M64: {=iferror(xlookup($H64,'Product Families'!$A:$A,'Product Families'!$P:$P),"")} | N64: {=iferror(xlookup($H64,'Product Families'!$A:$A,'Product Families'!$Q:$Q),"")} | O64: =iferror(M64/N64,"") | P64: =iferror(O64/$E64,"") | Q64: =round($D64*P64,2) -> 0 | R64: {=iferror(xlookup($I64,'Product Families'!$A:$A,'Product Families'!$P:$P),"")} | S64: {=iferror(xlookup($I64,'Product Families'!$A:$A,'Product Families'!$Q:$Q),"")} | T64: =iferror(R64/S64,"") | U64: =iferror(T64/$E64,"") | V64: =round($D64*U64,2) -> 0 | W64: {=iferror(xlookup($J64,'Product Families'!$A:$A,'Product Families'!$P:$P),"")} | X64: {=iferror(xlookup($J64,'Product Families'!$A:$A,'Product Families'!$Q:$Q),"")} | Y64: =iferror(W64/X64,"") | Z64: =iferror(Y64/$E64,"") | AA64: =round($D64*Z64,2) -> 0 | AB64: {=iferror(xlookup($K64,'Product Families'!$A:$A,'Product Families'!$P:$P),"")} | AC64: {=iferror(xlookup($K64,'Product Families'!$A:$A,'Product Families'!$Q:$Q),"")} | AD64: =iferror(AB64/AC64,"") | AE64: =iferror(AD64/$E64,"") | AF64: =round($D64*AE64,2) -> 0 | AG64: {=iferror(xlookup($L64,'Product Families'!$A:$A,'Product Families'!$P:$P),"")} | AH64: {=iferror(xlookup($L64,'Product Families'!$A:$A,'Product Families'!$Q:$Q),"")} | AI64: =iferror(AG64/AH64,"") | AJ64: =iferror(AI64/$E64,"") | AK64: =round($D64*AJ64,2) -> 0
A65: BBEOP | B65: n/a | D65: =iferror(B65/C65,"") | E65: =sum(O65+T65+Y65+AD65+AI65) -> 0 | G65: code not in use | M65: {=iferror(xlookup($H65,'Product Families'!$A:$A,'Product Families'!$P:$P),"")} | N65: {=iferror(xlookup($H65,'Product Families'!$A:$A,'Product Families'!$Q:$Q),"")} | O65: =iferror(M65/N65,"") | P65: =iferror(O65/$E65,"") | Q65: =round($D65*P65,2) -> 0 | R65: {=iferror(xlookup($I65,'Product Families'!$A:$A,'Product Families'!$P:$P),"")} | S65: {=iferror(xlookup($I65,'Product Families'!$A:$A,'Product Families'!$Q:$Q),"")} | T65: =iferror(R65/S65,"") | U65: =iferror(T65/$E65,"") | V65: =round($D65*U65,2) -> 0 | W65: {=iferror(xlookup($J65,'Product Families'!$A:$A,'Product Families'!$P:$P),"")} | X65: {=iferror(xlookup($J65,'Product Families'!$A:$A,'Product Families'!$Q:$Q),"")} | Y65: =iferror(W65/X65,"") | Z65: =iferror(Y65/$E65,"") | AA65: =round($D65*Z65,2) -> 0 | AB65: {=iferror(xlookup($K65,'Product Families'!$A:$A,'Product Families'!$P:$P),"")} | AC65: {=iferror(xlookup($K65,'Product Families'!$A:$A,'Product Families'!$Q:$Q),"")} | AD65: =iferror(AB65/AC65,"") | AE65: =iferror(AD65/$E65,"") | AF65: =round($D65*AE65,2) -> 0 | AG65: {=iferror(xlookup($L65,'Product Families'!$A:$A,'Product Families'!$P:$P),"")} | AH65: {=iferror(xlookup($L65,'Product Families'!$A:$A,'Product Families'!$Q:$Q),"")} | AI65: =iferror(AG65/AH65,"") | AJ65: =iferror(AI65/$E65,"") | AK65: =round($D65*AJ65,2) -> 0
A66: BBFO | B66: 2.39 | C66: 1 | D66: =iferror(B66/C66,"") -> 2.39 | E66: =sum(O66+T66+Y66+AD66+AI66) -> 0 | M66: {=iferror(xlookup($H66,'Product Families'!$A:$A,'Product Families'!$P:$P),"")} | N66: {=iferror(xlookup($H66,'Product Families'!$A:$A,'Product Families'!$Q:$Q),"")} | O66: =iferror(M66/N66,"") | P66: =iferror(O66/$E66,"") | Q66: =round($D66*P66,2) -> 0 | R66: {=iferror(xlookup($I66,'Product Families'!$A:$A,'Product Families'!$P:$P),"")} | S66: {=iferror(xlookup($I66,'Product Families'!$A:$A,'Product Families'!$Q:$Q),"")} | T66: =iferror(R66/S66,"") | U66: =iferror(T66/$E66,"") | V66: =round($D66*U66,2) -> 0 | W66: {=iferror(xlookup($J66,'Product Families'!$A:$A,'Product Families'!$P:$P),"")} | X66: {=iferror(xlookup($J66,'Product Families'!$A:$A,'Product Families'!$Q:$Q),"")} | Y66: =iferror(W66/X66,"") | Z66: =iferror(Y66/$E66,"") | AA66: =round($D66*Z66,2) -> 0 | AB66: {=iferror(xlookup($K66,'Product Families'!$A:$A,'Product Families'!$P:$P),"")} | AC66: {=iferror(xlookup($K66,'Product Families'!$A:$A,'Product Families'!$Q:$Q),"")} | AD66: =iferror(AB66/AC66,"") | AE66: =iferror(AD66/$E66,"") | AF66: =round($D66*AE66,2) -> 0 | AG66: {=iferror(xlookup($L66,'Product Families'!$A:$A,'Product Families'!$P:$P),"")} | AH66: {=iferror(xlookup($L66,'Product Families'!$A:$A,'Product Families'!$Q:$Q),"")} | AI66: =iferror(AG66/AH66,"") | AJ66: =iferror(AI66/$E66,"") | AK66: =round($D66*AJ66,2) -> 0
A67: BBFOM | B67: n/a | D67: =iferror(B67/C67,"") | E67: =sum(O67+T67+Y67+AD67+AI67) -> 0 | G67: code not in use | M67: {=iferror(xlookup($H67,'Product Families'!$A:$A,'Product Families'!$P:$P),"")} | N67: {=iferror(xlookup($H67,'Product Families'!$A:$A,'Product Families'!$Q:$Q),"")} | O67: =iferror(M67/N67,"") | P67: =iferror(O67/$E67,"") | Q67: =round($D67*P67,2) -> 0 | R67: {=iferror(xlookup($I67,'Product Families'!$A:$A,'Product Families'!$P:$P),"")} | S67: {=iferror(xlookup($I67,'Product Families'!$A:$A,'Product Families'!$Q:$Q),"")} | T67: =iferror(R67/S67,"") | U67: =iferror(T67/$E67,"") | V67: =round($D67*U67,2) -> 0 | W67: {=iferror(xlookup($J67,'Product Families'!$A:$A,'Product Families'!$P:$P),"")} | X67: {=iferror(xlookup($J67,'Product Families'!$A:$A,'Product Families'!$Q:$Q),"")} | Y67: =iferror(W67/X67,"") | Z67: =iferror(Y67/$E67,"") | AA67: =round($D67*Z67,2) -> 0 | AB67: {=iferror(xlookup($K67,'Product Families'!$A:$A,'Product Families'!$P:$P),"")} | AC67: {=iferror(xlookup($K67,'Product Families'!$A:$A,'Product Families'!$Q:$Q),"")} | AD67: =iferror(AB67/AC67,"") | AE67: =iferror(AD67/$E67,"") | AF67: =round($D67*AE67,2) -> 0 | AG67: {=iferror(xlookup($L67,'Product Families'!$A:$A,'Product Families'!$P:$P),"")} | AH67: {=iferror(xlookup($L67,'Product Families'!$A:$A,'Product Families'!$Q:$Q),"")} | AI67: =iferror(AG67/AH67,"") | AJ67: =iferror(AI67/$E67,"") | AK67: =round($D67*AJ67,2) -> 0
A68: BBFOP | B68: n/a | D68: =iferror(B68/C68,"") | E68: =sum(O68+T68+Y68+AD68+AI68) -> 0 | G68: code not in use | M68: {=iferror(xlookup($H68,'Product Families'!$A:$A,'Product Families'!$P:$P),"")} | N68: {=iferror(xlookup($H68,'Product Families'!$A:$A,'Product Families'!$Q:$Q),"")} | O68: =iferror(M68/N68,"") | P68: =iferror(O68/$E68,"") | Q68: =round($D68*P68,2) -> 0 | R68: {=iferror(xlookup($I68,'Product Families'!$A:$A,'Product Families'!$P:$P),"")} | S68: {=iferror(xlookup($I68,'Product Families'!$A:$A,'Product Families'!$Q:$Q),"")} | T68: =iferror(R68/S68,"") | U68: =iferror(T68/$E68,"") | V68: =round($D68*U68,2) -> 0 | W68: {=iferror(xlookup($J68,'Product Families'!$A:$A,'Product Families'!$P:$P),"")} | X68: {=iferror(xlookup($J68,'Product Families'!$A:$A,'Product Families'!$Q:$Q),"")} | Y68: =iferror(W68/X68,"") | Z68: =iferror(Y68/$E68,"") | AA68: =round($D68*Z68,2) -> 0 | AB68: {=iferror(xlookup($K68,'Product Families'!$A:$A,'Product Families'!$P:$P),"")} | AC68: {=iferror(xlookup($K68,'Product Families'!$A:$A,'Product Families'!$Q:$Q),"")} | AD68: =iferror(AB68/AC68,"") | AE68: =iferror(AD68/$E68,"") | AF68: =round($D68*AE68,2) -> 0 | AG68: {=iferror(xlookup($L68,'Product Families'!$A:$A,'Product Families'!$P:$P),"")} | AH68: {=iferror(xlookup($L68,'Product Families'!$A:$A,'Product Families'!$Q:$Q),"")} | AI68: =iferror(AG68/AH68,"") | AJ68: =iferror(AI68/$E68,"") | AK68: =round($D68*AJ68,2) -> 0
A69: BBKIT | B69: 11.61 | D69: 1 | E69: =sum(O69+T69+Y69+AD69+AI69) -> 0 | G69: Discontinued | H69: BBKIT | M69: {=iferror(xlookup($H69,'Product Families'!$A:$A,'Product Families'!$P:$P),"")} -> 1.36 | N69: {=iferror(xlookup($H69,'Product Families'!$A:$A,'Product Families'!$Q:$Q),"")} | O69: =iferror(M69/N69,"") | P69: =iferror(O69/$E69,"") | Q69: =round($D69*P69,2) -> 0 | R69: {=iferror(xlookup($I69,'Product Families'!$A:$A,'Product Families'!$P:$P),"")} | S69: {=iferror(xlookup($I69,'Product Families'!$A:$A,'Product Families'!$Q:$Q),"")} | T69: =iferror(R69/S69,"") | U69: =iferror(T69/$E69,"") | V69: =round($D69*U69,2) -> 0 | W69: {=iferror(xlookup($J69,'Product Families'!$A:$A,'Product Families'!$P:$P),"")} | X69: {=iferror(xlookup($J69,'Product Families'!$A:$A,'Product Families'!$Q:$Q),"")} | Y69: =iferror(W69/X69,"") | Z69: =iferror(Y69/$E69,"") | AA69: =round($D69*Z69,2) -> 0 | AB69: {=iferror(xlookup($K69,'Product Families'!$A:$A,'Product Families'!$P:$P),"")} | AC69: {=iferror(xlookup($K69,'Product Families'!$A:$A,'Product Families'!$Q:$Q),"")} | AD69: =iferror(AB69/AC69,"") | AE69: =iferror(AD69/$E69,"") | AF69: =round($D69*AE69,2) -> 0 | AG69: {=iferror(xlookup($L69,'Product Families'!$A:$A,'Product Families'!$P:$P),"")} | AH69: {=iferror(xlookup($L69,'Product Families'!$A:$A,'Product Families'!$Q:$Q),"")} | AI69: =iferror(AG69/AH69,"") | AJ69: =iferror(AI69/$E69,"") | AK69: =round($D69*AJ69,2) -> 0
A70: BBShrink | B70: n/a | D70: =iferror(B70/C70,"") | E70: =sum(O70+T70+Y70+AD70+AI70) -> 0 | G70: code not in use | M70: {=iferror(xlookup($H70,'Product Families'!$A:$A,'Product Families'!$P:$P),"")} | N70: {=iferror(xlookup($H70,'Product Families'!$A:$A,'Product Families'!$Q:$Q),"")} | O70: =iferror(M70/N70,"") | P70: =iferror(O70/$E70,"") | Q70: =round($D70*P70,2) -> 0 | R70: {=iferror(xlookup($I70,'Product Families'!$A:$A,'Product Families'!$P:$P),"")} | S70: {=iferror(xlookup($I70,'Product Families'!$A:$A,'Product Families'!$Q:$Q),"")} | T70: =iferror(R70/S70,"") | U70: =iferror(T70/$E70,"") | V70: =round($D70*U70,2) -> 0 | W70: {=iferror(xlookup($J70,'Product Families'!$A:$A,'Product Families'!$P:$P),"")} | X70: {=iferror(xlookup($J70,'Product Families'!$A:$A,'Product Families'!$Q:$Q),"")} | Y70: =iferror(W70/X70,"") | Z70: =iferror(Y70/$E70,"") | AA70: =round($D70*Z70,2) -> 0 | AB70: {=iferror(xlookup($K70,'Product Families'!$A:$A,'Product Families'!$P:$P),"")} | AC70: {=iferror(xlookup($K70,'Product Families'!$A:$A,'Product Families'!$Q:$Q),"")} | AD70: =iferror(AB70/AC70,"") | AE70: =iferror(AD70/$E70,"") | AF70: =round($D70*AE70,2) -> 0 | AG70: {=iferror(xlookup($L70,'Product Families'!$A:$A,'Product Families'!$P:$P),"")} | AH70: {=iferror(xlookup($L70,'Product Families'!$A:$A,'Product Families'!$Q:$Q),"")} | AI70: =iferror(AG70/AH70,"") | AJ70: =iferror(AI70/$E70,"") | AK70: =round($D70*AJ70,2) -> 0
A71: BBShrinkM | B71: n/a | D71: =iferror(B71/C71,"") | E71: =sum(O71+T71+Y71+AD71+AI71) -> 0 | G71: code not in use | M71: {=iferror(xlookup($H71,'Product Families'!$A:$A,'Product Families'!$P:$P),"")} | N71: {=iferror(xlookup($H71,'Product Families'!$A:$A,'Product Families'!$Q:$Q),"")} | O71: =iferror(M71/N71,"") | P71: =iferror(O71/$E71,"") | Q71: =round($D71*P71,2) -> 0 | R71: {=iferror(xlookup($I71,'Product Families'!$A:$A,'Product Families'!$P:$P),"")} | S71: {=iferror(xlookup($I71,'Product Families'!$A:$A,'Product Families'!$Q:$Q),"")} | T71: =iferror(R71/S71,"") | U71: =iferror(T71/$E71,"") | V71: =round($D71*U71,2) -> 0 | W71: {=iferror(xlookup($J71,'Product Families'!$A:$A,'Product Families'!$P:$P),"")} | X71: {=iferror(xlookup($J71,'Product Families'!$A:$A,'Product Families'!$Q:$Q),"")} | Y71: =iferror(W71/X71,"") | Z71: =iferror(Y71/$E71,"") | AA71: =round($D71*Z71,2) -> 0 | AB71: {=iferror(xlookup($K71,'Product Families'!$A:$A,'Product Families'!$P:$P),"")} | AC71: {=iferror(xlookup($K71,'Product Families'!$A:$A,'Product Families'!$Q:$Q),"")} | AD71: =iferror(AB71/AC71,"") | AE71: =iferror(AD71/$E71,"") | AF71: =round($D71*AE71,2) -> 0 | AG71: {=iferror(xlookup($L71,'Product Families'!$A:$A,'Product Families'!$P:$P),"")} | AH71: {=iferror(xlookup($L71,'Product Families'!$A:$A,'Product Families'!$Q:$Q),"")} | AI71: =iferror(AG71/AH71,"") | AJ71: =iferror(AI71/$E71,"") | AK71: =round($D71*AJ71,2) -> 0
A72: BeardO | B72: 37.52 | C72: 12 | D72: =iferror(B72/C72,"") -> 3.1266667 | E72: =sum(O72+T72+Y72+AD72+AI72) -> 0 | M72: {=iferror(xlookup($H72,'Product Families'!$A:$A,'Product Families'!$P:$P),"")} | N72: {=iferror(xlookup($H72,'Product Families'!$A:$A,'Product Families'!$Q:$Q),"")} | O72: =iferror(M72/N72,"") | P72: =iferror(O72/$E72,"") | Q72: =round($D72*P72,2) -> 0 | R72: {=iferror(xlookup($I72,'Product Families'!$A:$A,'Product Families'!$P:$P),"")} | S72: {=iferror(xlookup($I72,'Product Families'!$A:$A,'Product Families'!$Q:$Q),"")} | T72: =iferror(R72/S72,"") | U72: =iferror(T72/$E72,"") | V72: =round($D72*U72,2) -> 0 | W72: {=iferror(xlookup($J72,'Product Families'!$A:$A,'Product Families'!$P:$P),"")} | X72: {=iferror(xlookup($J72,'Product Families'!$A:$A,'Product Families'!$Q:$Q),"")} | Y72: =iferror(W72/X72,"") | Z72: =iferror(Y72/$E72,"") | AA72: =round($D72*Z72,2) -> 0 | AB72: {=iferror(xlookup($K72,'Product Families'!$A:$A,'Product Families'!$P:$P),"")} | AC72: {=iferror(xlookup($K72,'Product Families'!$A:$A,'Product Families'!$Q:$Q),"")} | AD72: =iferror(AB72/AC72,"") | AE72: =iferror(AD72/$E72,"") | AF72: =round($D72*AE72,2) -> 0 | AG72: {=iferror(xlookup($L72,'Product Families'!$A:$A,'Product Families'!$P:$P),"")} | AH72: {=iferror(xlookup($L72,'Product Families'!$A:$A,'Product Families'!$Q:$Q),"")} | AI72: =iferror(AG72/AH72,"") | AJ72: =iferror(AI72/$E72,"") | AK72: =round($D72*AJ72,2) -> 0
A73: BeardOUL | B73: 31.27 | C73: 12 | D73: =iferror(B73/C73,"") -> 2.6058333 | E73: =sum(O73+T73+Y73+AD73+AI73) -> 0 | M73: {=iferror(xlookup($H73,'Product Families'!$A:$A,'Product Families'!$P:$P),"")} | N73: {=iferror(xlookup($H73,'Product Families'!$A:$A,'Product Families'!$Q:$Q),"")} | O73: =iferror(M73/N73,"") | P73: =iferror(O73/$E73,"") | Q73: =round($D73*P73,2) -> 0 | R73: {=iferror(xlookup($I73,'Product Families'!$A:$A,'Product Families'!$P:$P),"")} | S73: {=iferror(xlookup($I73,'Product Families'!$A:$A,'Product Families'!$Q:$Q),"")} | T73: =iferror(R73/S73,"") | U73: =iferror(T73/$E73,"") | V73: =round($D73*U73,2) -> 0 | W73: {=iferror(xlookup($J73,'Product Families'!$A:$A,'Product Families'!$P:$P),"")} | X73: {=iferror(xlookup($J73,'Product Families'!$A:$A,'Product Families'!$Q:$Q),"")} | Y73: =iferror(W73/X73,"") | Z73: =iferror(Y73/$E73,"") | AA73: =round($D73*Z73,2) -> 0 | AB73: {=iferror(xlookup($K73,'Product Families'!$A:$A,'Product Families'!$P:$P),"")} | AC73: {=iferror(xlookup($K73,'Product Families'!$A:$A,'Product Families'!$Q:$Q),"")} | AD73: =iferror(AB73/AC73,"") | AE73: =iferror(AD73/$E73,"") | AF73: =round($D73*AE73,2) -> 0 | AG73: {=iferror(xlookup($L73,'Product Families'!$A:$A,'Product Families'!$P:$P),"")} | AH73: {=iferror(xlookup($L73,'Product Families'!$A:$A,'Product Families'!$Q:$Q),"")} | AI73: =iferror(AG73/AH73,"") | AJ73: =iferror(AI73/$E73,"") | AK73: =round($D73*AJ73,2) -> 0
A74: Begg | B74: 13.99 | C74: 30 | D74: =iferror(B74/C74,"") -> 0.46633333 | E74: =sum(O74+T74+Y74+AD74+AI74) -> 0 | M74: {=iferror(xlookup($H74,'Product Families'!$A:$A,'Product Families'!$P:$P),"")} | N74: {=iferror(xlookup($H74,'Product Families'!$A:$A,'Product Families'!$Q:$Q),"")} | O74: =iferror(M74/N74,"") | P74: =iferror(O74/$E74,"") | Q74: =round($D74*P74,2) -> 0 | R74: {=iferror(xlookup($I74,'Product Families'!$A:$A,'Product Families'!$P:$P),"")} | S74: {=iferror(xlookup($I74,'Product Families'!$A:$A,'Product Families'!$Q:$Q),"")} | T74: =iferror(R74/S74,"") | U74: =iferror(T74/$E74,"") | V74: =round($D74*U74,2) -> 0 | W74: {=iferror(xlookup($J74,'Product Families'!$A:$A,'Product Families'!$P:$P),"")} | X74: {=iferror(xlookup($J74,'Product Families'!$A:$A,'Product Families'!$Q:$Q),"")} | Y74: =iferror(W74/X74,"") | Z74: =iferror(Y74/$E74,"") | AA74: =round($D74*Z74,2) -> 0 | AB74: {=iferror(xlookup($K74,'Product Families'!$A:$A,'Product Families'!$P:$P),"")} | AC74: {=iferror(xlookup($K74,'Product Families'!$A:$A,'Product Families'!$Q:$Q),"")} | AD74: =iferror(AB74/AC74,"") | AE74: =iferror(AD74/$E74,"") | AF74: =round($D74*AE74,2) -> 0 | AG74: {=iferror(xlookup($L74,'Product Families'!$A:$A,'Product Families'!$P:$P),"")} | AH74: {=iferror(xlookup($L74,'Product Families'!$A:$A,'Product Families'!$Q:$Q),"")} | AI74: =iferror(AG74/AH74,"") | AJ74: =iferror(AI74/$E74,"") | AK74: =round($D74*AJ74,2) -> 0
A75: BeggP | B75: n/a | D75: =iferror(B75/C75,"") | E75: =sum(O75+T75+Y75+AD75+AI75) -> 0 | G75: code not in use | M75: {=iferror(xlookup($H75,'Product Families'!$A:$A,'Product Families'!$P:$P),"")} | N75: {=iferror(xlookup($H75,'Product Families'!$A:$A,'Product Families'!$Q:$Q),"")} | O75: =iferror(M75/N75,"") | P75: =iferror(O75/$E75,"") | Q75: =round($D75*P75,2) -> 0 | R75: {=iferror(xlookup($I75,'Product Families'!$A:$A,'Product Families'!$P:$P),"")} | S75: {=iferror(xlookup($I75,'Product Families'!$A:$A,'Product Families'!$Q:$Q),"")} | T75: =iferror(R75/S75,"") | U75: =iferror(T75/$E75,"") | V75: =round($D75*U75,2) -> 0 | W75: {=iferror(xlookup($J75,'Product Families'!$A:$A,'Product Families'!$P:$P),"")} | X75: {=iferror(xlookup($J75,'Product Families'!$A:$A,'Product Families'!$Q:$Q),"")} | Y75: =iferror(W75/X75,"") | Z75: =iferror(Y75/$E75,"") | AA75: =round($D75*Z75,2) -> 0 | AB75: {=iferror(xlookup($K75,'Product Families'!$A:$A,'Product Families'!$P:$P),"")} | AC75: {=iferror(xlookup($K75,'Product Families'!$A:$A,'Product Families'!$Q:$Q),"")} | AD75: =iferror(AB75/AC75,"") | AE75: =iferror(AD75/$E75,"") | AF75: =round($D75*AE75,2) -> 0 | AG75: {=iferror(xlookup($L75,'Product Families'!$A:$A,'Product Families'!$P:$P),"")} | AH75: {=iferror(xlookup($L75,'Product Families'!$A:$A,'Product Families'!$Q:$Q),"")} | AI75: =iferror(AG75/AH75,"") | AJ75: =iferror(AI75/$E75,"") | AK75: =round($D75*AJ75,2) -> 0
A76: BFS | B76: n/a | D76: =iferror(B76/C76,"") | E76: =sum(O76+T76+Y76+AD76+AI76) -> 0 | G76: code not in use | M76: {=iferror(xlookup($H76,'Product Families'!$A:$A,'Product Families'!$P:$P),"")} | N76: {=iferror(xlookup($H76,'Product Families'!$A:$A,'Product Families'!$Q:$Q),"")} | O76: =iferror(M76/N76,"") | P76: =iferror(O76/$E76,"") | Q76: =round($D76*P76,2) -> 0 | R76: {=iferror(xlookup($I76,'Product Families'!$A:$A,'Product Families'!$P:$P),"")} | S76: {=iferror(xlookup($I76,'Product Families'!$A:$A,'Product Families'!$Q:$Q),"")} | T76: =iferror(R76/S76,"") | U76: =iferror(T76/$E76,"") | V76: =round($D76*U76,2) -> 0 | W76: {=iferror(xlookup($J76,'Product Families'!$A:$A,'Product Families'!$P:$P),"")} | X76: {=iferror(xlookup($J76,'Product Families'!$A:$A,'Product Families'!$Q:$Q),"")} | Y76: =iferror(W76/X76,"") | Z76: =iferror(Y76/$E76,"") | AA76: =round($D76*Z76,2) -> 0 | AB76: {=iferror(xlookup($K76,'Product Families'!$A:$A,'Product Families'!$P:$P),"")} | AC76: {=iferror(xlookup($K76,'Product Families'!$A:$A,'Product Families'!$Q:$Q),"")} | AD76: =iferror(AB76/AC76,"") | AE76: =iferror(AD76/$E76,"") | AF76: =round($D76*AE76,2) -> 0 | AG76: {=iferror(xlookup($L76,'Product Families'!$A:$A,'Product Families'!$P:$P),"")} | AH76: {=iferror(xlookup($L76,'Product Families'!$A:$A,'Product Families'!$Q:$Q),"")} | AI76: =iferror(AG76/AH76,"") | AJ76: =iferror(AI76/$E76,"") | AK76: =round($D76*AJ76,2) -> 0
A77: BFSB | B77: 9.75 | C77: 4 | D77: =iferror(B77/C77,"") -> 2.4375 | E77: =sum(O77+T77+Y77+AD77+AI77) -> 0 | M77: {=iferror(xlookup($H77,'Product Families'!$A:$A,'Product Families'!$P:$P),"")} | N77: {=iferror(xlookup($H77,'Product Families'!$A:$A,'Product Families'!$Q:$Q),"")} | O77: =iferror(M77/N77,"") | P77: =iferror(O77/$E77,"") | Q77: =round($D77*P77,2) -> 0 | R77: {=iferror(xlookup($I77,'Product Families'!$A:$A,'Product Families'!$P:$P),"")} | S77: {=iferror(xlookup($I77,'Product Families'!$A:$A,'Product Families'!$Q:$Q),"")} | T77: =iferror(R77/S77,"") | U77: =iferror(T77/$E77,"") | V77: =round($D77*U77,2) -> 0 | W77: {=iferror(xlookup($J77,'Product Families'!$A:$A,'Product Families'!$P:$P),"")} | X77: {=iferror(xlookup($J77,'Product Families'!$A:$A,'Product Families'!$Q:$Q),"")} | Y77: =iferror(W77/X77,"") | Z77: =iferror(Y77/$E77,"") | AA77: =round($D77*Z77,2) -> 0 | AB77: {=iferror(xlookup($K77,'Product Families'!$A:$A,'Product Families'!$P:$P),"")} | AC77: {=iferror(xlookup($K77,'Product Families'!$A:$A,'Product Families'!$Q:$Q),"")} | AD77: =iferror(AB77/AC77,"") | AE77: =iferror(AD77/$E77,"") | AF77: =round($D77*AE77,2) -> 0 | AG77: {=iferror(xlookup($L77,'Product Families'!$A:$A,'Product Families'!$P:$P),"")} | AH77: {=iferror(xlookup($L77,'Product Families'!$A:$A,'Product Families'!$Q:$Q),"")} | AI77: =iferror(AG77/AH77,"") | AJ77: =iferror(AI77/$E77,"") | AK77: =round($D77*AJ77,2) -> 0
A78: BFSBUL | B78: 9.75 | C78: 4 | D78: =iferror(B78/C78,"") -> 2.4375 | E78: =sum(O78+T78+Y78+AD78+AI78) -> 0 | M78: {=iferror(xlookup($H78,'Product Families'!$A:$A,'Product Families'!$P:$P),"")} | N78: {=iferror(xlookup($H78,'Product Families'!$A:$A,'Product Families'!$Q:$Q),"")} | O78: =iferror(M78/N78,"") | P78: =iferror(O78/$E78,"") | Q78: =round($D78*P78,2) -> 0 | R78: {=iferror(xlookup($I78,'Product Families'!$A:$A,'Product Families'!$P:$P),"")} | S78: {=iferror(xlookup($I78,'Product Families'!$A:$A,'Product Families'!$Q:$Q),"")} | T78: =iferror(R78/S78,"") | U78: =iferror(T78/$E78,"") | V78: =round($D78*U78,2) -> 0 | W78: {=iferror(xlookup($J78,'Product Families'!$A:$A,'Product Families'!$P:$P),"")} | X78: {=iferror(xlookup($J78,'Product Families'!$A:$A,'Product Families'!$Q:$Q),"")} | Y78: =iferror(W78/X78,"") | Z78: =iferror(Y78/$E78,"") | AA78: =round($D78*Z78,2) -> 0 | AB78: {=iferror(xlookup($K78,'Product Families'!$A:$A,'Product Families'!$P:$P),"")} | AC78: {=iferror(xlookup($K78,'Product Families'!$A:$A,'Product Families'!$Q:$Q),"")} | AD78: =iferror(AB78/AC78,"") | AE78: =iferror(AD78/$E78,"") | AF78: =round($D78*AE78,2) -> 0 | AG78: {=iferror(xlookup($L78,'Product Families'!$A:$A,'Product Families'!$P:$P),"")} | AH78: {=iferror(xlookup($L78,'Product Families'!$A:$A,'Product Families'!$Q:$Q),"")} | AI78: =iferror(AG78/AH78,"") | AJ78: =iferror(AI78/$E78,"") | AK78: =round($D78*AJ78,2) -> 0
A79: BO | B79: - | D79: =iferror(B79/C79,"") | E79: =sum(O79+T79+Y79+AD79+AI79) -> 0 | G79: 33 products - different prices | M79: {=iferror(xlookup($H79,'Product Families'!$A:$A,'Product Families'!$P:$P),"")} | N79: {=iferror(xlookup($H79,'Product Families'!$A:$A,'Product Families'!$Q:$Q),"")} | O79: =iferror(M79/N79,"") | P79: =iferror(O79/$E79,"") | Q79: =round($D79*P79,2) -> 0 | R79: {=iferror(xlookup($I79,'Product Families'!$A:$A,'Product Families'!$P:$P),"")} | S79: {=iferror(xlookup($I79,'Product Families'!$A:$A,'Product Families'!$Q:$Q),"")} | T79: =iferror(R79/S79,"") | U79: =iferror(T79/$E79,"") | V79: =round($D79*U79,2) -> 0 | W79: {=iferror(xlookup($J79,'Product Families'!$A:$A,'Product Families'!$P:$P),"")} | X79: {=iferror(xlookup($J79,'Product Families'!$A:$A,'Product Families'!$Q:$Q),"")} | Y79: =iferror(W79/X79,"") | Z79: =iferror(Y79/$E79,"") | AA79: =round($D79*Z79,2) -> 0 | AB79: {=iferror(xlookup($K79,'Product Families'!$A:$A,'Product Families'!$P:$P),"")} | AC79: {=iferror(xlookup($K79,'Product Families'!$A:$A,'Product Families'!$Q:$Q),"")} | AD79: =iferror(AB79/AC79,"") | AE79: =iferror(AD79/$E79,"") | AF79: =round($D79*AE79,2) -> 0 | AG79: {=iferror(xlookup($L79,'Product Families'!$A:$A,'Product Families'!$P:$P),"")} | AH79: {=iferror(xlookup($L79,'Product Families'!$A:$A,'Product Families'!$Q:$Q),"")} | AI79: =iferror(AG79/AH79,"") | AJ79: =iferror(AI79/$E79,"") | AK79: =round($D79*AJ79,2) -> 0
A80: BOUL | B80: - | D80: =iferror(B80/C80,"") | E80: =sum(O80+T80+Y80+AD80+AI80) -> 0 | G80: 33 products - different prices | M80: {=iferror(xlookup($H80,'Product Families'!$A:$A,'Product Families'!$P:$P),"")} | N80: {=iferror(xlookup($H80,'Product Families'!$A:$A,'Product Families'!$Q:$Q),"")} | O80: =iferror(M80/N80,"") | P80: =iferror(O80/$E80,"") | Q80: =round($D80*P80,2) -> 0 | R80: {=iferror(xlookup($I80,'Product Families'!$A:$A,'Product Families'!$P:$P),"")} | S80: {=iferror(xlookup($I80,'Product Families'!$A:$A,'Product Families'!$Q:$Q),"")} | T80: =iferror(R80/S80,"") | U80: =iferror(T80/$E80,"") | V80: =round($D80*U80,2) -> 0 | W80: {=iferror(xlookup($J80,'Product Families'!$A:$A,'Product Families'!$P:$P),"")} | X80: {=iferror(xlookup($J80,'Product Families'!$A:$A,'Product Families'!$Q:$Q),"")} | Y80: =iferror(W80/X80,"") | Z80: =iferror(Y80/$E80,"") | AA80: =round($D80*Z80,2) -> 0 | AB80: {=iferror(xlookup($K80,'Product Families'!$A:$A,'Product Families'!$P:$P),"")} | AC80: {=iferror(xlookup($K80,'Product Families'!$A:$A,'Product Families'!$Q:$Q),"")} | AD80: =iferror(AB80/AC80,"") | AE80: =iferror(AD80/$E80,"") | AF80: =round($D80*AE80,2) -> 0 | AG80: {=iferror(xlookup($L80,'Product Families'!$A:$A,'Product Families'!$P:$P),"")} | AH80: {=iferror(xlookup($L80,'Product Families'!$A:$A,'Product Families'!$Q:$Q),"")} | AI80: =iferror(AG80/AH80,"") | AJ80: =iferror(AI80/$E80,"") | AK80: =round($D80*AJ80,2) -> 0
A81: BOz | B81: - | D81: =iferror(B81/C81,"") | E81: =sum(O81+T81+Y81+AD81+AI81) -> 0 | G81: 33 products - different prices | M81: {=iferror(xlookup($H81,'Product Families'!$A:$A,'Product Families'!$P:$P),"")} | N81: {=iferror(xlookup($H81,'Product Families'!$A:$A,'Product Families'!$Q:$Q),"")} | O81: =iferror(M81/N81,"") | P81: =iferror(O81/$E81,"") | Q81: =round($D81*P81,2) -> 0 | R81: {=iferror(xlookup($I81,'Product Families'!$A:$A,'Product Families'!$P:$P),"")} | S81: {=iferror(xlookup($I81,'Product Families'!$A:$A,'Product Families'!$Q:$Q),"")} | T81: =iferror(R81/S81,"") | U81: =iferror(T81/$E81,"") | V81: =round($D81*U81,2) -> 0 | W81: {=iferror(xlookup($J81,'Product Families'!$A:$A,'Product Families'!$P:$P),"")} | X81: {=iferror(xlookup($J81,'Product Families'!$A:$A,'Product Families'!$Q:$Q),"")} | Y81: =iferror(W81/X81,"") | Z81: =iferror(Y81/$E81,"") | AA81: =round($D81*Z81,2) -> 0 | AB81: {=iferror(xlookup($K81,'Product Families'!$A:$A,'Product Families'!$P:$P),"")} | AC81: {=iferror(xlookup($K81,'Product Families'!$A:$A,'Product Families'!$Q:$Q),"")} | AD81: =iferror(AB81/AC81,"") | AE81: =iferror(AD81/$E81,"") | AF81: =round($D81*AE81,2) -> 0 | AG81: {=iferror(xlookup($L81,'Product Families'!$A:$A,'Product Families'!$P:$P),"")} | AH81: {=iferror(xlookup($L81,'Product Families'!$A:$A,'Product Families'!$Q:$Q),"")} | AI81: =iferror(AG81/AH81,"") | AJ81: =iferror(AI81/$E81,"") | AK81: =round($D81*AJ81,2) -> 0
A82: BSV | B82: 8.43 - 9.28 | D82: =iferror(B82/C82,"") | E82: =sum(O82+T82+Y82+AD82+AI82) -> 0 | G82: 2 different prices | M82: {=iferror(xlookup($H82,'Product Families'!$A:$A,'Product Families'!$P:$P),"")} | N82: {=iferror(xlookup($H82,'Product Families'!$A:$A,'Product Families'!$Q:$Q),"")} | O82: =iferror(M82/N82,"") | P82: =iferror(O82/$E82,"") | Q82: =round($D82*P82,2) -> 0 | R82: {=iferror(xlookup($I82,'Product Families'!$A:$A,'Product Families'!$P:$P),"")} | S82: {=iferror(xlookup($I82,'Product Families'!$A:$A,'Product Families'!$Q:$Q),"")} | T82: =iferror(R82/S82,"") | U82: =iferror(T82/$E82,"") | V82: =round($D82*U82,2) -> 0 | W82: {=iferror(xlookup($J82,'Product Families'!$A:$A,'Product Families'!$P:$P),"")} | X82: {=iferror(xlookup($J82,'Product Families'!$A:$A,'Product Families'!$Q:$Q),"")} | Y82: =iferror(W82/X82,"") | Z82: =iferror(Y82/$E82,"") | AA82: =round($D82*Z82,2) -> 0 | AB82: {=iferror(xlookup($K82,'Product Families'!$A:$A,'Product Families'!$P:$P),"")} | AC82: {=iferror(xlookup($K82,'Product Families'!$A:$A,'Product Families'!$Q:$Q),"")} | AD82: =iferror(AB82/AC82,"") | AE82: =iferror(AD82/$E82,"") | AF82: =round($D82*AE82,2) -> 0 | AG82: {=iferror(xlookup($L82,'Product Families'!$A:$A,'Product Families'!$P:$P),"")} | AH82: {=iferror(xlookup($L82,'Product Families'!$A:$A,'Product Families'!$Q:$Q),"")} | AI82: =iferror(AG82/AH82,"") | AJ82: =iferror(AI82/$E82,"") | AK82: =round($D82*AJ82,2) -> 0
A83: BSV2 | B83: n/a | D83: =iferror(B83/C83,"") | E83: =sum(O83+T83+Y83+AD83+AI83) -> 0 | G83: code not in use | M83: {=iferror(xlookup($H83,'Product Families'!$A:$A,'Product Families'!$P:$P),"")} | N83: {=iferror(xlookup($H83,'Product Families'!$A:$A,'Product Families'!$Q:$Q),"")} | O83: =iferror(M83/N83,"") | P83: =iferror(O83/$E83,"") | Q83: =round($D83*P83,2) -> 0 | R83: {=iferror(xlookup($I83,'Product Families'!$A:$A,'Product Families'!$P:$P),"")} | S83: {=iferror(xlookup($I83,'Product Families'!$A:$A,'Product Families'!$Q:$Q),"")} | T83: =iferror(R83/S83,"") | U83: =iferror(T83/$E83,"") | V83: =round($D83*U83,2) -> 0 | W83: {=iferror(xlookup($J83,'Product Families'!$A:$A,'Product Families'!$P:$P),"")} | X83: {=iferror(xlookup($J83,'Product Families'!$A:$A,'Product Families'!$Q:$Q),"")} | Y83: =iferror(W83/X83,"") | Z83: =iferror(Y83/$E83,"") | AA83: =round($D83*Z83,2) -> 0 | AB83: {=iferror(xlookup($K83,'Product Families'!$A:$A,'Product Families'!$P:$P),"")} | AC83: {=iferror(xlookup($K83,'Product Families'!$A:$A,'Product Families'!$Q:$Q),"")} | AD83: =iferror(AB83/AC83,"") | AE83: =iferror(AD83/$E83,"") | AF83: =round($D83*AE83,2) -> 0 | AG83: {=iferror(xlookup($L83,'Product Families'!$A:$A,'Product Families'!$P:$P),"")} | AH83: {=iferror(xlookup($L83,'Product Families'!$A:$A,'Product Families'!$Q:$Q),"")} | AI83: =iferror(AG83/AH83,"") | AJ83: =iferror(AI83/$E83,"") | AK83: =round($D83*AJ83,2) -> 0
A84: BSVP | B84: n/a | D84: =iferror(B84/C84,"") | E84: =sum(O84+T84+Y84+AD84+AI84) -> 0 | G84: code not in use | M84: {=iferror(xlookup($H84,'Product Families'!$A:$A,'Product Families'!$P:$P),"")} | N84: {=iferror(xlookup($H84,'Product Families'!$A:$A,'Product Families'!$Q:$Q),"")} | O84: =iferror(M84/N84,"") | P84: =iferror(O84/$E84,"") | Q84: =round($D84*P84,2) -> 0 | R84: {=iferror(xlookup($I84,'Product Families'!$A:$A,'Product Families'!$P:$P),"")} | S84: {=iferror(xlookup($I84,'Product Families'!$A:$A,'Product Families'!$Q:$Q),"")} | T84: =iferror(R84/S84,"") | U84: =iferror(T84/$E84,"") | V84: =round($D84*U84,2) -> 0 | W84: {=iferror(xlookup($J84,'Product Families'!$A:$A,'Product Families'!$P:$P),"")} | X84: {=iferror(xlookup($J84,'Product Families'!$A:$A,'Product Families'!$Q:$Q),"")} | Y84: =iferror(W84/X84,"") | Z84: =iferror(Y84/$E84,"") | AA84: =round($D84*Z84,2) -> 0 | AB84: {=iferror(xlookup($K84,'Product Families'!$A:$A,'Product Families'!$P:$P),"")} | AC84: {=iferror(xlookup($K84,'Product Families'!$A:$A,'Product Families'!$Q:$Q),"")} | AD84: =iferror(AB84/AC84,"") | AE84: =iferror(AD84/$E84,"") | AF84: =round($D84*AE84,2) -> 0 | AG84: {=iferror(xlookup($L84,'Product Families'!$A:$A,'Product Families'!$P:$P),"")} | AH84: {=iferror(xlookup($L84,'Product Families'!$A:$A,'Product Families'!$Q:$Q),"")} | AI84: =iferror(AG84/AH84,"") | AJ84: =iferror(AI84/$E84,"") | AK84: =round($D84*AJ84,2) -> 0
A85: CarEO | B85: 1.59 | C85: 1 | D85: =iferror(B85/C85,"") -> 1.59 | E85: =sum(O85+T85+Y85+AD85+AI85) -> 0 | M85: {=iferror(xlookup($H85,'Product Families'!$A:$A,'Product Families'!$P:$P),"")} | N85: {=iferror(xlookup($H85,'Product Families'!$A:$A,'Product Families'!$Q:$Q),"")} | O85: =iferror(M85/N85,"") | P85: =iferror(O85/$E85,"") | Q85: =round($D85*P85,2) -> 0 | R85: {=iferror(xlookup($I85,'Product Families'!$A:$A,'Product Families'!$P:$P),"")} | S85: {=iferror(xlookup($I85,'Product Families'!$A:$A,'Product Families'!$Q:$Q),"")} | T85: =iferror(R85/S85,"") | U85: =iferror(T85/$E85,"") | V85: =round($D85*U85,2) -> 0 | W85: {=iferror(xlookup($J85,'Product Families'!$A:$A,'Product Families'!$P:$P),"")} | X85: {=iferror(xlookup($J85,'Product Families'!$A:$A,'Product Families'!$Q:$Q),"")} | Y85: =iferror(W85/X85,"") | Z85: =iferror(Y85/$E85,"") | AA85: =round($D85*Z85,2) -> 0 | AB85: {=iferror(xlookup($K85,'Product Families'!$A:$A,'Product Families'!$P:$P),"")} | AC85: {=iferror(xlookup($K85,'Product Families'!$A:$A,'Product Families'!$Q:$Q),"")} | AD85: =iferror(AB85/AC85,"") | AE85: =iferror(AD85/$E85,"") | AF85: =round($D85*AE85,2) -> 0 | AG85: {=iferror(xlookup($L85,'Product Families'!$A:$A,'Product Families'!$P:$P),"")} | AH85: {=iferror(xlookup($L85,'Product Families'!$A:$A,'Product Families'!$Q:$Q),"")} | AI85: =iferror(AG85/AH85,"") | AJ85: =iferror(AI85/$E85,"") | AK85: =round($D85*AJ85,2) -> 0
A86: careoul | B86: 15.9 | C86: 10 | D86: =iferror(B86/C86,"") -> 1.59 | E86: =sum(O86+T86+Y86+AD86+AI86) -> 0 | M86: {=iferror(xlookup($H86,'Product Families'!$A:$A,'Product Families'!$P:$P),"")} | N86: {=iferror(xlookup($H86,'Product Families'!$A:$A,'Product Families'!$Q:$Q),"")} | O86: =iferror(M86/N86,"") | P86: =iferror(O86/$E86,"") | Q86: =round($D86*P86,2) -> 0 | R86: {=iferror(xlookup($I86,'Product Families'!$A:$A,'Product Families'!$P:$P),"")} | S86: {=iferror(xlookup($I86,'Product Families'!$A:$A,'Product Families'!$Q:$Q),"")} | T86: =iferror(R86/S86,"") | U86: =iferror(T86/$E86,"") | V86: =round($D86*U86,2) -> 0 | W86: {=iferror(xlookup($J86,'Product Families'!$A:$A,'Product Families'!$P:$P),"")} | X86: {=iferror(xlookup($J86,'Product Families'!$A:$A,'Product Families'!$Q:$Q),"")} | Y86: =iferror(W86/X86,"") | Z86: =iferror(Y86/$E86,"") | AA86: =round($D86*Z86,2) -> 0 | AB86: {=iferror(xlookup($K86,'Product Families'!$A:$A,'Product Families'!$P:$P),"")} | AC86: {=iferror(xlookup($K86,'Product Families'!$A:$A,'Product Families'!$Q:$Q),"")} | AD86: =iferror(AB86/AC86,"") | AE86: =iferror(AD86/$E86,"") | AF86: =round($D86*AE86,2) -> 0 | AG86: {=iferror(xlookup($L86,'Product Families'!$A:$A,'Product Families'!$P:$P),"")} | AH86: {=iferror(xlookup($L86,'Product Families'!$A:$A,'Product Families'!$Q:$Q),"")} | AI86: =iferror(AG86/AH86,"") | AJ86: =iferror(AI86/$E86,"") | AK86: =round($D86*AJ86,2) -> 0
A87: CBB1 | B87: 10.18 | C87: 3 | D87: =iferror(B87/C87,"") -> 3.3933333 | E87: =sum(O87+T87+Y87+AD87+AI87) -> 0 | G87: cbb code | M87: {=iferror(xlookup($H87,'Product Families'!$A:$A,'Product Families'!$P:$P),"")} | N87: {=iferror(xlookup($H87,'Product Families'!$A:$A,'Product Families'!$Q:$Q),"")} | O87: =iferror(M87/N87,"") | P87: =iferror(O87/$E87,"") | Q87: =round($D87*P87,2) -> 0 | R87: {=iferror(xlookup($I87,'Product Families'!$A:$A,'Product Families'!$P:$P),"")} | S87: {=iferror(xlookup($I87,'Product Families'!$A:$A,'Product Families'!$Q:$Q),"")} | T87: =iferror(R87/S87,"") | U87: =iferror(T87/$E87,"") | V87: =round($D87*U87,2) -> 0 | W87: {=iferror(xlookup($J87,'Product Families'!$A:$A,'Product Families'!$P:$P),"")} | X87: {=iferror(xlookup($J87,'Product Families'!$A:$A,'Product Families'!$Q:$Q),"")} | Y87: =iferror(W87/X87,"") | Z87: =iferror(Y87/$E87,"") | AA87: =round($D87*Z87,2) -> 0 | AB87: {=iferror(xlookup($K87,'Product Families'!$A:$A,'Product Families'!$P:$P),"")} | AC87: {=iferror(xlookup($K87,'Product Families'!$A:$A,'Product Families'!$Q:$Q),"")} | AD87: =iferror(AB87/AC87,"") | AE87: =iferror(AD87/$E87,"") | AF87: =round($D87*AE87,2) -> 0 | AG87: {=iferror(xlookup($L87,'Product Families'!$A:$A,'Product Families'!$P:$P),"")} | AH87: {=iferror(xlookup($L87,'Product Families'!$A:$A,'Product Families'!$Q:$Q),"")} | AI87: =iferror(AG87/AH87,"") | AJ87: =iferror(AI87/$E87,"") | AK87: =round($D87*AJ87,2) -> 0
A88: CBB2 | B88: n/a | D88: =iferror(B88/C88,"") | E88: =sum(O88+T88+Y88+AD88+AI88) -> 0 | G88: code not in use | M88: {=iferror(xlookup($H88,'Product Families'!$A:$A,'Product Families'!$P:$P),"")} | N88: {=iferror(xlookup($H88,'Product Families'!$A:$A,'Product Families'!$Q:$Q),"")} | O88: =iferror(M88/N88,"") | P88: =iferror(O88/$E88,"") | Q88: =round($D88*P88,2) -> 0 | R88: {=iferror(xlookup($I88,'Product Families'!$A:$A,'Product Families'!$P:$P),"")} | S88: {=iferror(xlookup($I88,'Product Families'!$A:$A,'Product Families'!$Q:$Q),"")} | T88: =iferror(R88/S88,"") | U88: =iferror(T88/$E88,"") | V88: =round($D88*U88,2) -> 0 | W88: {=iferror(xlookup($J88,'Product Families'!$A:$A,'Product Families'!$P:$P),"")} | X88: {=iferror(xlookup($J88,'Product Families'!$A:$A,'Product Families'!$Q:$Q),"")} | Y88: =iferror(W88/X88,"") | Z88: =iferror(Y88/$E88,"") | AA88: =round($D88*Z88,2) -> 0 | AB88: {=iferror(xlookup($K88,'Product Families'!$A:$A,'Product Families'!$P:$P),"")} | AC88: {=iferror(xlookup($K88,'Product Families'!$A:$A,'Product Families'!$Q:$Q),"")} | AD88: =iferror(AB88/AC88,"") | AE88: =iferror(AD88/$E88,"") | AF88: =round($D88*AE88,2) -> 0 | AG88: {=iferror(xlookup($L88,'Product Families'!$A:$A,'Product Families'!$P:$P),"")} | AH88: {=iferror(xlookup($L88,'Product Families'!$A:$A,'Product Families'!$Q:$Q),"")} | AI88: =iferror(AG88/AH88,"") | AJ88: =iferror(AI88/$E88,"") | AK88: =round($D88*AJ88,2) -> 0
A89: CBBP | B89: n/a | D89: =iferror(B89/C89,"") | E89: =sum(O89+T89+Y89+AD89+AI89) -> 0 | G89: code not in use | M89: {=iferror(xlookup($H89,'Product Families'!$A:$A,'Product Families'!$P:$P),"")} | N89: {=iferror(xlookup($H89,'Product Families'!$A:$A,'Product Families'!$Q:$Q),"")} | O89: =iferror(M89/N89,"") | P89: =iferror(O89/$E89,"") | Q89: =round($D89*P89,2) -> 0 | R89: {=iferror(xlookup($I89,'Product Families'!$A:$A,'Product Families'!$P:$P),"")} | S89: {=iferror(xlookup($I89,'Product Families'!$A:$A,'Product Families'!$Q:$Q),"")} | T89: =iferror(R89/S89,"") | U89: =iferror(T89/$E89,"") | V89: =round($D89*U89,2) -> 0 | W89: {=iferror(xlookup($J89,'Product Families'!$A:$A,'Product Families'!$P:$P),"")} | X89: {=iferror(xlookup($J89,'Product Families'!$A:$A,'Product Families'!$Q:$Q),"")} | Y89: =iferror(W89/X89,"") | Z89: =iferror(Y89/$E89,"") | AA89: =round($D89*Z89,2) -> 0 | AB89: {=iferror(xlookup($K89,'Product Families'!$A:$A,'Product Families'!$P:$P),"")} | AC89: {=iferror(xlookup($K89,'Product Families'!$A:$A,'Product Families'!$Q:$Q),"")} | AD89: =iferror(AB89/AC89,"") | AE89: =iferror(AD89/$E89,"") | AF89: =round($D89*AE89,2) -> 0 | AG89: {=iferror(xlookup($L89,'Product Families'!$A:$A,'Product Families'!$P:$P),"")} | AH89: {=iferror(xlookup($L89,'Product Families'!$A:$A,'Product Families'!$Q:$Q),"")} | AI89: =iferror(AG89/AH89,"") | AJ89: =iferror(AI89/$E89,"") | AK89: =round($D89*AJ89,2) -> 0
A90: CBF | B90: 3.02 - 6.57 | D90: =iferror(B90/C90,"") | E90: =sum(O90+T90+Y90+AD90+AI90) -> 0 | G90: 2 different prices | M90: {=iferror(xlookup($H90,'Product Families'!$A:$A,'Product Families'!$P:$P),"")} | N90: {=iferror(xlookup($H90,'Product Families'!$A:$A,'Product Families'!$Q:$Q),"")} | O90: =iferror(M90/N90,"") | P90: =iferror(O90/$E90,"") | Q90: =round($D90*P90,2) -> 0 | R90: {=iferror(xlookup($I90,'Product Families'!$A:$A,'Product Families'!$P:$P),"")} | S90: {=iferror(xlookup($I90,'Product Families'!$A:$A,'Product Families'!$Q:$Q),"")} | T90: =iferror(R90/S90,"") | U90: =iferror(T90/$E90,"") | V90: =round($D90*U90,2) -> 0 | W90: {=iferror(xlookup($J90,'Product Families'!$A:$A,'Product Families'!$P:$P),"")} | X90: {=iferror(xlookup($J90,'Product Families'!$A:$A,'Product Families'!$Q:$Q),"")} | Y90: =iferror(W90/X90,"") | Z90: =iferror(Y90/$E90,"") | AA90: =round($D90*Z90,2) -> 0 | AB90: {=iferror(xlookup($K90,'Product Families'!$A:$A,'Product Families'!$P:$P),"")} | AC90: {=iferror(xlookup($K90,'Product Families'!$A:$A,'Product Families'!$Q:$Q),"")} | AD90: =iferror(AB90/AC90,"") | AE90: =iferror(AD90/$E90,"") | AF90: =round($D90*AE90,2) -> 0 | AG90: {=iferror(xlookup($L90,'Product Families'!$A:$A,'Product Families'!$P:$P),"")} | AH90: {=iferror(xlookup($L90,'Product Families'!$A:$A,'Product Families'!$Q:$Q),"")} | AI90: =iferror(AG90/AH90,"") | AJ90: =iferror(AI90/$E90,"") | AK90: =round($D90*AJ90,2) -> 0
A91: CBFP | B91: n/a | D91: =iferror(B91/C91,"") | E91: =sum(O91+T91+Y91+AD91+AI91) -> 0 | G91: code not in use | M91: {=iferror(xlookup($H91,'Product Families'!$A:$A,'Product Families'!$P:$P),"")} | N91: {=iferror(xlookup($H91,'Product Families'!$A:$A,'Product Families'!$Q:$Q),"")} | O91: =iferror(M91/N91,"") | P91: =iferror(O91/$E91,"") | Q91: =round($D91*P91,2) -> 0 | R91: {=iferror(xlookup($I91,'Product Families'!$A:$A,'Product Families'!$P:$P),"")} | S91: {=iferror(xlookup($I91,'Product Families'!$A:$A,'Product Families'!$Q:$Q),"")} | T91: =iferror(R91/S91,"") | U91: =iferror(T91/$E91,"") | V91: =round($D91*U91,2) -> 0 | W91: {=iferror(xlookup($J91,'Product Families'!$A:$A,'Product Families'!$P:$P),"")} | X91: {=iferror(xlookup($J91,'Product Families'!$A:$A,'Product Families'!$Q:$Q),"")} | Y91: =iferror(W91/X91,"") | Z91: =iferror(Y91/$E91,"") | AA91: =round($D91*Z91,2) -> 0 | AB91: {=iferror(xlookup($K91,'Product Families'!$A:$A,'Product Families'!$P:$P),"")} | AC91: {=iferror(xlookup($K91,'Product Families'!$A:$A,'Product Families'!$Q:$Q),"")} | AD91: =iferror(AB91/AC91,"") | AE91: =iferror(AD91/$E91,"") | AF91: =round($D91*AE91,2) -> 0 | AG91: {=iferror(xlookup($L91,'Product Families'!$A:$A,'Product Families'!$P:$P),"")} | AH91: {=iferror(xlookup($L91,'Product Families'!$A:$A,'Product Families'!$Q:$Q),"")} | AI91: =iferror(AG91/AH91,"") | AJ91: =iferror(AI91/$E91,"") | AK91: =round($D91*AJ91,2) -> 0
A92: CCREBLUL | B92: n/a | D92: =iferror(B92/C92,"") | E92: =sum(O92+T92+Y92+AD92+AI92) -> 0 | G92: code not in use | M92: {=iferror(xlookup($H92,'Product Families'!$A:$A,'Product Families'!$P:$P),"")} | N92: {=iferror(xlookup($H92,'Product Families'!$A:$A,'Product Families'!$Q:$Q),"")} | O92: =iferror(M92/N92,"") | P92: =iferror(O92/$E92,"") | Q92: =round($D92*P92,2) -> 0 | R92: {=iferror(xlookup($I92,'Product Families'!$A:$A,'Product Families'!$P:$P),"")} | S92: {=iferror(xlookup($I92,'Product Families'!$A:$A,'Product Families'!$Q:$Q),"")} | T92: =iferror(R92/S92,"") | U92: =iferror(T92/$E92,"") | V92: =round($D92*U92,2) -> 0 | W92: {=iferror(xlookup($J92,'Product Families'!$A:$A,'Product Families'!$P:$P),"")} | X92: {=iferror(xlookup($J92,'Product Families'!$A:$A,'Product Families'!$Q:$Q),"")} | Y92: =iferror(W92/X92,"") | Z92: =iferror(Y92/$E92,"") | AA92: =round($D92*Z92,2) -> 0 | AB92: {=iferror(xlookup($K92,'Product Families'!$A:$A,'Product Families'!$P:$P),"")} | AC92: {=iferror(xlookup($K92,'Product Families'!$A:$A,'Product Families'!$Q:$Q),"")} | AD92: =iferror(AB92/AC92,"") | AE92: =iferror(AD92/$E92,"") | AF92: =round($D92*AE92,2) -> 0 | AG92: {=iferror(xlookup($L92,'Product Families'!$A:$A,'Product Families'!$P:$P),"")} | AH92: {=iferror(xlookup($L92,'Product Families'!$A:$A,'Product Families'!$Q:$Q),"")} | AI92: =iferror(AG92/AH92,"") | AJ92: =iferror(AI92/$E92,"") | AK92: =round($D92*AJ92,2) -> 0
A93: CEyeP | B93: 4.19 | C93: 1 | D93: =iferror(B93/C93,"") -> 4.19 | E93: =sum(O93+T93+Y93+AD93+AI93) -> 0 | M93: {=iferror(xlookup($H93,'Product Families'!$A:$A,'Product Families'!$P:$P),"")} | N93: {=iferror(xlookup($H93,'Product Families'!$A:$A,'Product Families'!$Q:$Q),"")} | O93: =iferror(M93/N93,"") | P93: =iferror(O93/$E93,"") | Q93: =round($D93*P93,2) -> 0 | R93: {=iferror(xlookup($I93,'Product Families'!$A:$A,'Product Families'!$P:$P),"")} | S93: {=iferror(xlookup($I93,'Product Families'!$A:$A,'Product Families'!$Q:$Q),"")} | T93: =iferror(R93/S93,"") | U93: =iferror(T93/$E93,"") | V93: =round($D93*U93,2) -> 0 | W93: {=iferror(xlookup($J93,'Product Families'!$A:$A,'Product Families'!$P:$P),"")} | X93: {=iferror(xlookup($J93,'Product Families'!$A:$A,'Product Families'!$Q:$Q),"")} | Y93: =iferror(W93/X93,"") | Z93: =iferror(Y93/$E93,"") | AA93: =round($D93*Z93,2) -> 0 | AB93: {=iferror(xlookup($K93,'Product Families'!$A:$A,'Product Families'!$P:$P),"")} | AC93: {=iferror(xlookup($K93,'Product Families'!$A:$A,'Product Families'!$Q:$Q),"")} | AD93: =iferror(AB93/AC93,"") | AE93: =iferror(AD93/$E93,"") | AF93: =round($D93*AE93,2) -> 0 | AG93: {=iferror(xlookup($L93,'Product Families'!$A:$A,'Product Families'!$P:$P),"")} | AH93: {=iferror(xlookup($L93,'Product Families'!$A:$A,'Product Families'!$Q:$Q),"")} | AI93: =iferror(AG93/AH93,"") | AJ93: =iferror(AI93/$E93,"") | AK93: =round($D93*AJ93,2) -> 0
A94: ChillP | B94: 5.25 | C94: 1 | D94: =iferror(B94/C94,"") -> 5.25 | E94: =sum(O94+T94+Y94+AD94+AI94) -> 0 | M94: {=iferror(xlookup($H94,'Product Families'!$A:$A,'Product Families'!$P:$P),"")} | N94: {=iferror(xlookup($H94,'Product Families'!$A:$A,'Product Families'!$Q:$Q),"")} | O94: =iferror(M94/N94,"") | P94: =iferror(O94/$E94,"") | Q94: =round($D94*P94,2) -> 0 | R94: {=iferror(xlookup($I94,'Product Families'!$A:$A,'Product Families'!$P:$P),"")} | S94: {=iferror(xlookup($I94,'Product Families'!$A:$A,'Product Families'!$Q:$Q),"")} | T94: =iferror(R94/S94,"") | U94: =iferror(T94/$E94,"") | V94: =round($D94*U94,2) -> 0 | W94: {=iferror(xlookup($J94,'Product Families'!$A:$A,'Product Families'!$P:$P),"")} | X94: {=iferror(xlookup($J94,'Product Families'!$A:$A,'Product Families'!$Q:$Q),"")} | Y94: =iferror(W94/X94,"") | Z94: =iferror(Y94/$E94,"") | AA94: =round($D94*Z94,2) -> 0 | AB94: {=iferror(xlookup($K94,'Product Families'!$A:$A,'Product Families'!$P:$P),"")} | AC94: {=iferror(xlookup($K94,'Product Families'!$A:$A,'Product Families'!$Q:$Q),"")} | AD94: =iferror(AB94/AC94,"") | AE94: =iferror(AD94/$E94,"") | AF94: =round($D94*AE94,2) -> 0 | AG94: {=iferror(xlookup($L94,'Product Families'!$A:$A,'Product Families'!$P:$P),"")} | AH94: {=iferror(xlookup($L94,'Product Families'!$A:$A,'Product Families'!$Q:$Q),"")} | AI94: =iferror(AG94/AH94,"") | AJ94: =iferror(AI94/$E94,"") | AK94: =round($D94*AJ94,2) -> 0
A95: CHSB | B95: 10.34 | C95: 5 | D95: =iferror(B95/C95,"") -> 2.068 | E95: =sum(O95+T95+Y95+AD95+AI95) -> 0 | M95: {=iferror(xlookup($H95,'Product Families'!$A:$A,'Product Families'!$P:$P),"")} | N95: {=iferror(xlookup($H95,'Product Families'!$A:$A,'Product Families'!$Q:$Q),"")} | O95: =iferror(M95/N95,"") | P95: =iferror(O95/$E95,"") | Q95: =round($D95*P95,2) -> 0 | R95: {=iferror(xlookup($I95,'Product Families'!$A:$A,'Product Families'!$P:$P),"")} | S95: {=iferror(xlookup($I95,'Product Families'!$A:$A,'Product Families'!$Q:$Q),"")} | T95: =iferror(R95/S95,"") | U95: =iferror(T95/$E95,"") | V95: =round($D95*U95,2) -> 0 | W95: {=iferror(xlookup($J95,'Product Families'!$A:$A,'Product Families'!$P:$P),"")} | X95: {=iferror(xlookup($J95,'Product Families'!$A:$A,'Product Families'!$Q:$Q),"")} | Y95: =iferror(W95/X95,"") | Z95: =iferror(Y95/$E95,"") | AA95: =round($D95*Z95,2) -> 0 | AB95: {=iferror(xlookup($K95,'Product Families'!$A:$A,'Product Families'!$P:$P),"")} | AC95: {=iferror(xlookup($K95,'Product Families'!$A:$A,'Product Families'!$Q:$Q),"")} | AD95: =iferror(AB95/AC95,"") | AE95: =iferror(AD95/$E95,"") | AF95: =round($D95*AE95,2) -> 0 | AG95: {=iferror(xlookup($L95,'Product Families'!$A:$A,'Product Families'!$P:$P),"")} | AH95: {=iferror(xlookup($L95,'Product Families'!$A:$A,'Product Families'!$Q:$Q),"")} | AI95: =iferror(AG95/AH95,"") | AJ95: =iferror(AI95/$E95,"") | AK95: =round($D95*AJ95,2) -> 0
A96: CHSBP | B96: n/a | D96: =iferror(B96/C96,"") | E96: =sum(O96+T96+Y96+AD96+AI96) -> 0 | G96: code not in use | M96: {=iferror(xlookup($H96,'Product Families'!$A:$A,'Product Families'!$P:$P),"")} | N96: {=iferror(xlookup($H96,'Product Families'!$A:$A,'Product Families'!$Q:$Q),"")} | O96: =iferror(M96/N96,"") | P96: =iferror(O96/$E96,"") | Q96: =round($D96*P96,2) -> 0 | R96: {=iferror(xlookup($I96,'Product Families'!$A:$A,'Product Families'!$P:$P),"")} | S96: {=iferror(xlookup($I96,'Product Families'!$A:$A,'Product Families'!$Q:$Q),"")} | T96: =iferror(R96/S96,"") | U96: =iferror(T96/$E96,"") | V96: =round($D96*U96,2) -> 0 | W96: {=iferror(xlookup($J96,'Product Families'!$A:$A,'Product Families'!$P:$P),"")} | X96: {=iferror(xlookup($J96,'Product Families'!$A:$A,'Product Families'!$Q:$Q),"")} | Y96: =iferror(W96/X96,"") | Z96: =iferror(Y96/$E96,"") | AA96: =round($D96*Z96,2) -> 0 | AB96: {=iferror(xlookup($K96,'Product Families'!$A:$A,'Product Families'!$P:$P),"")} | AC96: {=iferror(xlookup($K96,'Product Families'!$A:$A,'Product Families'!$Q:$Q),"")} | AD96: =iferror(AB96/AC96,"") | AE96: =iferror(AD96/$E96,"") | AF96: =round($D96*AE96,2) -> 0 | AG96: {=iferror(xlookup($L96,'Product Families'!$A:$A,'Product Families'!$P:$P),"")} | AH96: {=iferror(xlookup($L96,'Product Families'!$A:$A,'Product Families'!$Q:$Q),"")} | AI96: =iferror(AG96/AH96,"") | AJ96: =iferror(AI96/$E96,"") | AK96: =round($D96*AJ96,2) -> 0
A97: CHSBUL | B97: 10.96 | C97: 5 | D97: =iferror(B97/C97,"") -> 2.192 | E97: =sum(O97+T97+Y97+AD97+AI97) -> 0 | M97: {=iferror(xlookup($H97,'Product Families'!$A:$A,'Product Families'!$P:$P),"")} | N97: {=iferror(xlookup($H97,'Product Families'!$A:$A,'Product Families'!$Q:$Q),"")} | O97: =iferror(M97/N97,"") | P97: =iferror(O97/$E97,"") | Q97: =round($D97*P97,2) -> 0 | R97: {=iferror(xlookup($I97,'Product Families'!$A:$A,'Product Families'!$P:$P),"")} | S97: {=iferror(xlookup($I97,'Product Families'!$A:$A,'Product Families'!$Q:$Q),"")} | T97: =iferror(R97/S97,"") | U97: =iferror(T97/$E97,"") | V97: =round($D97*U97,2) -> 0 | W97: {=iferror(xlookup($J97,'Product Families'!$A:$A,'Product Families'!$P:$P),"")} | X97: {=iferror(xlookup($J97,'Product Families'!$A:$A,'Product Families'!$Q:$Q),"")} | Y97: =iferror(W97/X97,"") | Z97: =iferror(Y97/$E97,"") | AA97: =round($D97*Z97,2) -> 0 | AB97: {=iferror(xlookup($K97,'Product Families'!$A:$A,'Product Families'!$P:$P),"")} | AC97: {=iferror(xlookup($K97,'Product Families'!$A:$A,'Product Families'!$Q:$Q),"")} | AD97: =iferror(AB97/AC97,"") | AE97: =iferror(AD97/$E97,"") | AF97: =round($D97*AE97,2) -> 0 | AG97: {=iferror(xlookup($L97,'Product Families'!$A:$A,'Product Families'!$P:$P),"")} | AH97: {=iferror(xlookup($L97,'Product Families'!$A:$A,'Product Families'!$Q:$Q),"")} | AI97: =iferror(AG97/AH97,"") | AJ97: =iferror(AI97/$E97,"") | AK97: =round($D97*AJ97,2) -> 0
A98: CHSBULP | B98: n/a | D98: =iferror(B98/C98,"") | E98: =sum(O98+T98+Y98+AD98+AI98) -> 0 | G98: code not in use | M98: {=iferror(xlookup($H98,'Product Families'!$A:$A,'Product Families'!$P:$P),"")} | N98: {=iferror(xlookup($H98,'Product Families'!$A:$A,'Product Families'!$Q:$Q),"")} | O98: =iferror(M98/N98,"") | P98: =iferror(O98/$E98,"") | Q98: =round($D98*P98,2) -> 0 | R98: {=iferror(xlookup($I98,'Product Families'!$A:$A,'Product Families'!$P:$P),"")} | S98: {=iferror(xlookup($I98,'Product Families'!$A:$A,'Product Families'!$Q:$Q),"")} | T98: =iferror(R98/S98,"") | U98: =iferror(T98/$E98,"") | V98: =round($D98*U98,2) -> 0 | W98: {=iferror(xlookup($J98,'Product Families'!$A:$A,'Product Families'!$P:$P),"")} | X98: {=iferror(xlookup($J98,'Product Families'!$A:$A,'Product Families'!$Q:$Q),"")} | Y98: =iferror(W98/X98,"") | Z98: =iferror(Y98/$E98,"") | AA98: =round($D98*Z98,2) -> 0 | AB98: {=iferror(xlookup($K98,'Product Families'!$A:$A,'Product Families'!$P:$P),"")} | AC98: {=iferror(xlookup($K98,'Product Families'!$A:$A,'Product Families'!$Q:$Q),"")} | AD98: =iferror(AB98/AC98,"") | AE98: =iferror(AD98/$E98,"") | AF98: =round($D98*AE98,2) -> 0 | AG98: {=iferror(xlookup($L98,'Product Families'!$A:$A,'Product Families'!$P:$P),"")} | AH98: {=iferror(xlookup($L98,'Product Families'!$A:$A,'Product Families'!$Q:$Q),"")} | AI98: =iferror(AG98/AH98,"") | AJ98: =iferror(AI98/$E98,"") | AK98: =round($D98*AJ98,2) -> 0
A99: CJBB | B99: n/a | D99: =iferror(B99/C99,"") | E99: =sum(O99+T99+Y99+AD99+AI99) -> 0 | G99: Discontinued | M99: {=iferror(xlookup($H99,'Product Families'!$A:$A,'Product Families'!$P:$P),"")} | N99: {=iferror(xlookup($H99,'Product Families'!$A:$A,'Product Families'!$Q:$Q),"")} | O99: =iferror(M99/N99,"") | P99: =iferror(O99/$E99,"") | Q99: =round($D99*P99,2) -> 0 | R99: {=iferror(xlookup($I99,'Product Families'!$A:$A,'Product Families'!$P:$P),"")} | S99: {=iferror(xlookup($I99,'Product Families'!$A:$A,'Product Families'!$Q:$Q),"")} | T99: =iferror(R99/S99,"") | U99: =iferror(T99/$E99,"") | V99: =round($D99*U99,2) -> 0 | W99: {=iferror(xlookup($J99,'Product Families'!$A:$A,'Product Families'!$P:$P),"")} | X99: {=iferror(xlookup($J99,'Product Families'!$A:$A,'Product Families'!$Q:$Q),"")} | Y99: =iferror(W99/X99,"") | Z99: =iferror(Y99/$E99,"") | AA99: =round($D99*Z99,2) -> 0 | AB99: {=iferror(xlookup($K99,'Product Families'!$A:$A,'Product Families'!$P:$P),"")} | AC99: {=iferror(xlookup($K99,'Product Families'!$A:$A,'Product Families'!$Q:$Q),"")} | AD99: =iferror(AB99/AC99,"") | AE99: =iferror(AD99/$E99,"") | AF99: =round($D99*AE99,2) -> 0 | AG99: {=iferror(xlookup($L99,'Product Families'!$A:$A,'Product Families'!$P:$P),"")} | AH99: {=iferror(xlookup($L99,'Product Families'!$A:$A,'Product Families'!$Q:$Q),"")} | AI99: =iferror(AG99/AH99,"") | AJ99: =iferror(AI99/$E99,"") | AK99: =round($D99*AJ99,2) -> 0
A100: CJBBP | B100: n/a | D100: =iferror(B100/C100,"") | E100: =sum(O100+T100+Y100+AD100+AI100) -> 0 | G100: code not in use | M100: {=iferror(xlookup($H100,'Product Families'!$A:$A,'Product Families'!$P:$P),"")} | N100: {=iferror(xlookup($H100,'Product Families'!$A:$A,'Product Families'!$Q:$Q),"")} | O100: =iferror(M100/N100,"") | P100: =iferror(O100/$E100,"") | Q100: =round($D100*P100,2) -> 0 | R100: {=iferror(xlookup($I100,'Product Families'!$A:$A,'Product Families'!$P:$P),"")} | S100: {=iferror(xlookup($I100,'Product Families'!$A:$A,'Product Families'!$Q:$Q),"")} | T100: =iferror(R100/S100,"") | U100: =iferror(T100/$E100,"") | V100: =round($D100*U100,2) -> 0 | W100: {=iferror(xlookup($J100,'Product Families'!$A:$A,'Product Families'!$P:$P),"")} | X100: {=iferror(xlookup($J100,'Product Families'!$A:$A,'Product Families'!$Q:$Q),"")} | Y100: =iferror(W100/X100,"") | Z100: =iferror(Y100/$E100,"") | AA100: =round($D100*Z100,2) -> 0 | AB100: {=iferror(xlookup($K100,'Product Families'!$A:$A,'Product Families'!$P:$P),"")} | AC100: {=iferror(xlookup($K100,'Product Families'!$A:$A,'Product Families'!$Q:$Q),"")} | AD100: =iferror(AB100/AC100,"") | AE100: =iferror(AD100/$E100,"") | AF100: =round($D100*AE100,2) -> 0 | AG100: {=iferror(xlookup($L100,'Product Families'!$A:$A,'Product Families'!$P:$P),"")} | AH100: {=iferror(xlookup($L100,'Product Families'!$A:$A,'Product Families'!$Q:$Q),"")} | AI100: =iferror(AG100/AH100,"") | AJ100: =iferror(AI100/$E100,"") | AK100: =round($D100*AJ100,2) -> 0
...

Sheet Wholesale Earnings
B1: Totals
A2: Name | B2: Week 1 | C2: Week 2 | D2: Week 3 | E2: Week 4 | F2: Week 5
A3: Audrey Migliaccio | B3: =sumif('Week 1 - Making'!$A:$A,$A3,'Week 1 - Making'!$Y:$Y) -> 0 | C3: =sumif('Week 2 - Making'!$A:$A,$A3,'Week 2 - Making'!$Y:$Y) -> 0 | D3: =sumif('Week 3 - Making'!$A:$A,$A3,'Week 3 - Making'!$Y:$Y) -> 0 | E3: =sumif('Week 4 - Making'!$A:$A,$A3,'Week 4 - Making'!$Y:$Y) -> 0 | F3: =sumif('Week 5 - Making'!$A:$A,$A3,'Week 5 - Making'!$Y:$Y) -> 0
A4: Filip Kurinec | B4: =sumif('Week 1 - Making'!$A:$A,$A4,'Week 1 - Making'!$Y:$Y) -> 0 | C4: =sumif('Week 2 - Making'!$A:$A,$A4,'Week 2 - Making'!$Y:$Y) -> 0 | D4: =sumif('Week 3 - Making'!$A:$A,$A4,'Week 3 - Making'!$Y:$Y) -> 0 | E4: =sumif('Week 4 - Making'!$A:$A,$A4,'Week 4 - Making'!$Y:$Y) -> 0 | F4: =sumif('Week 5 - Making'!$A:$A,$A4,'Week 5 - Making'!$Y:$Y) -> 0
A5: Georgeta Videanu | B5: =sumif('Week 1 - Making'!$A:$A,$A5,'Week 1 - Making'!$Y:$Y) -> 0 | C5: =sumif('Week 2 - Making'!$A:$A,$A5,'Week 2 - Making'!$Y:$Y) -> 0 | D5: =sumif('Week 3 - Making'!$A:$A,$A5,'Week 3 - Making'!$Y:$Y) -> 0 | E5: =sumif('Week 4 - Making'!$A:$A,$A5,'Week 4 - Making'!$Y:$Y) -> 0 | F5: =sumif('Week 5 - Making'!$A:$A,$A5,'Week 5 - Making'!$Y:$Y) -> 0
A6: Gheorghe Hutu | B6: =sumif('Week 1 - Making'!$A:$A,$A6,'Week 1 - Making'!$Y:$Y) -> 1893.43 | C6: =sumif('Week 2 - Making'!$A:$A,$A6,'Week 2 - Making'!$Y:$Y) -> 1466.08 | D6: =sumif('Week 3 - Making'!$A:$A,$A6,'Week 3 - Making'!$Y:$Y) -> 0 | E6: =sumif('Week 4 - Making'!$A:$A,$A6,'Week 4 - Making'!$Y:$Y) -> 0 | F6: =sumif('Week 5 - Making'!$A:$A,$A6,'Week 5 - Making'!$Y:$Y) -> 0
A7: Gintare Grimalauskiene | B7: =sumif('Week 1 - Making'!$A:$A,$A7,'Week 1 - Making'!$Y:$Y) -> 0 | C7: =sumif('Week 2 - Making'!$A:$A,$A7,'Week 2 - Making'!$Y:$Y) -> 0 | D7: =sumif('Week 3 - Making'!$A:$A,$A7,'Week 3 - Making'!$Y:$Y) -> 0 | E7: =sumif('Week 4 - Making'!$A:$A,$A7,'Week 4 - Making'!$Y:$Y) -> 0 | F7: =sumif('Week 5 - Making'!$A:$A,$A7,'Week 5 - Making'!$Y:$Y) -> 0
A8: Izabela Walicht | B8: =sumif('Week 1 - Making'!$A:$A,$A8,'Week 1 - Making'!$Y:$Y) -> 0 | C8: =sumif('Week 2 - Making'!$A:$A,$A8,'Week 2 - Making'!$Y:$Y) -> 0 | D8: =sumif('Week 3 - Making'!$A:$A,$A8,'Week 3 - Making'!$Y:$Y) -> 0 | E8: =sumif('Week 4 - Making'!$A:$A,$A8,'Week 4 - Making'!$Y:$Y) -> 0 | F8: =sumif('Week 5 - Making'!$A:$A,$A8,'Week 5 - Making'!$Y:$Y) -> 0
A9: Katie Hammond | B9: =sumif('Week 1 - Making'!$A:$A,$A9,'Week 1 - Making'!$Y:$Y) -> 0 | C9: =sumif('Week 2 - Making'!$A:$A,$A9,'Week 2 - Making'!$Y:$Y) -> 0 | D9: =sumif('Week 3 - Making'!$A:$A,$A9,'Week 3 - Making'!$Y:$Y) -> 0 | E9: =sumif('Week 4 - Making'!$A:$A,$A9,'Week 4 - Making'!$Y:$Y) -> 0 | F9: =sumif('Week 5 - Making'!$A:$A,$A9,'Week 5 - Making'!$Y:$Y) -> 0
A10: Lucie Sicova | B10: =sumif('Week 1 - Making'!$A:$A,$A10,'Week 1 - Making'!$Y:$Y) -> 0 | C10: =sumif('Week 2 - Making'!$A:$A,$A10,'Week 2 - Making'!$Y:$Y) -> 0 | D10: =sumif('Week 3 - Making'!$A:$A,$A10,'Week 3 - Making'!$Y:$Y) -> 0 | E10: =sumif('Week 4 - Making'!$A:$A,$A10,'Week 4 - Making'!$Y:$Y) -> 0 | F10: =sumif('Week 5 - Making'!$A:$A,$A10,'Week 5 - Making'!$Y:$Y) -> 0
A11: Lucie Vondrakova | B11: =sumif('Week 1 - Making'!$A:$A,$A11,'Week 1 - Making'!$Y:$Y) -> 0 | C11: =sumif('Week 2 - Making'!$A:$A,$A11,'Week 2 - Making'!$Y:$Y) -> 0 | D11: =sumif('Week 3 - Making'!$A:$A,$A11,'Week 3 - Making'!$Y:$Y) -> 0 | E11: =sumif('Week 4 - Making'!$A:$A,$A11,'Week 4 - Making'!$Y:$Y) -> 0 | F11: =sumif('Week 5 - Making'!$A:$A,$A11,'Week 5 - Making'!$Y:$Y) -> 0
A12: Lukasz Szybowski | B12: =sumif('Week 1 - Making'!$A:$A,$A12,'Week 1 - Making'!$Y:$Y) -> 0 | C12: =sumif('Week 2 - Making'!$A:$A,$A12,'Week 2 - Making'!$Y:$Y) -> 0 | D12: =sumif('Week 3 - Making'!$A:$A,$A12,'Week 3 - Making'!$Y:$Y) -> 0 | E12: =sumif('Week 4 - Making'!$A:$A,$A12,'Week 4 - Making'!$Y:$Y) -> 0 | F12: =sumif('Week 5 - Making'!$A:$A,$A12,'Week 5 - Making'!$Y:$Y) -> 0
A13: Marija Morgunova | B13: =sumif('Week 1 - Making'!$A:$A,$A13,'Week 1 - Making'!$Y:$Y) -> 0 | C13: =sumif('Week 2 - Making'!$A:$A,$A13,'Week 2 - Making'!$Y:$Y) -> 0 | D13: =sumif('Week 3 - Making'!$A:$A,$A13,'Week 3 - Making'!$Y:$Y) -> 0 | E13: =sumif('Week 4 - Making'!$A:$A,$A13,'Week 4 - Making'!$Y:$Y) -> 0 | F13: =sumif('Week 5 - Making'!$A:$A,$A13,'Week 5 - Making'!$Y:$Y) -> 0
A14: Monika Kamionska | B14: =sumif('Week 1 - Making'!$A:$A,$A14,'Week 1 - Making'!$Y:$Y) -> 0 | C14: =sumif('Week 2 - Making'!$A:$A,$A14,'Week 2 - Making'!$Y:$Y) -> 0 | D14: =sumif('Week 3 - Making'!$A:$A,$A14,'Week 3 - Making'!$Y:$Y) -> 0 | E14: =sumif('Week 4 - Making'!$A:$A,$A14,'Week 4 - Making'!$Y:$Y) -> 0 | F14: =sumif('Week 5 - Making'!$A:$A,$A14,'Week 5 - Making'!$Y:$Y) -> 0
... A17: Zofia Baka | B17: =sumif('Week 1 - Making'!$A:$A,$A17,'Week 1 - Making'!$Y:$Y) -> 0 | C17: =sumif('Week 2 - Making'!$A:$A,$A17,'Week 2 - Making'!$Y:$Y) -> 0 | D17: =sumif('Week 3 - Making'!$A:$A,$A17,'Week 3 - Making'!$Y:$Y) -> 0 | E17: =sumif('Week 4 - Making'!$A:$A,$A17,'Week 4 - Making'!$Y:$Y) -> 0 | F17: =sumif('Week 5 - Making'!$A:$A,$A17,'Week 5 - Making'!$Y:$Y) -> 0

Sheet Production Sheet - Auto
I2: Georgeta Videanu
H4: Piece Rate | J4: WORKED HOURS
H5: 0 | I5: 12.21 | J5: Start | L5: :
C6: Date: | D6: =TODAY()+1 -> 46249 | H6: 1 | I6: 12.5 | J6: Finish | L6: :
H7: 2 | I7: 13.5 | J7: Breaks | L7: :
H8: 3 | I8: 14.5 | J8: Total Worked : | L8: :
D10: Targets (Per Hour) | L10: QC Check
A11: Item Code | B11: Family | C11: Amount Required | D11: 0 | E11: 1 | F11: 2 | G11: 3 | H11: Start | I11: Finish | J11: Breaks | K11: Amount Made | L11: QC Initials | M11: QC CODE
A12: ABB-01 - Making | B12: {=iferror(XLOOKUP(A12,'Product List'!A:A,'Product List'!C:C),"")} -> ABB1 | C12: 200 | D12: {=IFERROR(XLOOKUP($B12,Family,'Product Families'!D:D),"")} -> 236 | E12: {=IFERROR(XLOOKUP($B12,Family,'Product Families'!E:E),"")} -> 242 | F12: {=IFERROR(XLOOKUP($B12,Family,'Product Families'!F:F),"")} -> 260 | G12: {=IFERROR(XLOOKUP($B12,Family,'Product Families'!G:G),"")} -> 279 | H12: : | I12: : | J12: :
A13: ABB-08 - Packing | B13: {=iferror(XLOOKUP(A13,'Product List'!A:A,'Product List'!C:C),"")} -> ABBP | C13: 200 | D13: {=IFERROR(XLOOKUP($B13,Family,'Product Families'!D:D),"")} -> 43 | E13: {=IFERROR(XLOOKUP($B13,Family,'Product Families'!E:E),"")} -> 44 | F13: {=IFERROR(XLOOKUP($B13,Family,'Product Families'!F:F),"")} -> 48 | G13: {=IFERROR(XLOOKUP($B13,Family,'Product Families'!G:G),"")} -> 51 | H13: : | I13: : | J13: :
A14: ACWM-20 | B14: {=iferror(XLOOKUP(A14,'Product List'!A:A,'Product List'!C:C),"")} -> ACWM | D14: {=IFERROR(XLOOKUP($B14,Family,'Product Families'!D:D),"")} -> 28 | E14: {=IFERROR(XLOOKUP($B14,Family,'Product Families'!E:E),"")} -> 29 | F14: {=IFERROR(XLOOKUP($B14,Family,'Product Families'!F:F),"")} -> 31 | G14: {=IFERROR(XLOOKUP($B14,Family,'Product Families'!G:G),"")} -> 34 | H14: : | I14: : | J14: :
B15: {=iferror(XLOOKUP(A15,'Product List'!A:A,'Product List'!C:C),"")} | D15: {=IFERROR(XLOOKUP($B15,Family,'Product Families'!D:D),"")} | E15: {=IFERROR(XLOOKUP($B15,Family,'Product Families'!E:E),"")} | F15: {=IFERROR(XLOOKUP($B15,Family,'Product Families'!F:F),"")} | G15: {=IFERROR(XLOOKUP($B15,Family,'Product Families'!G:G),"")} | H15: : | I15: : | J15: :
B16: {=iferror(XLOOKUP(A16,'Product List'!A:A,'Product List'!C:C),"")} | D16: {=IFERROR(XLOOKUP($B16,Family,'Product Families'!D:D),"")} | E16: {=IFERROR(XLOOKUP($B16,Family,'Product Families'!E:E),"")} | F16: {=IFERROR(XLOOKUP($B16,Family,'Product Families'!F:F),"")} | G16: {=IFERROR(XLOOKUP($B16,Family,'Product Families'!G:G),"")} | H16: : | I16: : | J16: :
B17: {=iferror(XLOOKUP(A17,'Product List'!A:A,'Product List'!C:C),"")} | D17: {=IFERROR(XLOOKUP($B17,Family,'Product Families'!D:D),"")} | E17: {=IFERROR(XLOOKUP($B17,Family,'Product Families'!E:E),"")} | F17: {=IFERROR(XLOOKUP($B17,Family,'Product Families'!F:F),"")} | G17: {=IFERROR(XLOOKUP($B17,Family,'Product Families'!G:G),"")} | H17: : | I17: : | J17: :
B18: {=iferror(XLOOKUP(A18,'Product List'!A:A,'Product List'!C:C),"")} | D18: {=IFERROR(XLOOKUP($B18,Family,'Product Families'!D:D),"")} | E18: {=IFERROR(XLOOKUP($B18,Family,'Product Families'!E:E),"")} | F18: {=IFERROR(XLOOKUP($B18,Family,'Product Families'!F:F),"")} | G18: {=IFERROR(XLOOKUP($B18,Family,'Product Families'!G:G),"")} | H18: : | I18: : | J18: :
B19: {=iferror(XLOOKUP(A19,'Product List'!A:A,'Product List'!C:C),"")} | D19: {=IFERROR(XLOOKUP($B19,Family,'Product Families'!D:D),"")} | E19: {=IFERROR(XLOOKUP($B19,Family,'Product Families'!E:E),"")} | F19: {=IFERROR(XLOOKUP($B19,Family,'Product Families'!F:F),"")} | G19: {=IFERROR(XLOOKUP($B19,Family,'Product Families'!G:G),"")} | H19: : | I19: : | J19: :
B20: {=iferror(XLOOKUP(A20,'Product List'!A:A,'Product List'!C:C),"")} | D20: {=IFERROR(XLOOKUP($B20,Family,'Product Families'!D:D),"")} | E20: {=IFERROR(XLOOKUP($B20,Family,'Product Families'!E:E),"")} | F20: {=IFERROR(XLOOKUP($B20,Family,'Product Families'!F:F),"")} | G20: {=IFERROR(XLOOKUP($B20,Family,'Product Families'!G:G),"")} | H20: : | I20: : | J20: :
B21: {=iferror(XLOOKUP(A21,'Product List'!A:A,'Product List'!C:C),"")} | D21: {=IFERROR(XLOOKUP($B21,Family,'Product Families'!D:D),"")} | E21: {=IFERROR(XLOOKUP($B21,Family,'Product Families'!E:E),"")} | F21: {=IFERROR(XLOOKUP($B21,Family,'Product Families'!F:F),"")} | G21: {=IFERROR(XLOOKUP($B21,Family,'Product Families'!G:G),"")} | H21: : | I21: : | J21: :
B22: {=iferror(XLOOKUP(A22,'Product List'!A:A,'Product List'!C:C),"")} | D22: {=IFERROR(XLOOKUP($B22,Family,'Product Families'!D:D),"")} | E22: {=IFERROR(XLOOKUP($B22,Family,'Product Families'!E:E),"")} | F22: {=IFERROR(XLOOKUP($B22,Family,'Product Families'!F:F),"")} | G22: {=IFERROR(XLOOKUP($B22,Family,'Product Families'!G:G),"")} | H22: : | I22: : | J22: :
B23: {=iferror(XLOOKUP(A23,'Product List'!A:A,'Product List'!C:C),"")} | D23: {=IFERROR(XLOOKUP($B23,Family,'Product Families'!D:D),"")} | E23: {=IFERROR(XLOOKUP($B23,Family,'Product Families'!E:E),"")} | F23: {=IFERROR(XLOOKUP($B23,Family,'Product Families'!F:F),"")} | G23: {=IFERROR(XLOOKUP($B23,Family,'Product Families'!G:G),"")} | H23: : | I23: : | J23: :
B24: {=iferror(XLOOKUP(A24,'Product List'!A:A,'Product List'!C:C),"")} | D24: {=IFERROR(XLOOKUP($B24,Family,'Product Families'!D:D),"")} | E24: {=IFERROR(XLOOKUP($B24,Family,'Product Families'!E:E),"")} | F24: {=IFERROR(XLOOKUP($B24,Family,'Product Families'!F:F),"")} | G24: {=IFERROR(XLOOKUP($B24,Family,'Product Families'!G:G),"")} | H24: : | I24: : | J24: :
B25: {=iferror(XLOOKUP(A25,'Product List'!A:A,'Product List'!C:C),"")} | D25: {=IFERROR(XLOOKUP($B25,Family,'Product Families'!D:D),"")} | E25: {=IFERROR(XLOOKUP($B25,Family,'Product Families'!E:E),"")} | F25: {=IFERROR(XLOOKUP($B25,Family,'Product Families'!F:F),"")} | G25: {=IFERROR(XLOOKUP($B25,Family,'Product Families'!G:G),"")} | H25: : | I25: : | J25: :
B26: {=iferror(XLOOKUP(A26,'Product List'!A:A,'Product List'!C:C),"")} | D26: {=IFERROR(XLOOKUP($B26,Family,'Product Families'!D:D),"")} | E26: {=IFERROR(XLOOKUP($B26,Family,'Product Families'!E:E),"")} | F26: {=IFERROR(XLOOKUP($B26,Family,'Product Families'!F:F),"")} | G26: {=IFERROR(XLOOKUP($B26,Family,'Product Families'!G:G),"")} | H26: : | I26: : | J26: :
... B35: {=iferror(XLOOKUP(A35,'Product List'!A:A,'Product List'!C:C),"")} | D35: {=IFERROR(XLOOKUP($B35,Family,'Product Families'!D:D),"")} | E35: {=IFERROR(XLOOKUP($B35,Family,'Product Families'!E:E),"")} | F35: {=IFERROR(XLOOKUP($B35,Family,'Product Families'!F:F),"")} | G35: {=IFERROR(XLOOKUP($B35,Family,'Product Families'!G:G),"")} | H35: : | I35: : | J35: :
K36: Signature:
A39: `
D42: My work area is clean & tidy - Y / N | J42: Checked by : ______________________________
D45: Daily expected time for cleaning:15 mins
D46: Basic Cleaning Guideline | I46: ✔
D47: Clean your work station and surroundings
D48: Clean the machinery and surroundings | J48: Workstation, Machinery and surroundings is clean, tidy and ready to hand out for the next shift.
D49: Clean your equipment and PPE
D50: Sweep floor around your area | J50: Signature
D51: Remove all rubbish and empty your bin
D52: Put away any empty packaging and raw material

Sheet Production Sheet - Manual
E2: NAME: | K2: PACKING RATES - Pg 1 | Y2: PACKING RATES - Pg 2
D4: Piece Rate | F4: WORKED HOURS | K4: Product Family / Code | L4: Description | M4: 0 | N4: 1 | O4: 2 | P4: 3 | R4: Product Family / Code | S4: Description | T4: 0 | U4: 1 | V4: 2 | W4: 3 | Y4: Product Family / Code | Z4: Description | AA4: 0 | AB4: 1 | AC4: 2 | AD4: 3 | AF4: Product Family / Code | AG4: Description | AH4: 0 | AI4: 1 | AJ4: 2 | AK4: 3
D5: 0 | E5: =Personnel!B5 -> 12.71 | F5: Start | G5: : | K5: BATHROOM DEPARTMENT | R5: SOAPS | Y5: AROMATHERAPY DEPARTMENT | AF5: HOME FRAGRANCE DEPARTMENT
D6: 1 | E6: =Personnel!C5 -> 13 | F6: Finish | G6: : | K6: ABB1 | L6: {=IF(K6="","",IFERROR(XLOOKUP(K6,'Product Families'!$A:$A,'Product Families'!$B:$B),""))} -> Bath Potion Bath Bombs - Single Mix - Making | M6: {=IF(K6="","",(IFERROR(XLOOKUP($K6,Family,'Product Families'!D:D),"")))} -> 236 | N6: {=IF(L6="","",(IFERROR(XLOOKUP($K6,Family,'Product Families'!E:E),"")))} -> 242 | O6: {=IF(M6="","",(IFERROR(XLOOKUP($K6,Family,'Product Families'!F:F),"")))} -> 260 | P6: {=IF(N6="","",(IFERROR(XLOOKUP($K6,Family,'Product Families'!G:G),"")))} -> 279 | R6: AVENA | S6: {=IF(R6="","",IFERROR(XLOOKUP(R6,'Product Families'!$A:$A,'Product Families'!$B:$B),""))} -> Avena Herbal Products Soap - Making | T6: {=IF(R6="","",(IFERROR(XLOOKUP($R6,Family,'Product Families'!D:D),"")))} -> 72 | U6: {=IF(S6="","",(IFERROR(XLOOKUP($R6,Family,'Product Families'!E:E),"")))} -> 74 | V6: {=IF(T6="","",(IFERROR(XLOOKUP($R6,Family,'Product Families'!F:F),"")))} -> 80 | W6: {=IF(U6="","",(IFERROR(XLOOKUP($R6,Family,'Product Families'!G:G),"")))} -> 85 | Y6: ABP | Z6: {=IF(Y6="","",IFERROR(XLOOKUP(Y6,'Product Families'!$A:$A,'Product Families'!$B:$B),""))} -> 7kg Bath Potions | AA6: {=IF(Y6="","",(IFERROR(XLOOKUP($Y6,Family,'Product Families'!D:D),"")))} -> 65 | AB6: {=IF(Z6="","",(IFERROR(XLOOKUP($Y6,Family,'Product Families'!E:E),"")))} -> 67 | AC6: {=IF(AA6="","",(IFERROR(XLOOKUP($Y6,Family,'Product Families'!F:F),"")))} -> 72 | AD6: {=IF(AB6="","",(IFERROR(XLOOKUP($Y6,Family,'Product Families'!G:G),"")))} -> 77 | AF6: AWFO | AG6: {=IF(AF6="","",IFERROR(XLOOKUP(AF6,'Product Families'!$A:$A,'Product Families'!$B:$B),""))} -> Fragrance Oils 10ml | AH6: {=IF(AF6="","",(IFERROR(XLOOKUP($AF6,Family,'Product Families'!D:D),"")))} -> 17 | AI6: {=IF(AG6="","",(IFERROR(XLOOKUP($AF6,Family,'Product Families'!E:E),"")))} -> 18 | AJ6: {=IF(AH6="","",(IFERROR(XLOOKUP($AF6,Family,'Product Families'!F:F),"")))} -> 19 | AK6: {=IF(AI6="","",(IFERROR(XLOOKUP($AF6,Family,'Product Families'!G:G),"")))} -> 21
A7: Date: | D7: 2 | E7: =Personnel!D5 -> 14 | F7: Breaks | G7: : | K7: ABBP | L7: {=IF(K7="","",IFERROR(XLOOKUP(K7,'Product Families'!$A:$A,'Product Families'!$B:$B),""))} -> Bath Potion Bath Bombs - Packing | M7: {=IF(K7="","",(IFERROR(XLOOKUP($K7,Family,'Product Families'!D:D),"")))} -> 43 | N7: {=IF(L7="","",(IFERROR(XLOOKUP($K7,Family,'Product Families'!E:E),"")))} -> 44 | O7: {=IF(M7="","",(IFERROR(XLOOKUP($K7,Family,'Product Families'!F:F),"")))} -> 48 | P7: {=IF(N7="","",(IFERROR(XLOOKUP($K7,Family,'Product Families'!G:G),"")))} -> 51 | R7: AVENAP | S7: {=IF(R7="","",IFERROR(XLOOKUP(R7,'Product Families'!$A:$A,'Product Families'!$B:$B),""))} -> Avena Herbal Products Soap - Packing | T7: {=IF(R7="","",(IFERROR(XLOOKUP($R7,Family,'Product Families'!D:D),"")))} -> 41 | U7: {=IF(S7="","",(IFERROR(XLOOKUP($R7,Family,'Product Families'!E:E),"")))} -> 42 | V7: {=IF(T7="","",(IFERROR(XLOOKUP($R7,Family,'Product Families'!F:F),"")))} -> 46 | W7: {=IF(U7="","",(IFERROR(XLOOKUP($R7,Family,'Product Families'!G:G),"")))} -> 49 | Y7: ABPCB | Z7: {=IF(Y7="","",IFERROR(XLOOKUP(Y7,'Product Families'!$A:$A,'Product Families'!$B:$B),""))} -> 350g Bagged Bath Potions - Box of 5 | AA7: {=IF(Y7="","",(IFERROR(XLOOKUP($Y7,Family,'Product Families'!D:D),"")))} -> 9 | AB7: {=IF(Z7="","",(IFERROR(XLOOKUP($Y7,Family,'Product Families'!E:E),"")))} -> 10 | AC7: {=IF(AA7="","",(IFERROR(XLOOKUP($Y7,Family,'Product Families'!F:F),"")))} -> 11 | AD7: {=IF(AB7="","",(IFERROR(XLOOKUP($Y7,Family,'Product Families'!G:G),"")))} -> 12 | AF7: AWFOT | AG7: {=IF(AF7="","",IFERROR(XLOOKUP(AF7,'Product Families'!$A:$A,'Product Families'!$B:$B),""))} -> Fragrance Oils 10ml - Tactile Label | AH7: {=IF(AF7="","",(IFERROR(XLOOKUP($AF7,Family,'Product Families'!D:D),"")))} -> 14 | AI7: {=IF(AG7="","",(IFERROR(XLOOKUP($AF7,Family,'Product Families'!E:E),"")))} -> 15 | AJ7: {=IF(AH7="","",(IFERROR(XLOOKUP($AF7,Family,'Product Families'!F:F),"")))} -> 16 | AK7: {=IF(AI7="","",(IFERROR(XLOOKUP($AF7,Family,'Product Families'!G:G),"")))} -> 17
D8: 3 | E8: =Personnel!E5 -> 15 | F8: Total Worked : | G8: : | K8: AROSS | L8: {=IF(K8="","",IFERROR(XLOOKUP(K8,'Product Families'!$A:$A,'Product Families'!$B:$B),""))} -> Aromatherapy Shower Steamers - Making | M8: {=IF(K8="","",(IFERROR(XLOOKUP($K8,Family,'Product Families'!D:D),"")))} -> 260 | N8: {=IF(L8="","",(IFERROR(XLOOKUP($K8,Family,'Product Families'!E:E),"")))} -> 266 | O8: {=IF(M8="","",(IFERROR(XLOOKUP($K8,Family,'Product Families'!F:F),"")))} -> 287 | P8: {=IF(N8="","",(IFERROR(XLOOKUP($K8,Family,'Product Families'!G:G),"")))} -> 307 | R8: AWGSoap | S8: {=IF(R8="","",IFERROR(XLOOKUP(R8,'Product Families'!$A:$A,'Product Families'!$B:$B),""))} -> Guest Soaps | T8: {=IF(R8="","",(IFERROR(XLOOKUP($R8,Family,'Product Families'!D:D),"")))} -> 3 | U8: {=IF(S8="","",(IFERROR(XLOOKUP($R8,Family,'Product Families'!E:E),"")))} -> 4 | V8: {=IF(T8="","",(IFERROR(XLOOKUP($R8,Family,'Product Families'!F:F),"")))} -> 5 | W8: {=IF(U8="","",(IFERROR(XLOOKUP($R8,Family,'Product Families'!G:G),"")))} -> 6 | Y8: ABPCULB | Z8: {=IF(Y8="","",IFERROR(XLOOKUP(Y8,'Product Families'!$A:$A,'Product Families'!$B:$B),""))} -> Aromatherapy Bath Potion in Kraft Bags - White Label - Box of 5 | AA8: {=IF(Y8="","",(IFERROR(XLOOKUP($Y8,Family,'Product Families'!D:D),"")))} -> 13 | AB8: {=IF(Z8="","",(IFERROR(XLOOKUP($Y8,Family,'Product Families'!E:E),"")))} -> 14 | AC8: {=IF(AA8="","",(IFERROR(XLOOKUP($Y8,Family,'Product Families'!F:F),"")))} -> 15 | AD8: {=IF(AB8="","",(IFERROR(XLOOKUP($Y8,Family,'Product Families'!G:G),"")))} -> 16 | AF8: AWPFO | AG8: {=IF(AF8="","",IFERROR(XLOOKUP(AF8,'Product Families'!$A:$A,'Product Families'!$B:$B),""))} -> 250ml Pure Fragrance Oils | AH8: {=IF(AF8="","",(IFERROR(XLOOKUP($AF8,Family,'Product Families'!D:D),"")))} -> 108 | AI8: {=IF(AG8="","",(IFERROR(XLOOKUP($AF8,Family,'Product Families'!E:E),"")))} -> 111 | AJ8: {=IF(AH8="","",(IFERROR(XLOOKUP($AF8,Family,'Product Families'!F:F),"")))} -> 119 | AK8: {=IF(AI8="","",(IFERROR(XLOOKUP($AF8,Family,'Product Families'!G:G),"")))} -> 128
D9: Development Rate | E9: =Personnel!F5 -> 13.3 | K9: AROSSP | L9: {=IF(K9="","",IFERROR(XLOOKUP(K9,'Product Families'!$A:$A,'Product Families'!$B:$B),""))} -> Aromatherapy Shower Steamers - Packing | M9: {=IF(K9="","",(IFERROR(XLOOKUP($K9,Family,'Product Families'!D:D),"")))} -> 34 | N9: {=IF(L9="","",(IFERROR(XLOOKUP($K9,Family,'Product Families'!E:E),"")))} -> 35 | O9: {=IF(M9="","",(IFERROR(XLOOKUP($K9,Family,'Product Families'!F:F),"")))} -> 38 | P9: {=IF(N9="","",(IFERROR(XLOOKUP($K9,Family,'Product Families'!G:G),"")))} -> 41 | R9: BSS | S9: {=IF(R9="","",IFERROR(XLOOKUP(R9,'Product Families'!$A:$A,'Product Families'!$B:$B),""))} -> Soap Sponge - Making | T9: {=IF(R9="","",(IFERROR(XLOOKUP($R9,Family,'Product Families'!D:D),"")))} -> 101 | U9: {=IF(S9="","",(IFERROR(XLOOKUP($R9,Family,'Product Families'!E:E),"")))} -> 104 | V9: {=IF(T9="","",(IFERROR(XLOOKUP($R9,Family,'Product Families'!F:F),"")))} -> 112 | W9: {=IF(U9="","",(IFERROR(XLOOKUP($R9,Family,'Product Families'!G:G),"")))} -> 120 | Y9: AHBL | Z9: {=IF(Y9="","",IFERROR(XLOOKUP(Y9,'Product Families'!$A:$A,'Product Families'!$B:$B),""))} -> Aromatherapy Hand and Body Lotions - 250 ml - Making | AA9: {=IF(Y9="","",(IFERROR(XLOOKUP($Y9,Family,'Product Families'!D:D),"")))} -> 86 | AB9: {=IF(Z9="","",(IFERROR(XLOOKUP($Y9,Family,'Product Families'!E:E),"")))} -> 88 | AC9: {=IF(AA9="","",(IFERROR(XLOOKUP($Y9,Family,'Product Families'!F:F),"")))} -> 95 | AD9: {=IF(AB9="","",(IFERROR(XLOOKUP($Y9,Family,'Product Families'!G:G),"")))} -> 102 | AF9: AWRS | AG9: {=IF(AF9="","",IFERROR(XLOOKUP(AF9,'Product Families'!$A:$A,'Product Families'!$B:$B),""))} -> Room Sprays - Making + Packing in 6s | AH9: {=IF(AF9="","",(IFERROR(XLOOKUP($AF9,Family,'Product Families'!D:D),"")))} -> 15 | AI9: {=IF(AG9="","",(IFERROR(XLOOKUP($AF9,Family,'Product Families'!E:E),"")))} -> 16 | AJ9: {=IF(AH9="","",(IFERROR(XLOOKUP($AF9,Family,'Product Families'!F:F),"")))} -> 17 | AK9: {=IF(AI9="","",(IFERROR(XLOOKUP($AF9,Family,'Product Families'!G:G),"")))} -> 18
G10: QC Check | K10: AWCHILL | L10: {=IF(K10="","",IFERROR(XLOOKUP(K10,'Product Families'!$A:$A,'Product Families'!$B:$B),""))} -> Chill Pills - Making | M10: {=IF(K10="","",(IFERROR(XLOOKUP($K10,Family,'Product Families'!D:D),"")))} -> 10 | N10: {=IF(L10="","",(IFERROR(XLOOKUP($K10,Family,'Product Families'!E:E),"")))} -> 11 | O10: {=IF(M10="","",(IFERROR(XLOOKUP($K10,Family,'Product Families'!F:F),"")))} -> 12 | P10: {=IF(N10="","",(IFERROR(XLOOKUP($K10,Family,'Product Families'!G:G),"")))} -> 13 | R10: BSSD | S10: {=IF(R10="","",IFERROR(XLOOKUP(R10,'Product Families'!$A:$A,'Product Families'!$B:$B),""))} -> Soap Sponge - Drizzle | T10: {=IF(R10="","",(IFERROR(XLOOKUP($R10,Family,'Product Families'!D:D),"")))} -> 187 | U10: {=IF(S10="","",(IFERROR(XLOOKUP($R10,Family,'Product Families'!E:E),"")))} -> 192 | V10: {=IF(T10="","",(IFERROR(XLOOKUP($R10,Family,'Product Families'!F:F),"")))} -> 206 | W10: {=IF(U10="","",(IFERROR(XLOOKUP($R10,Family,'Product Families'!G:G),"")))} -> 221 | Y10: AHBLC | Z10: {=IF(Y10="","",IFERROR(XLOOKUP(Y10,'Product Families'!$A:$A,'Product Families'!$B:$B),""))} -> Aromatherapy Hand and Body Lotions - 250 ml - Making + Packing (Pack of 4) | AA10: {=IF(Y10="","",(IFERROR(XLOOKUP($Y10,Family,'Product Families'!D:D),"")))} -> 9 | AB10: {=IF(Z10="","",(IFERROR(XLOOKUP($Y10,Family,'Product Families'!E:E),"")))} -> 10 | AC10: {=IF(AA10="","",(IFERROR(XLOOKUP($Y10,Family,'Product Families'!F:F),"")))} -> 11 | AD10: {=IF(AB10="","",(IFERROR(XLOOKUP($Y10,Family,'Product Families'!G:G),"")))} -> 12 | AF10: AWRSUL | AG10: {=IF(AF10="","",IFERROR(XLOOKUP(AF10,'Product Families'!$A:$A,'Product Families'!$B:$B),""))} -> 100ml Room Sprays - White Label - Making + Packing in 6s | AH10: {=IF(AF10="","",(IFERROR(XLOOKUP($AF10,Family,'Product Families'!D:D),"")))} -> 16 | AI10: {=IF(AG10="","",(IFERROR(XLOOKUP($AF10,Family,'Product Families'!E:E),"")))} -> 17 | AJ10: {=IF(AH10="","",(IFERROR(XLOOKUP($AF10,Family,'Product Families'!F:F),"")))} -> 18 | AK10: {=IF(AI10="","",(IFERROR(XLOOKUP($AF10,Family,'Product Families'!G:G),"")))} -> 19
A11: Item Code | C11: Start | D11: Finish | E11: Breaks | F11: Amount Made | G11: QC Initials | H11: QC CODE | K11: AWCHILLP | L11: {=IF(K11="","",IFERROR(XLOOKUP(K11,'Product Families'!$A:$A,'Product Families'!$B:$B),""))} -> Chill Pills - Packing | M11: {=IF(K11="","",(IFERROR(XLOOKUP($K11,Family,'Product Families'!D:D),"")))} -> 32 | N11: {=IF(L11="","",(IFERROR(XLOOKUP($K11,Family,'Product Families'!E:E),"")))} -> 33 | O11: {=IF(M11="","",(IFERROR(XLOOKUP($K11,Family,'Product Families'!F:F),"")))} -> 36 | P11: {=IF(N11="","",(IFERROR(XLOOKUP($K11,Family,'Product Families'!G:G),"")))} -> 38 | R11: CHSB | S11: {=IF(R11="","",IFERROR(XLOOKUP(R11,'Product Families'!$A:$A,'Product Families'!$B:$B),""))} -> Charcoal Soap 85g | T11: {=IF(R11="","",(IFERROR(XLOOKUP($R11,Family,'Product Families'!D:D),"")))} -> 162 | U11: {=IF(S11="","",(IFERROR(XLOOKUP($R11,Family,'Product Families'!E:E),"")))} -> 166 | V11: {=IF(T11="","",(IFERROR(XLOOKUP($R11,Family,'Product Families'!F:F),"")))} -> 179 | W11: {=IF(U11="","",(IFERROR(XLOOKUP($R11,Family,'Product Families'!G:G),"")))} -> 192 | Y11: AHBLP | Z11: {=IF(Y11="","",IFERROR(XLOOKUP(Y11,'Product Families'!$A:$A,'Product Families'!$B:$B),""))} -> Aromatherapy Hand and Body Lotions - 250 ml - Packing in 4 | AA11: {=IF(Y11="","",(IFERROR(XLOOKUP($Y11,Family,'Product Families'!D:D),"")))} -> 21 | AB11: {=IF(Z11="","",(IFERROR(XLOOKUP($Y11,Family,'Product Families'!E:E),"")))} -> 22 | AC11: {=IF(AA11="","",(IFERROR(XLOOKUP($Y11,Family,'Product Families'!F:F),"")))} -> 23 | AD11: {=IF(AB11="","",(IFERROR(XLOOKUP($Y11,Family,'Product Families'!G:G),"")))} -> 24 | AF11: EBLUL | AG11: {=IF(AF11="","",IFERROR(XLOOKUP(AF11,'Product Families'!$A:$A,'Product Families'!$B:$B),""))} -> Bottle & Label Essential Oils Blend 10ml - Unlabelled - Pack of 10 | AH11: {=IF(AF11="","",(IFERROR(XLOOKUP($AF11,Family,'Product Families'!D:D),"")))} -> 20 | AI11: {=IF(AG11="","",(IFERROR(XLOOKUP($AF11,Family,'Product Families'!E:E),"")))} -> 21 | AJ11: {=IF(AH11="","",(IFERROR(XLOOKUP($AF11,Family,'Product Families'!F:F),"")))} -> 23 | AK11: {=IF(AI11="","",(IFERROR(XLOOKUP($AF11,Family,'Product Families'!G:G),"")))} -> 24
C12: : | D12: : | E12: : | K12: BAS | L12: {=IF(K12="","",IFERROR(XLOOKUP(K12,'Product Families'!$A:$A,'Product Families'!$B:$B),""))} -> Bubble & Splash Bath Dust 200g | M12: {=IF(K12="","",(IFERROR(XLOOKUP($K12,Family,'Product Families'!D:D),"")))} -> 52 | N12: {=IF(L12="","",(IFERROR(XLOOKUP($K12,Family,'Product Families'!E:E),"")))} -> 54 | O12: {=IF(M12="","",(IFERROR(XLOOKUP($K12,Family,'Product Families'!F:F),"")))} -> 58 | P12: {=IF(N12="","",(IFERROR(XLOOKUP($K12,Family,'Product Families'!G:G),"")))} -> 62 | R12: CHSBP | S12: {=IF(R12="","",IFERROR(XLOOKUP(R12,'Product Families'!$A:$A,'Product Families'!$B:$B),""))} -> Charcoal Soap 85g - Packing | T12: {=IF(R12="","",(IFERROR(XLOOKUP($R12,Family,'Product Families'!D:D),"")))} -> 108 | U12: {=IF(S12="","",(IFERROR(XLOOKUP($R12,Family,'Product Families'!E:E),"")))} -> 111 | V12: {=IF(T12="","",(IFERROR(XLOOKUP($R12,Family,'Product Families'!F:F),"")))} -> 119 | W12: {=IF(U12="","",(IFERROR(XLOOKUP($R12,Family,'Product Families'!G:G),"")))} -> 128 | Y12: AHBLUL | Z12: {=IF(Y12="","",IFERROR(XLOOKUP(Y12,'Product Families'!$A:$A,'Product Families'!$B:$B),""))} -> Aromatherapy Hand & Body Lotions - Unlabelled (Pack 4) | AA12: {=IF(Y12="","",(IFERROR(XLOOKUP($Y12,Family,'Product Families'!D:D),"")))} -> 9 | AB12: {=IF(Z12="","",(IFERROR(XLOOKUP($Y12,Family,'Product Families'!E:E),"")))} -> 10 | AC12: {=IF(AA12="","",(IFERROR(XLOOKUP($Y12,Family,'Product Families'!F:F),"")))} -> 11 | AD12: {=IF(AB12="","",(IFERROR(XLOOKUP($Y12,Family,'Product Families'!G:G),"")))} -> 12 | AF12: EOMUL | AG12: {=IF(AF12="","",IFERROR(XLOOKUP(AF12,'Product Families'!$A:$A,'Product Families'!$B:$B),""))} -> Room Sprays - Making + Packing - Pack Of 6 | AH12: {=IF(AF12="","",(IFERROR(XLOOKUP($AF12,Family,'Product Families'!D:D),"")))} -> 12 | AI12: {=IF(AG12="","",(IFERROR(XLOOKUP($AF12,Family,'Product Families'!E:E),"")))} -> 13 | AJ12: {=IF(AH12="","",(IFERROR(XLOOKUP($AF12,Family,'Product Families'!F:F),"")))} -> 14 | AK12: {=IF(AI12="","",(IFERROR(XLOOKUP($AF12,Family,'Product Families'!G:G),"")))} -> 15
K13: BEGG | L13: {=IF(K13="","",IFERROR(XLOOKUP(K13,'Product Families'!$A:$A,'Product Families'!$B:$B),""))} -> Bath Eggs - Making | M13: {=IF(K13="","",(IFERROR(XLOOKUP($K13,Family,'Product Families'!D:D),"")))} -> 236 | N13: {=IF(L13="","",(IFERROR(XLOOKUP($K13,Family,'Product Families'!E:E),"")))} -> 242 | O13: {=IF(M13="","",(IFERROR(XLOOKUP($K13,Family,'Product Families'!F:F),"")))} -> 260 | P13: {=IF(N13="","",(IFERROR(XLOOKUP($K13,Family,'Product Families'!G:G),"")))} -> 279 | R13: CHSBUL | S13: {=IF(R13="","",IFERROR(XLOOKUP(R13,'Product Families'!$A:$A,'Product Families'!$B:$B),""))} -> Charcoal Soaps 85g - White Label - Making | T13: {=IF(R13="","",(IFERROR(XLOOKUP($R13,Family,'Product Families'!D:D),"")))} -> 162 | U13: {=IF(S13="","",(IFERROR(XLOOKUP($R13,Family,'Product Families'!E:E),"")))} -> 166 | V13: {=IF(T13="","",(IFERROR(XLOOKUP($R13,Family,'Product Families'!F:F),"")))} -> 179 | W13: {=IF(U13="","",(IFERROR(XLOOKUP($R13,Family,'Product Families'!G:G),"")))} -> 192 | Y13: AHBW | Z13: {=IF(Y13="","",IFERROR(XLOOKUP(Y13,'Product Families'!$A:$A,'Product Families'!$B:$B),""))} -> Aromatherapy Hand & Body Wash - Making | AA13: {=IF(Y13="","",(IFERROR(XLOOKUP($Y13,Family,'Product Families'!D:D),"")))} -> 86 | AB13: {=IF(Z13="","",(IFERROR(XLOOKUP($Y13,Family,'Product Families'!E:E),"")))} -> 88 | AC13: {=IF(AA13="","",(IFERROR(XLOOKUP($Y13,Family,'Product Families'!F:F),"")))} -> 95 | AD13: {=IF(AB13="","",(IFERROR(XLOOKUP($Y13,Family,'Product Families'!G:G),"")))} -> 102 | AF13: EOUL | AG13: {=IF(AF13="","",IFERROR(XLOOKUP(AF13,'Product Families'!$A:$A,'Product Families'!$B:$B),""))} -> Essential Oils Unbranded - Pack of 10 | AH13: {=IF(AF13="","",(IFERROR(XLOOKUP($AF13,Family,'Product Families'!D:D),"")))} -> 20 | AI13: {=IF(AG13="","",(IFERROR(XLOOKUP($AF13,Family,'Product Families'!E:E),"")))} -> 21 | AJ13: {=IF(AH13="","",(IFERROR(XLOOKUP($AF13,Family,'Product Families'!F:F),"")))} -> 23 | AK13: {=IF(AI13="","",(IFERROR(XLOOKUP($AF13,Family,'Product Families'!G:G),"")))} -> 24
A14: {=IF(A15="","",(XLOOKUP(A15,Product,'Product List'!C:C)))} | C14: : | D14: : | E14: : | K14: BEGGP | L14: {=IF(K14="","",IFERROR(XLOOKUP(K14,'Product Families'!$A:$A,'Product Families'!$B:$B),""))} -> Bath Eggs - Packing | M14: {=IF(K14="","",(IFERROR(XLOOKUP($K14,Family,'Product Families'!D:D),"")))} -> 34 | N14: {=IF(L14="","",(IFERROR(XLOOKUP($K14,Family,'Product Families'!E:E),"")))} -> 35 | O14: {=IF(M14="","",(IFERROR(XLOOKUP($K14,Family,'Product Families'!F:F),"")))} -> 38 | P14: {=IF(N14="","",(IFERROR(XLOOKUP($K14,Family,'Product Families'!G:G),"")))} -> 41 | R14: CHSBULP | S14: {=IF(R14="","",IFERROR(XLOOKUP(R14,'Product Families'!$A:$A,'Product Families'!$B:$B),""))} -> Charcoal Soaps 85g - White Label + Packing | T14: {=IF(R14="","",(IFERROR(XLOOKUP($R14,Family,'Product Families'!D:D),"")))} -> 108 | U14: {=IF(S14="","",(IFERROR(XLOOKUP($R14,Family,'Product Families'!E:E),"")))} -> 111 | V14: {=IF(T14="","",(IFERROR(XLOOKUP($R14,Family,'Product Families'!F:F),"")))} -> 119 | W14: {=IF(U14="","",(IFERROR(XLOOKUP($R14,Family,'Product Families'!G:G),"")))} -> 128 | Y14: AHBWB | Z14: {=IF(Y14="","",IFERROR(XLOOKUP(Y14,'Product Families'!$A:$A,'Product Families'!$B:$B),""))} -> Aromatherapy Hand & Body Wash - Pack of 4 | AA14: {=IF(Y14="","",(IFERROR(XLOOKUP($Y14,Family,'Product Families'!D:D),"")))} -> 9 | AB14: {=IF(Z14="","",(IFERROR(XLOOKUP($Y14,Family,'Product Families'!E:E),"")))} -> 10 | AC14: {=IF(AA14="","",(IFERROR(XLOOKUP($Y14,Family,'Product Families'!F:F),"")))} -> 11 | AD14: {=IF(AB14="","",(IFERROR(XLOOKUP($Y14,Family,'Product Families'!G:G),"")))} -> 12 | AF14: FOBP | AG14: {=IF(AF14="","",IFERROR(XLOOKUP(AF14,'Product Families'!$A:$A,'Product Families'!$B:$B),""))} -> FOBp | AH14: {=IF(AF14="","",(IFERROR(XLOOKUP($AF14,Family,'Product Families'!D:D),"")))} -> 26 | AI14: {=IF(AG14="","",(IFERROR(XLOOKUP($AF14,Family,'Product Families'!E:E),"")))} -> 27 | AJ14: {=IF(AH14="","",(IFERROR(XLOOKUP($AF14,Family,'Product Families'!F:F),"")))} -> 29 | AK14: {=IF(AI14="","",(IFERROR(XLOOKUP($AF14,Family,'Product Families'!G:G),"")))} -> 31
K15: CBB1 | L15: {=IF(K15="","",IFERROR(XLOOKUP(K15,'Product Families'!$A:$A,'Product Families'!$B:$B),""))} -> Cocktail Bath Bombs Single Mix 120g | M15: {=IF(K15="","",(IFERROR(XLOOKUP($K15,Family,'Product Families'!D:D),"")))} -> 216 | N15: {=IF(L15="","",(IFERROR(XLOOKUP($K15,Family,'Product Families'!E:E),"")))} -> 221 | O15: {=IF(M15="","",(IFERROR(XLOOKUP($K15,Family,'Product Families'!F:F),"")))} -> 238 | P15: {=IF(N15="","",(IFERROR(XLOOKUP($K15,Family,'Product Families'!G:G),"")))} -> 255 | R15: CSOAP | S15: {=IF(R15="","",IFERROR(XLOOKUP(R15,'Product Families'!$A:$A,'Product Families'!$B:$B),""))} -> Crystal Elemental Soaps - Making | T15: {=IF(R15="","",(IFERROR(XLOOKUP($R15,Family,'Product Families'!D:D),"")))} -> 130 | U15: {=IF(S15="","",(IFERROR(XLOOKUP($R15,Family,'Product Families'!E:E),"")))} -> 133 | V15: {=IF(T15="","",(IFERROR(XLOOKUP($R15,Family,'Product Families'!F:F),"")))} -> 144 | W15: {=IF(U15="","",(IFERROR(XLOOKUP($R15,Family,'Product Families'!G:G),"")))} -> 154 | Y15: AHBWP | Z15: {=IF(Y15="","",IFERROR(XLOOKUP(Y15,'Product Families'!$A:$A,'Product Families'!$B:$B),""))} -> Aromatherapy Hand & Body Wash - Packing in 4 | AA15: {=IF(Y15="","",(IFERROR(XLOOKUP($Y15,Family,'Product Families'!D:D),"")))} -> 21 | AB15: {=IF(Z15="","",(IFERROR(XLOOKUP($Y15,Family,'Product Families'!E:E),"")))} -> 22 | AC15: {=IF(AA15="","",(IFERROR(XLOOKUP($Y15,Family,'Product Families'!F:F),"")))} -> 23 | AD15: {=IF(AB15="","",(IFERROR(XLOOKUP($Y15,Family,'Product Families'!G:G),"")))} -> 24 | AF15: FOT | AG15: {=IF(AF15="","",IFERROR(XLOOKUP(AF15,'Product Families'!$A:$A,'Product Families'!$B:$B),""))} -> Fragrance Oil Testers 10ml (AW Family) - Tactile Label | AH15: {=IF(AF15="","",(IFERROR(XLOOKUP($AF15,Family,'Product Families'!D:D),"")))} -> 144 | AI15: {=IF(AG15="","",(IFERROR(XLOOKUP($AF15,Family,'Product Families'!E:E),"")))} -> 148 | AJ15: {=IF(AH15="","",(IFERROR(XLOOKUP($AF15,Family,'Product Families'!F:F),"")))} -> 159 | AK15: {=IF(AI15="","",(IFERROR(XLOOKUP($AF15,Family,'Product Families'!G:G),"")))} -> 170
C16: : | D16: : | E16: : | K16: CBB2 | L16: {=IF(K16="","",IFERROR(XLOOKUP(K16,'Product Families'!$A:$A,'Product Families'!$B:$B),""))} -> Cocktail Bath Bombs Double Mix 120g | M16: {=IF(K16="","",(IFERROR(XLOOKUP($K16,Family,'Product Families'!D:D),"")))} -> 185 | N16: {=IF(L16="","",(IFERROR(XLOOKUP($K16,Family,'Product Families'!E:E),"")))} -> 190 | O16: {=IF(M16="","",(IFERROR(XLOOKUP($K16,Family,'Product Families'!F:F),"")))} -> 204 | P16: {=IF(N16="","",(IFERROR(XLOOKUP($K16,Family,'Product Families'!G:G),"")))} -> 219 | R16: CSOAPP | S16: {=IF(R16="","",IFERROR(XLOOKUP(R16,'Product Families'!$A:$A,'Product Families'!$B:$B),""))} -> Crystal Elemental Soaps - Packing | T16: {=IF(R16="","",(IFERROR(XLOOKUP($R16,Family,'Product Families'!D:D),"")))} -> 86 | U16: {=IF(S16="","",(IFERROR(XLOOKUP($R16,Family,'Product Families'!E:E),"")))} -> 88 | V16: {=IF(T16="","",(IFERROR(XLOOKUP($R16,Family,'Product Families'!F:F),"")))} -> 95 | W16: {=IF(U16="","",(IFERROR(XLOOKUP($R16,Family,'Product Families'!G:G),"")))} -> 102 | Y16: AWBP | Z16: {=IF(Y16="","",IFERROR(XLOOKUP(Y16,'Product Families'!$A:$A,'Product Families'!$B:$B),""))} -> Ancient Witch Bath Potions - Making - Pack of 4 | AA16: {=IF(Y16="","",(IFERROR(XLOOKUP($Y16,Family,'Product Families'!D:D),"")))} -> 5 | AB16: {=IF(Z16="","",(IFERROR(XLOOKUP($Y16,Family,'Product Families'!E:E),"")))} -> 6 | AC16: {=IF(AA16="","",(IFERROR(XLOOKUP($Y16,Family,'Product Families'!F:F),"")))} -> 7 | AD16: {=IF(AB16="","",(IFERROR(XLOOKUP($Y16,Family,'Product Families'!G:G),"")))} -> 8 | AF16: ORGEOUL | AG16: {=IF(AF16="","",IFERROR(XLOOKUP(AF16,'Product Families'!$A:$A,'Product Families'!$B:$B),""))} -> Orgeo - Unlabelled - Pack of 10 | AH16: {=IF(AF16="","",(IFERROR(XLOOKUP($AF16,Family,'Product Families'!D:D),"")))} -> 20 | AI16: {=IF(AG16="","",(IFERROR(XLOOKUP($AF16,Family,'Product Families'!E:E),"")))} -> 21 | AJ16: {=IF(AH16="","",(IFERROR(XLOOKUP($AF16,Family,'Product Families'!F:F),"")))} -> 23 | AK16: {=IF(AI16="","",(IFERROR(XLOOKUP($AF16,Family,'Product Families'!G:G),"")))} -> 24
K17: CBBP | L17: {=IF(K17="","",IFERROR(XLOOKUP(K17,'Product Families'!$A:$A,'Product Families'!$B:$B),""))} -> Cocktail Bath Bombs 120g Packing in Three | M17: {=IF(K17="","",(IFERROR(XLOOKUP($K17,Family,'Product Families'!D:D),"")))} -> 108 | N17: {=IF(L17="","",(IFERROR(XLOOKUP($K17,Family,'Product Families'!E:E),"")))} -> 111 | O17: {=IF(M17="","",(IFERROR(XLOOKUP($K17,Family,'Product Families'!F:F),"")))} -> 119 | P17: {=IF(N17="","",(IFERROR(XLOOKUP($K17,Family,'Product Families'!G:G),"")))} -> 128 | R17: GMSOAP | S17: {=IF(R17="","",IFERROR(XLOOKUP(R17,'Product Families'!$A:$A,'Product Families'!$B:$B),""))} -> GMSoap | T17: {=IF(R17="","",(IFERROR(XLOOKUP($R17,Family,'Product Families'!D:D),"")))} -> 6 | U17: {=IF(S17="","",(IFERROR(XLOOKUP($R17,Family,'Product Families'!E:E),"")))} -> 7 | V17: {=IF(T17="","",(IFERROR(XLOOKUP($R17,Family,'Product Families'!F:F),"")))} -> 8 | W17: {=IF(U17="","",(IFERROR(XLOOKUP($R17,Family,'Product Families'!G:G),"")))} -> 9 | Y17: AWBPP | Z17: {=IF(Y17="","",IFERROR(XLOOKUP(Y17,'Product Families'!$A:$A,'Product Families'!$B:$B),""))} -> Ancient Witch Bath Potions - Packing - Pack of 4 | AA17: {=IF(Y17="","",(IFERROR(XLOOKUP($Y17,Family,'Product Families'!D:D),"")))} -> 5 | AB17: {=IF(Z17="","",(IFERROR(XLOOKUP($Y17,Family,'Product Families'!E:E),"")))} -> 6 | AC17: {=IF(AA17="","",(IFERROR(XLOOKUP($Y17,Family,'Product Families'!F:F),"")))} -> 7 | AD17: {=IF(AB17="","",(IFERROR(XLOOKUP($Y17,Family,'Product Families'!G:G),"")))} -> 8 | AF17: OUDHRSUL | AG17: {=IF(AF17="","",IFERROR(XLOOKUP(AF17,'Product Families'!$A:$A,'Product Families'!$B:$B),""))} -> Oudh Room Sprays 100ml - Unlabelled - Pack of 6 | AH17: {=IF(AF17="","",(IFERROR(XLOOKUP($AF17,Family,'Product Families'!D:D),"")))} -> 12 | AI17: {=IF(AG17="","",(IFERROR(XLOOKUP($AF17,Family,'Product Families'!E:E),"")))} -> 13 | AJ17: {=IF(AH17="","",(IFERROR(XLOOKUP($AF17,Family,'Product Families'!F:F),"")))} -> 14 | AK17: {=IF(AI17="","",(IFERROR(XLOOKUP($AF17,Family,'Product Families'!G:G),"")))} -> 15
C18: : | D18: : | E18: : | K18: CBF | L18: {=IF(K18="","",IFERROR(XLOOKUP(K18,'Product Families'!$A:$A,'Product Families'!$B:$B),""))} -> Chakra Bath Fizz - Making | M18: {=IF(K18="","",(IFERROR(XLOOKUP($K18,Family,'Product Families'!D:D),"")))} -> 130 | N18: {=IF(L18="","",(IFERROR(XLOOKUP($K18,Family,'Product Families'!E:E),"")))} -> 133 | O18: {=IF(M18="","",(IFERROR(XLOOKUP($K18,Family,'Product Families'!F:F),"")))} -> 144 | P18: {=IF(N18="","",(IFERROR(XLOOKUP($K18,Family,'Product Families'!G:G),"")))} -> 154 | R18: HCS1 | S18: {=IF(R18="","",IFERROR(XLOOKUP(R18,'Product Families'!$A:$A,'Product Families'!$B:$B),""))} -> Hand Crafted Soap Loaves | T18: {=IF(R18="","",(IFERROR(XLOOKUP($R18,Family,'Product Families'!D:D),"")))} -> 21 | U18: {=IF(S18="","",(IFERROR(XLOOKUP($R18,Family,'Product Families'!E:E),"")))} -> 22 | V18: {=IF(T18="","",(IFERROR(XLOOKUP($R18,Family,'Product Families'!F:F),"")))} -> 23 | W18: {=IF(U18="","",(IFERROR(XLOOKUP($R18,Family,'Product Families'!G:G),"")))} -> 24 | Y18: AWEBL | Z18: {=IF(Y18="","",IFERROR(XLOOKUP(Y18,'Product Families'!$A:$A,'Product Families'!$B:$B),""))} -> Essential Oil Blends Boxed | AA18: {=IF(Y18="","",(IFERROR(XLOOKUP($Y18,Family,'Product Families'!D:D),"")))} -> 76 | AB18: {=IF(Z18="","",(IFERROR(XLOOKUP($Y18,Family,'Product Families'!E:E),"")))} -> 78 | AC18: {=IF(AA18="","",(IFERROR(XLOOKUP($Y18,Family,'Product Families'!F:F),"")))} -> 84 | AD18: {=IF(AB18="","",(IFERROR(XLOOKUP($Y18,Family,'Product Families'!G:G),"")))} -> 90 | AF18: RDEO | AG18: {=IF(AF18="","",IFERROR(XLOOKUP(AF18,'Product Families'!$A:$A,'Product Families'!$B:$B),""))} -> Reed Diffusers | AH18: {=IF(AF18="","",(IFERROR(XLOOKUP($AF18,Family,'Product Families'!D:D),"")))} -> 17 | AI18: {=IF(AG18="","",(IFERROR(XLOOKUP($AF18,Family,'Product Families'!E:E),"")))} -> 18 | AJ18: {=IF(AH18="","",(IFERROR(XLOOKUP($AF18,Family,'Product Families'!F:F),"")))} -> 19 | AK18: {=IF(AI18="","",(IFERROR(XLOOKUP($AF18,Family,'Product Families'!G:G),"")))} -> 21
K19: CBFP | L19: {=IF(K19="","",IFERROR(XLOOKUP(K19,'Product Families'!$A:$A,'Product Families'!$B:$B),""))} -> Chakra Bath Fizz - Packing | M19: {=IF(K19="","",(IFERROR(XLOOKUP($K19,Family,'Product Families'!D:D),"")))} -> 81 | N19: {=IF(L19="","",(IFERROR(XLOOKUP($K19,Family,'Product Families'!E:E),"")))} -> 83 | O19: {=IF(M19="","",(IFERROR(XLOOKUP($K19,Family,'Product Families'!F:F),"")))} -> 90 | P19: {=IF(N19="","",(IFERROR(XLOOKUP($K19,Family,'Product Families'!G:G),"")))} -> 96 | R19: HCS2 | S19: {=IF(R19="","",IFERROR(XLOOKUP(R19,'Product Families'!$A:$A,'Product Families'!$B:$B),""))} -> Hand Crafted Soap Loaves 47,49,50,51,52,53,54,55 | T19: {=IF(R19="","",(IFERROR(XLOOKUP($R19,Family,'Product Families'!D:D),"")))} -> 20 | U19: {=IF(S19="","",(IFERROR(XLOOKUP($R19,Family,'Product Families'!E:E),"")))} -> 21 | V19: {=IF(T19="","",(IFERROR(XLOOKUP($R19,Family,'Product Families'!F:F),"")))} -> 22 | W19: {=IF(U19="","",(IFERROR(XLOOKUP($R19,Family,'Product Families'!G:G),"")))} -> 23 | Y19: AWHBL1 | Z19: {=IF(Y19="","",IFERROR(XLOOKUP(Y19,'Product Families'!$A:$A,'Product Families'!$B:$B),""))} -> Luxury Lavender Wheat Bag - 1-6 | AA19: {=IF(Y19="","",(IFERROR(XLOOKUP($Y19,Family,'Product Families'!D:D),"")))} -> 43 | AB19: {=IF(Z19="","",(IFERROR(XLOOKUP($Y19,Family,'Product Families'!E:E),"")))} -> 44 | AC19: {=IF(AA19="","",(IFERROR(XLOOKUP($Y19,Family,'Product Families'!F:F),"")))} -> 48 | AD19: {=IF(AB19="","",(IFERROR(XLOOKUP($Y19,Family,'Product Families'!G:G),"")))} -> 51 | AF19: RDHF | AG19: {=IF(AF19="","",IFERROR(XLOOKUP(AF19,'Product Families'!$A:$A,'Product Families'!$B:$B),""))} -> Reed Diffusers | AH19: {=IF(AF19="","",(IFERROR(XLOOKUP($AF19,Family,'Product Families'!D:D),"")))} -> 17 | AI19: {=IF(AG19="","",(IFERROR(XLOOKUP($AF19,Family,'Product Families'!E:E),"")))} -> 18 | AJ19: {=IF(AH19="","",(IFERROR(XLOOKUP($AF19,Family,'Product Families'!F:F),"")))} -> 19 | AK19: {=IF(AI19="","",(IFERROR(XLOOKUP($AF19,Family,'Product Families'!G:G),"")))} -> 21
C20: : | D20: : | E20: : | K20: CHILLP | L20: {=IF(K20="","",IFERROR(XLOOKUP(K20,'Product Families'!$A:$A,'Product Families'!$B:$B),""))} -> Chill Pill Gift Packs 350g | M20: {=IF(K20="","",(IFERROR(XLOOKUP($K20,Family,'Product Families'!D:D),"")))} -> 8 | N20: {=IF(L20="","",(IFERROR(XLOOKUP($K20,Family,'Product Families'!E:E),"")))} -> 9 | O20: {=IF(M20="","",(IFERROR(XLOOKUP($K20,Family,'Product Families'!F:F),"")))} -> 10 | P20: {=IF(N20="","",(IFERROR(XLOOKUP($K20,Family,'Product Families'!G:G),"")))} -> 11 | R20: HCSP | S20: {=IF(R20="","",IFERROR(XLOOKUP(R20,'Product Families'!$A:$A,'Product Families'!$B:$B),""))} -> Hand Crafted Soap Loaves | T20: {=IF(R20="","",(IFERROR(XLOOKUP($R20,Family,'Product Families'!D:D),"")))} -> 65 | U20: {=IF(S20="","",(IFERROR(XLOOKUP($R20,Family,'Product Families'!E:E),"")))} -> 67 | V20: {=IF(T20="","",(IFERROR(XLOOKUP($R20,Family,'Product Families'!F:F),"")))} -> 72 | W20: {=IF(U20="","",(IFERROR(XLOOKUP($R20,Family,'Product Families'!G:G),"")))} -> 77 | Y20: AWHBL2 | Z20: {=IF(Y20="","",IFERROR(XLOOKUP(Y20,'Product Families'!$A:$A,'Product Families'!$B:$B),""))} -> Luxury Lavender Wheat Bag - 7-12 with Inner | AA20: {=IF(Y20="","",(IFERROR(XLOOKUP($Y20,Family,'Product Families'!D:D),"")))} -> 27 | AB20: {=IF(Z20="","",(IFERROR(XLOOKUP($Y20,Family,'Product Families'!E:E),"")))} -> 28 | AC20: {=IF(AA20="","",(IFERROR(XLOOKUP($Y20,Family,'Product Families'!F:F),"")))} -> 30 | AD20: {=IF(AB20="","",(IFERROR(XLOOKUP($Y20,Family,'Product Families'!G:G),"")))} -> 32 | AF20: SG | AG20: {=IF(AF20="","",IFERROR(XLOOKUP(AF20,'Product Families'!$A:$A,'Product Families'!$B:$B),""))} -> Simmering Granules | AH20: {=IF(AF20="","",(IFERROR(XLOOKUP($AF20,Family,'Product Families'!D:D),"")))} -> 9 | AI20: {=IF(AG20="","",(IFERROR(XLOOKUP($AF20,Family,'Product Families'!E:E),"")))} -> 10 | AJ20: {=IF(AH20="","",(IFERROR(XLOOKUP($AF20,Family,'Product Families'!F:F),"")))} -> 11 | AK20: {=IF(AI20="","",(IFERROR(XLOOKUP($AF20,Family,'Product Families'!G:G),"")))} -> 12
K21: CJBB | L21: {=IF(K21="","",IFERROR(XLOOKUP(K21,'Product Families'!$A:$A,'Product Families'!$B:$B),""))} -> Christmas Bath Bombs - Making | M21: {=IF(K21="","",(IFERROR(XLOOKUP($K21,Family,'Product Families'!D:D),"")))} -> 144 | N21: {=IF(L21="","",(IFERROR(XLOOKUP($K21,Family,'Product Families'!E:E),"")))} -> 148 | O21: {=IF(M21="","",(IFERROR(XLOOKUP($K21,Family,'Product Families'!F:F),"")))} -> 159 | P21: {=IF(N21="","",(IFERROR(XLOOKUP($K21,Family,'Product Families'!G:G),"")))} -> 170 | R21: HHCS | S21: {=IF(R21="","",IFERROR(XLOOKUP(R21,'Product Families'!$A:$A,'Product Families'!$B:$B),""))} -> HHCS - Making | T21: {=IF(R21="","",(IFERROR(XLOOKUP($R21,Family,'Product Families'!D:D),"")))} -> 4 | U21: {=IF(S21="","",(IFERROR(XLOOKUP($R21,Family,'Product Families'!E:E),"")))} -> 5 | V21: {=IF(T21="","",(IFERROR(XLOOKUP($R21,Family,'Product Families'!F:F),"")))} -> 6 | W21: {=IF(U21="","",(IFERROR(XLOOKUP($R21,Family,'Product Families'!G:G),"")))} -> 7 | Y21: AWPO | Z21: {=IF(Y21="","",IFERROR(XLOOKUP(Y21,Family,'Product Families'!$B:$B),""))} -> Ancient Witch Perfume Oil - Single | AA21: {=IF(Y21="","",(IFERROR(XLOOKUP($Y21,Family,'Product Families'!D:D),"")))} -> 54 | AB21: {=IF(Z21="","",(IFERROR(XLOOKUP($Y21,Family,'Product Families'!E:E),"")))} -> 56 | AC21: {=IF(AA21="","",(IFERROR(XLOOKUP($Y21,Family,'Product Families'!F:F),"")))} -> 60 | AD21: {=IF(AB21="","",(IFERROR(XLOOKUP($Y21,Family,'Product Families'!G:G),"")))} -> 64 | AF21: ULFO | AG21: {=IF(AF21="","",IFERROR(XLOOKUP(AF21,'Product Families'!$A:$A,'Product Families'!$B:$B),""))} -> 10ml Fragrance Oils - White Label - Pack of 10 | AH21: {=IF(AF21="","",(IFERROR(XLOOKUP($AF21,Family,'Product Families'!D:D),"")))} -> 20 | AI21: {=IF(AG21="","",(IFERROR(XLOOKUP($AF21,Family,'Product Families'!E:E),"")))} -> 21 | AJ21: {=IF(AH21="","",(IFERROR(XLOOKUP($AF21,Family,'Product Families'!F:F),"")))} -> 23 | AK21: {=IF(AI21="","",(IFERROR(XLOOKUP($AF21,Family,'Product Families'!G:G),"")))} -> 24
C22: : | D22: : | E22: : | K22: CJBBP | L22: {=IF(K22="","",IFERROR(XLOOKUP(K22,'Product Families'!$A:$A,'Product Families'!$B:$B),""))} -> Christmas Bath Bombs - Packing | M22: {=IF(K22="","",(IFERROR(XLOOKUP($K22,Family,'Product Families'!D:D),"")))} -> 34 | N22: {=IF(L22="","",(IFERROR(XLOOKUP($K22,Family,'Product Families'!E:E),"")))} -> 35 | O22: {=IF(M22="","",(IFERROR(XLOOKUP($K22,Family,'Product Families'!F:F),"")))} -> 38 | P22: {=IF(N22="","",(IFERROR(XLOOKUP($K22,Family,'Product Families'!G:G),"")))} -> 41 | R22: HSS | S22: {=IF(R22="","",IFERROR(XLOOKUP(R22,'Product Families'!$A:$A,'Product Families'!$B:$B),""))} -> Happy Scrub Soaps - Making | T22: {=IF(R22="","",(IFERROR(XLOOKUP($R22,Family,'Product Families'!D:D),"")))} -> 162 | U22: {=IF(S22="","",(IFERROR(XLOOKUP($R22,Family,'Product Families'!E:E),"")))} -> 166 | V22: {=IF(T22="","",(IFERROR(XLOOKUP($R22,Family,'Product Families'!F:F),"")))} -> 179 | W22: {=IF(U22="","",(IFERROR(XLOOKUP($R22,Family,'Product Families'!G:G),"")))} -> 192 | Y22: BB | Z22: {=IF(Y22="","",IFERROR(XLOOKUP(Y22,'Product Families'!$A:$A,'Product Families'!$B:$B),""))} -> Body Butters 90g - Make+Pack | AA22: {=IF(Y22="","",(IFERROR(XLOOKUP($Y22,Family,'Product Families'!D:D),"")))} -> 43 | AB22: {=IF(Z22="","",(IFERROR(XLOOKUP($Y22,Family,'Product Families'!E:E),"")))} -> 44 | AC22: {=IF(AA22="","",(IFERROR(XLOOKUP($Y22,Family,'Product Families'!F:F),"")))} -> 48 | AD22: {=IF(AB22="","",(IFERROR(XLOOKUP($Y22,Family,'Product Families'!G:G),"")))} -> 51 | AF22: ZFO | AG22: {=IF(AF22="","",IFERROR(XLOOKUP(AF22,Family,'Product Families'!$B:$B),""))} -> Zodiac Fragrance Oil - 4,7,8,11 | AH22: {=IF(AF22="","",(IFERROR(XLOOKUP($AF22,Family,'Product Families'!D:D),"")))} -> 108 | AI22: {=IF(AG22="","",(IFERROR(XLOOKUP($AF22,Family,'Product Families'!E:E),"")))} -> 111 | AJ22: {=IF(AH22="","",(IFERROR(XLOOKUP($AF22,Family,'Product Families'!F:F),"")))} -> 119 | AK22: {=IF(AI22="","",(IFERROR(XLOOKUP($AF22,Family,'Product Families'!G:G),"")))} -> 128
K23: DONUT | L23: {=IF(K23="","",IFERROR(XLOOKUP(K23,'Product Families'!$A:$A,'Product Families'!$B:$B),""))} -> Donut Shaped Bath Bombs - Making | M23: {=IF(K23="","",(IFERROR(XLOOKUP($K23,Family,'Product Families'!D:D),"")))} -> 173 | N23: {=IF(L23="","",(IFERROR(XLOOKUP($K23,Family,'Product Families'!E:E),"")))} -> 177 | O23: {=IF(M23="","",(IFERROR(XLOOKUP($K23,Family,'Product Families'!F:F),"")))} -> 191 | P23: {=IF(N23="","",(IFERROR(XLOOKUP($K23,Family,'Product Families'!G:G),"")))} -> 205 | R23: HSSP | S23: {=IF(R23="","",IFERROR(XLOOKUP(R23,'Product Families'!$A:$A,'Product Families'!$B:$B),""))} -> Happy Scrub Soaps - Packing | T23: {=IF(R23="","",(IFERROR(XLOOKUP($R23,Family,'Product Families'!D:D),"")))} -> 108 | U23: {=IF(S23="","",(IFERROR(XLOOKUP($R23,Family,'Product Families'!E:E),"")))} -> 111 | V23: {=IF(T23="","",(IFERROR(XLOOKUP($R23,Family,'Product Families'!F:F),"")))} -> 119 | W23: {=IF(U23="","",(IFERROR(XLOOKUP($R23,Family,'Product Families'!G:G),"")))} -> 128 | Y23: BBEO | Z23: {=IF(Y23="","",IFERROR(XLOOKUP(Y23,'Product Families'!$A:$A,'Product Families'!$B:$B),""))} -> Body Butters with Essential Oils | AA23: {=IF(Y23="","",(IFERROR(XLOOKUP($Y23,Family,'Product Families'!D:D),"")))} -> 43 | AB23: {=IF(Z23="","",(IFERROR(XLOOKUP($Y23,Family,'Product Families'!E:E),"")))} -> 44 | AC23: {=IF(AA23="","",(IFERROR(XLOOKUP($Y23,Family,'Product Families'!F:F),"")))} -> 48 | AD23: {=IF(AB23="","",(IFERROR(XLOOKUP($Y23,Family,'Product Families'!G:G),"")))} -> 51 | AF23: ZFOT | AG23: {=IF(AF23="","",IFERROR(XLOOKUP(AF23,Family,'Product Families'!$B:$B),""))} -> Zodiac Fragrance Oil - Tactile Label | AH23: {=IF(AF23="","",(IFERROR(XLOOKUP($AF23,Family,'Product Families'!D:D),"")))} -> 100 | AI23: {=IF(AG23="","",(IFERROR(XLOOKUP($AF23,Family,'Product Families'!E:E),"")))} -> 103 | AJ23: {=IF(AH23="","",(IFERROR(XLOOKUP($AF23,Family,'Product Families'!F:F),"")))} -> 111 | AK23: {=IF(AI23="","",(IFERROR(XLOOKUP($AF23,Family,'Product Families'!G:G),"")))} -> 119
C24: : | D24: : | E24: : | K24: DONUTP | L24: {=IF(K24="","",IFERROR(XLOOKUP(K24,'Product Families'!$A:$A,'Product Families'!$B:$B),""))} -> Donut Shaped Bath Bombs - Packing | M24: {=IF(K24="","",(IFERROR(XLOOKUP($K24,Family,'Product Families'!D:D),"")))} -> 34 | N24: {=IF(L24="","",(IFERROR(XLOOKUP($K24,Family,'Product Families'!E:E),"")))} -> 35 | O24: {=IF(M24="","",(IFERROR(XLOOKUP($K24,Family,'Product Families'!F:F),"")))} -> 38 | P24: {=IF(N24="","",(IFERROR(XLOOKUP($K24,Family,'Product Families'!G:G),"")))} -> 41 | R24: KSOAP | S24: {=IF(R24="","",IFERROR(XLOOKUP(R24,'Product Families'!$A:$A,'Product Families'!$B:$B),""))} -> KSoap | T24: {=IF(R24="","",(IFERROR(XLOOKUP($R24,Family,'Product Families'!D:D),"")))} -> 72 | U24: {=IF(S24="","",(IFERROR(XLOOKUP($R24,Family,'Product Families'!E:E),"")))} -> 74 | V24: {=IF(T24="","",(IFERROR(XLOOKUP($R24,Family,'Product Families'!F:F),"")))} -> 80 | W24: {=IF(U24="","",(IFERROR(XLOOKUP($R24,Family,'Product Families'!G:G),"")))} -> 85 | Y24: BBFO | Z24: {=IF(Y24="","",IFERROR(XLOOKUP(Y24,'Product Families'!$A:$A,'Product Families'!$B:$B),""))} -> Body Butters with Fragrance - Making | AA24: {=IF(Y24="","",(IFERROR(XLOOKUP($Y24,Family,'Product Families'!D:D),"")))} -> 43 | AB24: {=IF(Z24="","",(IFERROR(XLOOKUP($Y24,Family,'Product Families'!E:E),"")))} -> 44 | AC24: {=IF(AA24="","",(IFERROR(XLOOKUP($Y24,Family,'Product Families'!F:F),"")))} -> 48 | AD24: {=IF(AB24="","",(IFERROR(XLOOKUP($Y24,Family,'Product Families'!G:G),"")))} -> 51 | AH24: {=IF(AF24="","",(IFERROR(XLOOKUP($AF24,Family,'Product Families'!D:D),"")))} | AI24: {=IF(AG24="","",(IFERROR(XLOOKUP($AF24,Family,'Product Families'!E:E),"")))} | AJ24: {=IF(AH24="","",(IFERROR(XLOOKUP($AF24,Family,'Product Families'!F:F),"")))} | AK24: {=IF(AI24="","",(IFERROR(XLOOKUP($AF24,Family,'Product Families'!G:G),"")))}
K25: EBB1 | L25: {=IF(K25="","",IFERROR(XLOOKUP(K25,'Product Families'!$A:$A,'Product Families'!$B:$B),""))} -> Making Bath Balls / Tray of 8 / Single Mix | M25: {=IF(K25="","",(IFERROR(XLOOKUP($K25,Family,'Product Families'!D:D),"")))} -> 236 | N25: {=IF(L25="","",(IFERROR(XLOOKUP($K25,Family,'Product Families'!E:E),"")))} -> 242 | O25: {=IF(M25="","",(IFERROR(XLOOKUP($K25,Family,'Product Families'!F:F),"")))} -> 260 | P25: {=IF(N25="","",(IFERROR(XLOOKUP($K25,Family,'Product Families'!G:G),"")))} -> 279 | R25: KSOAPUL | S25: {=IF(R25="","",IFERROR(XLOOKUP(R25,'Product Families'!$A:$A,'Product Families'!$B:$B),""))} -> KSOAPUL | T25: {=IF(R25="","",(IFERROR(XLOOKUP($R25,Family,'Product Families'!D:D),"")))} | U25: {=IF(S25="","",(IFERROR(XLOOKUP($R25,Family,'Product Families'!E:E),"")))} -> 0 | V25: {=IF(T25="","",(IFERROR(XLOOKUP($R25,Family,'Product Families'!F:F),"")))} | W25: {=IF(U25="","",(IFERROR(XLOOKUP($R25,Family,'Product Families'!G:G),"")))} -> 0 | Y25: BBKIT | Z25: {=IF(Y25="","",IFERROR(XLOOKUP(Y25,'Product Families'!$A:$A,'Product Families'!$B:$B),""))} -> Bath Bomb Kits | AA25: {=IF(Y25="","",(IFERROR(XLOOKUP($Y25,Family,'Product Families'!D:D),"")))} -> 8 | AB25: {=IF(Z25="","",(IFERROR(XLOOKUP($Y25,Family,'Product Families'!E:E),"")))} -> 9 | AC25: {=IF(AA25="","",(IFERROR(XLOOKUP($Y25,Family,'Product Families'!F:F),"")))} -> 10 | AD25: {=IF(AB25="","",(IFERROR(XLOOKUP($Y25,Family,'Product Families'!G:G),"")))} -> 11 | AH25: {=IF(AF25="","",(IFERROR(XLOOKUP($AF25,Family,'Product Families'!D:D),"")))} | AI25: {=IF(AG25="","",(IFERROR(XLOOKUP($AF25,Family,'Product Families'!E:E),"")))} | AJ25: {=IF(AH25="","",(IFERROR(XLOOKUP($AF25,Family,'Product Families'!F:F),"")))} | AK25: {=IF(AI25="","",(IFERROR(XLOOKUP($AF25,Family,'Product Families'!G:G),"")))}
C26: : | D26: : | E26: : | K26: EBBP | L26: {=IF(K26="","",IFERROR(XLOOKUP(K26,'Product Families'!$A:$A,'Product Families'!$B:$B),""))} -> Packing Bath Balls - Tray of 8 - Packing | M26: {=IF(K26="","",(IFERROR(XLOOKUP($K26,Family,'Product Families'!D:D),"")))} -> 43 | N26: {=IF(L26="","",(IFERROR(XLOOKUP($K26,Family,'Product Families'!E:E),"")))} -> 44 | O26: {=IF(M26="","",(IFERROR(XLOOKUP($K26,Family,'Product Families'!F:F),"")))} -> 48 | P26: {=IF(N26="","",(IFERROR(XLOOKUP($K26,Family,'Product Families'!G:G),"")))} -> 51 | R26: MELT | S26: {=IF(R26="","",IFERROR(XLOOKUP(R26,'Product Families'!$A:$A,'Product Families'!$B:$B),""))} -> Melt & Pour Soap Kits | T26: {=IF(R26="","",(IFERROR(XLOOKUP($R26,Family,'Product Families'!D:D),"")))} -> 37 | U26: {=IF(S26="","",(IFERROR(XLOOKUP($R26,Family,'Product Families'!E:E),"")))} -> 38 | V26: {=IF(T26="","",(IFERROR(XLOOKUP($R26,Family,'Product Families'!F:F),"")))} -> 41 | W26: {=IF(U26="","",(IFERROR(XLOOKUP($R26,Family,'Product Families'!G:G),"")))} -> 44 | Y26: BBM | Z26: {=IF(Y26="","",IFERROR(XLOOKUP(Y26,'Product Families'!$A:$A,'Product Families'!$B:$B),""))} -> Body Butters 90g - Pouring | AA26: {=IF(Y26="","",(IFERROR(XLOOKUP($Y26,Family,'Product Families'!D:D),"")))} -> 130 | AB26: {=IF(Z26="","",(IFERROR(XLOOKUP($Y26,Family,'Product Families'!E:E),"")))} -> 133 | AC26: {=IF(AA26="","",(IFERROR(XLOOKUP($Y26,Family,'Product Families'!F:F),"")))} -> 144 | AD26: {=IF(AB26="","",(IFERROR(XLOOKUP($Y26,Family,'Product Families'!G:G),"")))} -> 154 | AH26: {=IF(AF26="","",(IFERROR(XLOOKUP($AF26,Family,'Product Families'!D:D),"")))} | AI26: {=IF(AG26="","",(IFERROR(XLOOKUP($AF26,Family,'Product Families'!E:E),"")))} | AJ26: {=IF(AH26="","",(IFERROR(XLOOKUP($AF26,Family,'Product Families'!F:F),"")))} | AK26: {=IF(AI26="","",(IFERROR(XLOOKUP($AF26,Family,'Product Families'!G:G),"")))}
K27: EBBS | L27: {=IF(K27="","",IFERROR(XLOOKUP(K27,'Product Families'!$A:$A,'Product Families'!$B:$B),""))} -> Essential Bath Bomb Set | M27: {=IF(K27="","",(IFERROR(XLOOKUP($K27,Family,'Product Families'!D:D),"")))} -> 59 | N27: {=IF(L27="","",(IFERROR(XLOOKUP($K27,Family,'Product Families'!E:E),"")))} -> 61 | O27: {=IF(M27="","",(IFERROR(XLOOKUP($K27,Family,'Product Families'!F:F),"")))} -> 65 | P27: {=IF(N27="","",(IFERROR(XLOOKUP($K27,Family,'Product Families'!G:G),"")))} -> 70 | R27: MELTP | S27: {=IF(R27="","",IFERROR(XLOOKUP(R27,'Product Families'!$A:$A,'Product Families'!$B:$B),""))} -> Melt & Pour Soap Kits - Packing | T27: {=IF(R27="","",(IFERROR(XLOOKUP($R27,Family,'Product Families'!D:D),"")))} -> 65 | U27: {=IF(S27="","",(IFERROR(XLOOKUP($R27,Family,'Product Families'!E:E),"")))} -> 67 | V27: {=IF(T27="","",(IFERROR(XLOOKUP($R27,Family,'Product Families'!F:F),"")))} -> 72 | W27: {=IF(U27="","",(IFERROR(XLOOKUP($R27,Family,'Product Families'!G:G),"")))} -> 77 | Y27: BBP | Z27: {=IF(Y27="","",IFERROR(XLOOKUP(Y27,'Product Families'!$A:$A,'Product Families'!$B:$B),""))} -> Body Butters 90g - Packing | AA27: {=IF(Y27="","",(IFERROR(XLOOKUP($Y27,Family,'Product Families'!D:D),"")))} -> 65 | AB27: {=IF(Z27="","",(IFERROR(XLOOKUP($Y27,Family,'Product Families'!E:E),"")))} -> 67 | AC27: {=IF(AA27="","",(IFERROR(XLOOKUP($Y27,Family,'Product Families'!F:F),"")))} -> 72 | AD27: {=IF(AB27="","",(IFERROR(XLOOKUP($Y27,Family,'Product Families'!G:G),"")))} -> 77 | AG27: {=IF(AF27="","",IFERROR(XLOOKUP(AF27,Family,'Product Families'!$B:$B),""))} | AH27: {=IF(AF27="","",(IFERROR(XLOOKUP($AF27,Family,'Product Families'!D:D),"")))} | AI27: {=IF(AG27="","",(IFERROR(XLOOKUP($AF27,Family,'Product Families'!E:E),"")))} | AJ27: {=IF(AH27="","",(IFERROR(XLOOKUP($AF27,Family,'Product Families'!F:F),"")))} | AK27: {=IF(AI27="","",(IFERROR(XLOOKUP($AF27,Family,'Product Families'!G:G),"")))}
